Workbook

Sheet Geração_Dezembro
A1: Mês | B1: UC | C1: Usina BC | D1: SPE | E1: Projeto | F1: Geração Plataforma MWh | G1: Geração Local MWh | H1: Previsão | I1: Atingimento %
A2: 12 | B2: 10031214850 | C2: UFV Araçu I | D2: BC Energia Araçu I.I | E2: BC Araçu I | G2: =(18301.5+18559+18704.1+18474.3+17544.2+16254.4+18781.5)/1000 -> 126.619 | H2: 135.1 | I2: =IF(G2<>0,G2/H2,F2/H2) -> 0.93722428
A3: 12 | B3: 10031394475 | C3: UFV Araçu II | D3: BC Energia Araçu II.II | E3: BC Araçu II | F3: 42.58 | H3: 36.62 | I3: =IF(G3<>0,G3/H3,F3/H3) -> 1.1627526
A4: 12 | B4: 10031394572 | C4: UFV Araçu III | D4: BC Energia Araçu II.III | E4: BC Araçu II | F4: 38.21 | H4: 43.16 | I4: =IF(G4<>0,G4/H4,F4/H4) -> 0.88531047
A5: 12 | B5: 10031394211 | C5: UFV Araçu IV | D5: BC Energia Araçu II.IV | E5: BC Araçu II | F5: 52.18 | H5: 78.33 | I5: =IF(G5<>0,G5/H5,F5/H5) -> 0.66615601
A6: 12 | B6: 10031394599 | C6: UFV Araçu V | D6: BC Energia Araçu II.V | E6: BC Araçu II | F6: 77.08 | H6: 87.5 | I6: =IF(G6<>0,G6/H6,F6/H6) -> 0.88091429
A7: 12 | B7: 10035044444 | C7: UFV Araçu VI | D7: BC Energia Araçu III.VI | E7: BC Araçu III | F7: 19.14 | H7: 20.47 | I7: =IF(G7<>0,G7/H7,F7/H7) -> 0.93502687
A8: 12 | B8: 10035044363 | C8: UFV Araçu VII | D8: BC Energia Araçu III.VII | E8: BC Araçu III | F8: 18.75 | H8: 20.35 | I8: =IF(G8<>0,G8/H8,F8/H8) -> 0.92137592
A9: 12 | B9: 10035302079 | C9: UFV Araçu VIII | D9: BC Energia Araçu IV.VIII | E9: BC Araçu IV | F9: 45.71 | H9: 53.49 | I9: =IF(G9<>0,G9/H9,F9/H9) -> 0.85455225
A10: 12 | B10: 6/4136603-0 | C10: UFV Barra do Garças I | D10: BC Energia Barra das Garças I | E10: BC Barra do Garças | F10: 12.03 | H10: 11.94 | I10: =IF(G10<>0,G10/H10,F10/H10) -> 1.0075377
A11: 12 | B11: 6/4136542-0 | C11: UFV Barra do Garças II | D11: BC Energia Barra das Garças II | E11: BC Barra do Garças | F11: 45.57 | H11: 45.27 | I11: =IF(G11<>0,G11/H11,F11/H11) -> 1.0066269
A12: 12 | B12: 6/4136538-8 | C12: UFV Barra do Garças III | D12: BC Energia Barra das Garças III | E12: BC Barra do Garças | F12: 45.36 | H12: 46.02 | I12: =IF(G12<>0,G12/H12,F12/H12) -> 0.98565841
A13: 12 | B13: 10031246905 | C13: UFV Bom Sucesso | D13: BC Energia Bom Sucesso I | E13: BC Bom Sucesso | F13: 95.25 | G13: 96.64 | H13: 100.8 | I13: =IF(G13<>0,G13/H13,F13/H13) -> 0.95873016
A14: 12 | B14: 10035461975 | C14: UFV Caiapônia I | D14: BC Energia Caiapônia I.I | E14: BC Caiapônia I | F14: 81.63 | H14: 91.2 | I14: =IF(G14<>0,G14/H14,F14/H14) -> 0.89506579
A15: 12 | B15: 10035461983 | C15: UFV Caiapônia II | D15: BC Energia Caiapônia I.II | E15: BC Caiapônia I | F15: 68.91 | H15: 77.81 | I15: =IF(G15<>0,G15/H15,F15/H15) -> 0.88561882
A16: 12 | B16: 10035505336 | C16: UFV Caiapônia III | D16: BC Energia Caiapônia I.III | E16: BC Caiapônia I | F16: 51.45 | H16: 56.31 | I16: =IF(G16<>0,G16/H16,F16/H16) -> 0.91369206
A17: 12 | B17: 10035462122 | C17: UFV Caiapônia IV | D17: BC Energia Caiapônia I.IV | E17: BC Caiapônia I | F17: 40.09 | H17: 42.99 | I17: =IF(G17<>0,G17/H17,F17/H17) -> 0.93254245
A18: 12 | B18: 10035462130 | C18: UFV Caiapônia V | D18: BC Energia Caiapônia I.V | E18: BC Caiapônia I | F18: 42.28 | H18: 48.32 | I18: =IF(G18<>0,G18/H18,F18/H18) -> 0.875
A19: 12 | B19: 10035462084 | C19: UFV Caiaponia VI | D19: BC Energia Caiapônia II.VI | E19: BC Caiapônia II | F19: 182.71 | H19: 232.78 | I19: =IF(G19<>0,G19/H19,F19/H19) -> 0.7849042
A20: 12 | B20: 10035462114 | C20: UFV Caiaponia VII | D20: BC Energia Caiapônia II.VII | E20: BC Caiapônia II | F20: 177.1 | H20: 222.66 | I20: =IF(G20<>0,G20/H20,F20/H20) -> 0.7953831
A21: 12 | B21: 10035462262 | C21: UFV Caiaponia VIII | D21: BC Energia Caiapônia II.VIII | E21: BC Caiapônia II | F21: 179.44 | H21: 230.76 | I21: =IF(G21<>0,G21/H21,F21/H21) -> 0.77760444
A22: 12 | B22: 10035977122 | C22: UFV Palmeiras de Goiás 1.1 | D22: BC Energia Camarão - Palmeiras de Goiais I.I | E22: BC Camarão I - Palmeiras de Goiás I | F22: 195.04 | H22: 252.1 | I22: =IF(G22<>0,G22/H22,F22/H22) -> 0.77366125
A23: 12 | B23: 10035977130 | C23: UFV Palmeiras de Goiás 1.2 | D23: BC Energia Camarão - Palmeiras de Goiais I.II | E23: BC Camarão I - Palmeiras de Goiás I | F23: 200.42 | H23: 251.3 | I23: =IF(G23<>0,G23/H23,F23/H23) -> 0.79753283
A24: 12 | B24: 10035977149 | C24: UFV Palmeiras de Goiás 1.3 | D24: BC Energia Camarão - Palmeiras de Goiais I.III | E24: BC Camarão I - Palmeiras de Goiás I | F24: 200.02 | H24: 251.2 | I24: =IF(G24<>0,G24/H24,F24/H24) -> 0.79625796
A25: 12 | B25: 10035977157 | C25: UFV Palmeiras de Goiás 1.4 | D25: BC Energia Camarão - Palmeiras de Goiais I.IV | E25: BC Camarão I - Palmeiras de Goiás I | F25: 200.34 | H25: 250.8 | I25: =IF(G25<>0,G25/H25,F25/H25) -> 0.79880383
... A41: 12 | B41: 10035156609 | C41: UFV Panamá VII | D41: BC Energia Panamá I.VII | E41: BC Panamá I | F41: 9.64 | H41: 9.25 | I41: =IF(G41<>0,G41/H41,F41/H41) -> 1.0421622
A42: 12 | B42: 2353016-2 | C42: UFV Paranoá I | D42: BC Energia Paranoá I.I | E42: BC Paranoá I | F42: 85.92 | H42: 88.8 | I42: =IF(G42<>0,G42/H42,F42/H42) -> 0.96756757
A43: 12 | B43: 2352648-3 | C43: UFV Paranoá II | D43: BC Energia Paranoá I.II | E43: BC Paranoá I | F43: 45 | H43: 48.92 | I43: =IF(G43<>0,G43/H43,F43/H43) -> 0.91986917
A44: 12 | B44: 2353023-5 | C44: UFV Paranoá III | D44: BC Energia Paranoá I.III | E44: BC Paranoá I | F44: 19.02 | H44: 53.63 | I44: =IF(G44<>0,G44/H44,F44/H44) -> 0.35465225
A45: 12 | B45: 2346023-7 | C45: UFV Paranoá IV | D45: BC Energia Paranoá I.IV | E45: BC Paranoá I | F45: 59.93 | H45: 61.45 | I45: =IF(G45<>0,G45/H45,F45/H45) -> 0.97526444
A46: 12 | B46: 2346009-1 | C46: UFV Paranoá V | D46: BC Energia Paranoá I.V | E46: BC Paranoá I | F46: 26.65 | H46: 27.47 | I46: =IF(G46<>0,G46/H46,F46/H46) -> 0.97014925
A47: 12 | B47: 2345997-2 | C47: UFV Paranoá VI | D47: BC Energia Paranoá I.VI | E47: BC Paranoá I | F47: 27.12 | H47: 27.47 | I47: =IF(G47<>0,G47/H47,F47/H47) -> 0.98725883
A48: 12 | B48: 2345992-1 | C48: UFV Paranoá VII | D48: BC Energia Paranoá I.VII | E48: BC Paranoá I | F48: 32.6 | H48: 62.33 | I48: =IF(G48<>0,G48/H48,F48/H48) -> 0.52302262
A49: 12 | B49: 2352661-0 | C49: UFV Paranoá VIII | D49: BC Energia Paranoá I.VIII | E49: BC Paranoá I | F49: 28.34 | H49: 29.29 | I49: =IF(G49<>0,G49/H49,F49/H49) -> 0.96756572
A50: 12 | B50: 10029355760 | C50: UFV Rio Bonito 1 | D50: BC Energia Rio Bonito I.I | E50: BC Rio Bonito I | F50: 160.13 | H50: 159.8 | I50: =IF(G50<>0,G50/H50,F50/H50) -> 1.0020651
A51: 12 | B51: 10035716108 | C51: UFV Rio Bonito 2 | D51: BC Energia Rio Bonito II.II | E51: BC Rio Bonito II | F51: 50.52 | H51: 54.99 | I51: =IF(G51<>0,G51/H51,F51/H51) -> 0.91871249
A52: 12 | B52: 10029848863 | C52: UFV Rio Monte I | D52: BC Energia Rio Monte I.I | E52: BC Rio Monte I | F52: 11.87 | H52: 13.69 | I52: =IF(G52<>0,G52/H52,F52/H52) -> 0.86705625
A53: 12 | B53: 10029848855 | C53: UFV Rio Monte II | D53: BC Energia Rio Monte I.II | E53: BC Rio Monte I | F53: 51.68 | H53: 55.75 | I53: =IF(G53<>0,G53/H53,F53/H53) -> 0.92699552
A54: 12 | B54: 10029848820 | C54: UFV Rio Monte III | D54: BC Energia Rio Monte I.III | E54: BC Rio Monte I | F54: 90.84 | H54: 102.2 | I54: =IF(G54<>0,G54/H54,F54/H54) -> 0.8888454
A55: 12 | B55: 3014365852 | C55: UFV Varjão de Minas I | D55: BC Energia Varjão de Minas I.I | E55: BC Varjão de Minas I | F55: 202.31 | H55: 233.1 | I55: =IF(G55<>0,G55/H55,F55/H55) -> 0.86791077
A56: 12 | B56: 3014365880 | C56: UFV Varjão de Minas II | D56: BC Energia Varjão de Minas I.II | E56: BC Varjão de Minas I | F56: 203.91 | H56: 232.3 | I56: =IF(G56<>0,G56/H56,F56/H56) -> 0.87778734
A57: 12 | B57: 3014365849 | C57: UFV Varjão de Minas III | D57: BC Energia Varjão de Minas I.III | E57: BC Varjão de Minas I | F57: 88.73 | H57: 110.1 | I57: =IF(G57<>0,G57/H57,F57/H57) -> 0.80590372
A58: 12 | B58: 3014367769 | C58: UFV Varjão de Minas IV | D58: BC Energia Varjão de Minas II.IV | E58: BC Varjão de Minas II | F58: 195.92 | H58: 229.1 | I58: =IF(G58<>0,G58/H58,F58/H58) -> 0.85517241
A59: 12 | B59: 3014367806 | C59: UFV Varjão de Minas V | D59: BC Energia Varjão de Minas II.V | E59: BC Varjão de Minas II | F59: 205.36 | H59: 230.5 | I59: =IF(G59<>0,G59/H59,F59/H59) -> 0.89093275
A60: 12 | B60: 3014367812 | C60: UFV Varjão de Minas VI | D60: BC Energia Varjão de Minas II.VI | E60: BC Varjão de Minas II | F60: 101.23 | H60: 110.1 | I60: =IF(G60<>0,G60/H60,F60/H60) -> 0.91943688
A61: 12 | B61: 3014367788 | C61: UFV Vazante I | D61: BC Energia Vazante I.I | E61: BC Vazante I | F61: 189.53 | H61: 217.9 | I61: =IF(G61<>0,G61/H61,F61/H61) -> 0.86980266
... A89: 12 | B89: 834669424 | C89: UFV Araguatins VI | D89: BC Energia Araguatins II.III | E89: BC Energia Araguatins II | F89: 85.78 | H89: 92.2 | I89: =IF(G89<>0,G89/H89,F89/H89) -> 0.93036876
A90: 12 | C90: UFV Ibiuna I | D90: BC Energia Ibiuna I.I | E90: BC Energia Ibiuna 1.1 | F90: 44.4 | H90: 125.68 | I90: =IF(G90<>0,G90/H90,F90/H90) -> 0.35327817
A91: 12 | C91: UFV Ibiuna II | D91: BC Energia Ibiuna I.II | E91: BC Energia Ibiuna 1.2 | F91: 50.47 | H91: 125.68 | I91: =IF(G91<>0,G91/H91,F91/H91) -> 0.40157543
A92: Total | F92: =SUM(F2:F91) -> 9296.49 | G92: =SUM(F14:F91,G13,F3:F12,G2) -> 9424.499 | H92: =SUM(H2:H91) -> 11617.9 | I92: =IF(G92<>0,G92/H92,F92/H92) -> 0.81120504

Sheet Março 2026
A1: UC | B1: UFV | C1: Tag | D1: Início Real do Evento | E1: Início | F1: Fim | G1: Duração | H1: Estado Operativo | I1: Condição Operativa | J1: Origem | K1: Equipamento | L1: Causa | M1: Causas Padrão | N1: Resolução | O1: Observação | P1: Concat - duplicata | Q1: Combinação
B2: BC Aracu5.2 | C2: Inverter(MBUS-1) | D2: 46027.385 | E2: 46082 | F2: 46094.469 | G2: =+F2-E2 -> 12.46875 | H2: DEM | J2: TRF | K2: Transformador | L2: Inversor 1 apresentou falha. Ao realizar a análise em campo, verificou-se curto circuito em uma das fases do trafo. | M2: Falha Inversor | N2: Prestador de Serviço O&M | O2: Identificado no sistema desequilibrio de fase, ao fazer a inspeção o mantenedor identificou curto circuito no trafo, o mesmo fez as manobras e desenergizou a UFV. Transformador foi coletado e encaminhado para garantia. Após retorno de garantia, transformador foi instalado e comissionado novamente. A normalização da geração se deu em 16/03. | P2: =_xlfn.CONCAT(B2,C2,D2,E2,F2) -> BC Aracu5.2Inverter(MBUS-1)46027,38541666674608246094,46875 | Q2: =_xlfn.CONCAT(H2,I2,J2) -> DEMTRF
B3: BC Formoso2.1 | C3: Inverter(MBUS-12) | D3: 46082.153 | E3: 46082.153 | F3: 46083.34 | G3: =+F3-E3 -> 1.1875 | H3: DAU | J3: RDE | K3: =_xlfn.XLOOKUP(J3,REF!$D$2:$D$12,REF!$E$2:$E$12) -> Rede | L3: Queda de rede da concessionária. | M3: Falha Rede | N3: Distribuidora | O3: Devido a uma falha no nobreak, não foi possível a atuação do relé. Foi realizada uma inspeção visual, não sendo identificada nenhuma anomalia. Em seguida, foi efetuado o rearme da usina. | P3: =_xlfn.CONCAT(B3,C3,D3,E3,F3) -> BC Formoso2.1Inverter(MBUS-12)46082,152777777846082,152777777846083,3402777778 | Q3: =_xlfn.CONCAT(H3,I3,J3) -> DAURDE
B4: BC Formoso2.1 | C4: Inverter(MBUS-14) | D4: 46082.153 | E4: 46082.153 | F4: 46083.34 | G4: =+F4-E4 -> 1.1875 | H4: DAU | J4: RDE | K4: =_xlfn.XLOOKUP(J4,REF!$D$2:$D$12,REF!$E$2:$E$12) -> Rede | L4: Queda de rede da concessionária. | M4: Falha Rede | N4: Distribuidora | O4: Devido a uma falha no nobreak, não foi possível a atuação do relé. Foi realizada uma inspeção visual, não sendo identificada nenhuma anomalia. Em seguida, foi efetuado o rearme da usina. | P4: =_xlfn.CONCAT(B4,C4,D4,E4,F4) -> BC Formoso2.1Inverter(MBUS-14)46082,152777777846082,152777777846083,3402777778 | Q4: =_xlfn.CONCAT(H4,I4,J4) -> DAURDE
B5: BC Formoso2.1 | C5: Inverter(MBUS-13) | D5: 46082.153 | E5: 46082.153 | F5: 46083.34 | G5: =+F5-E5 -> 1.1875 | H5: DAU | J5: RDE | K5: =_xlfn.XLOOKUP(J5,REF!$D$2:$D$12,REF!$E$2:$E$12) -> Rede | L5: Queda de rede da concessionária. | M5: Falha Rede | N5: Distribuidora | O5: Devido a uma falha no nobreak, não foi possível a atuação do relé. Foi realizada uma inspeção visual, não sendo identificada nenhuma anomalia. Em seguida, foi efetuado o rearme da usina. | P5: =_xlfn.CONCAT(B5,C5,D5,E5,F5) -> BC Formoso2.1Inverter(MBUS-13)46082,152777777846082,152777777846083,3402777778 | Q5: =_xlfn.CONCAT(H5,I5,J5) -> DAURDE
B6: BC Formoso2.1 | C6: Inverter(MBUS-1) | D6: 46082.153 | E6: 46082.153 | F6: 46083.34 | G6: =+F6-E6 -> 1.1875 | H6: DAU | J6: RDE | K6: =_xlfn.XLOOKUP(J6,REF!$D$2:$D$12,REF!$E$2:$E$12) -> Rede | L6: Queda de rede da concessionária. | M6: Falha Rede | N6: Distribuidora | O6: Devido a uma falha no nobreak, não foi possível a atuação do relé. Foi realizada uma inspeção visual, não sendo identificada nenhuma anomalia. Em seguida, foi efetuado o rearme da usina. | P6: =_xlfn.CONCAT(B6,C6,D6,E6,F6) -> BC Formoso2.1Inverter(MBUS-1)46082,152777777846082,152777777846083,3402777778 | Q6: =_xlfn.CONCAT(H6,I6,J6) -> DAURDE
B7: BC Formoso2.2 | C7: Inverter(MBUS-14) | D7: 46082.306 | E7: 46082.306 | F7: 46084.342 | G7: =+F7-E7 -> 2.0361111 | H7: DAU | J7: RDE | K7: =_xlfn.XLOOKUP(J7,REF!$D$2:$D$12,REF!$E$2:$E$12) -> Rede | L7: Queda de rede da concessionária. | M7: Falha Rede | N7: Distribuidora | O7: Após a realização de uma inspeção visual, não foram identificadas anomalias no sistema. Em seguida, foi efetuado o reset do relé, restabelecendo a operação normal da usina. | P7: =_xlfn.CONCAT(B7,C7,D7,E7,F7) -> BC Formoso2.2Inverter(MBUS-14)46082,305555555646082,305555555646084,3416666667 | Q7: =_xlfn.CONCAT(H7,I7,J7) -> DAURDE
B8: BC Formoso2.2 | C8: Inverter(MBUS-13) | D8: 46082.306 | E8: 46082.306 | F8: 46084.342 | G8: =+F8-E8 -> 2.0361111 | H8: DAU | J8: RDE | K8: =_xlfn.XLOOKUP(J8,REF!$D$2:$D$12,REF!$E$2:$E$12) -> Rede | L8: Queda de rede da concessionária. | M8: Falha Rede | N8: Distribuidora | O8: Após a realização de uma inspeção visual, não foram identificadas anomalias no sistema. Em seguida, foi efetuado o reset do relé, restabelecendo a operação normal da usina. | P8: =_xlfn.CONCAT(B8,C8,D8,E8,F8) -> BC Formoso2.2Inverter(MBUS-13)46082,305555555646082,305555555646084,3416666667 | Q8: =_xlfn.CONCAT(H8,I8,J8) -> DAURDE
B9: BC Formoso2.2 | C9: Inverter(MBUS-12) | D9: 46082.306 | E9: 46082.306 | F9: 46084.342 | G9: =+F9-E9 -> 2.0361111 | H9: DAU | J9: RDE | K9: =_xlfn.XLOOKUP(J9,REF!$D$2:$D$12,REF!$E$2:$E$12) -> Rede | L9: Queda de rede da concessionária. | M9: Falha Rede | N9: Distribuidora | O9: Após a realização de uma inspeção visual, não foram identificadas anomalias no sistema. Em seguida, foi efetuado o reset do relé, restabelecendo a operação normal da usina. | P9: =_xlfn.CONCAT(B9,C9,D9,E9,F9) -> BC Formoso2.2Inverter(MBUS-12)46082,305555555646082,305555555646084,3416666667 | Q9: =_xlfn.CONCAT(H9,I9,J9) -> DAURDE
B10: BC Formoso2.2 | C10: Inverter(MBUS-1) | D10: 46082.306 | E10: 46082.306 | F10: 46084.342 | G10: =+F10-E10 -> 2.0361111 | H10: DAU | J10: RDE | K10: =_xlfn.XLOOKUP(J10,REF!$D$2:$D$12,REF!$E$2:$E$12) -> Rede | L10: Queda de rede da concessionária. | M10: Falha Rede | N10: Distribuidora | O10: Após a realização de uma inspeção visual, não foram identificadas anomalias no sistema. Em seguida, foi efetuado o reset do relé, restabelecendo a operação normal da usina. | P10: =_xlfn.CONCAT(B10,C10,D10,E10,F10) -> BC Formoso2.2Inverter(MBUS-1)46082,305555555646082,305555555646084,3416666667 | Q10: =_xlfn.CONCAT(H10,I10,J10) -> DAURDE
B11: BC Bom Sucesso | C11: SG60KTL | D11: 46082.968 | E11: 46082.968 | F11: 46083.351 | G11: =+F11-E11 -> 0.38263889 | H11: LIG | I11: RFO | J11: INT | K11: =_xlfn.XLOOKUP(J11,REF!$D$2:$D$12,REF!$E$2:$E$12) -> Internet | L11: Indisponibilidade de comunicação devido a problema no provedor de internet. | M11: Conexão c/ Internet | N11: Provedora de Internet | O11: Foi realizada inspeção visual no sistema, não sendo identificadas anomalias. Após a normalização do serviço de internet, a comunicação foi restabelecida e a usina voltou a operar normalmente. | P11: =_xlfn.CONCAT(B11,C11,D11,E11,F11) -> BC Bom SucessoSG60KTL46082,968055555646082,968055555646083,3506944444 | Q11: =_xlfn.CONCAT(H11,I11,J11) -> LIGRFOINT
B12: BC Bom Sucesso | C12: I | D12: 46082.968 | E12: 46082.968 | F12: 46083.351 | G12: =+F12-E12 -> 0.38263889 | H12: LIG | I12: RFO | J12: INT | K12: =_xlfn.XLOOKUP(J12,REF!$D$2:$D$12,REF!$E$2:$E$12) -> Internet | L12: Indisponibilidade de comunicação devido a problema no provedor de internet. | M12: Conexão c/ Internet | N12: Provedora de Internet | O12: Foi realizada inspeção visual no sistema, não sendo identificadas anomalias. Após a normalização do serviço de internet, a comunicação foi restabelecida e a usina voltou a operar normalmente. | P12: =_xlfn.CONCAT(B12,C12,D12,E12,F12) -> BC Bom SucessoI46082,968055555646082,968055555646083,3506944444 | Q12: =_xlfn.CONCAT(H12,I12,J12) -> LIGRFOINT
B13: BC Bom Sucesso | C13: G | D13: 46082.968 | E13: 46082.968 | F13: 46083.351 | G13: =+F13-E13 -> 0.38263889 | H13: LIG | I13: RFO | J13: INT | K13: =_xlfn.XLOOKUP(J13,REF!$D$2:$D$12,REF!$E$2:$E$12) -> Internet | L13: Indisponibilidade de comunicação devido a problema no provedor de internet. | M13: Conexão c/ Internet | N13: Provedora de Internet | O13: Foi realizada inspeção visual no sistema, não sendo identificadas anomalias. Após a normalização do serviço de internet, a comunicação foi restabelecida e a usina voltou a operar normalmente. | P13: =_xlfn.CONCAT(B13,C13,D13,E13,F13) -> BC Bom SucessoG46082,968055555646082,968055555646083,3506944444 | Q13: =_xlfn.CONCAT(H13,I13,J13) -> LIGRFOINT
B14: BC Bom Sucesso | C14: K | D14: 46082.968 | E14: 46082.968 | F14: 46083.351 | G14: =+F14-E14 -> 0.38263889 | H14: LIG | I14: RFO | J14: INT | K14: =_xlfn.XLOOKUP(J14,REF!$D$2:$D$12,REF!$E$2:$E$12) -> Internet | L14: Indisponibilidade de comunicação devido a problema no provedor de internet. | M14: Conexão c/ Internet | N14: Provedora de Internet | O14: Foi realizada inspeção visual no sistema, não sendo identificadas anomalias. Após a normalização do serviço de internet, a comunicação foi restabelecida e a usina voltou a operar normalmente. | P14: =_xlfn.CONCAT(B14,C14,D14,E14,F14) -> BC Bom SucessoK46082,968055555646082,968055555646083,3506944444 | Q14: =_xlfn.CONCAT(H14,I14,J14) -> LIGRFOINT
B15: BC Bom Sucesso | C15: H | D15: 46082.968 | E15: 46082.968 | F15: 46083.351 | G15: =+F15-E15 -> 0.38263889 | H15: LIG | I15: RFO | J15: INT | K15: =_xlfn.XLOOKUP(J15,REF!$D$2:$D$12,REF!$E$2:$E$12) -> Internet | L15: Indisponibilidade de comunicação devido a problema no provedor de internet. | M15: Conexão c/ Internet | N15: Provedora de Internet | O15: Foi realizada inspeção visual no sistema, não sendo identificadas anomalias. Após a normalização do serviço de internet, a comunicação foi restabelecida e a usina voltou a operar normalmente. | P15: =_xlfn.CONCAT(B15,C15,D15,E15,F15) -> BC Bom SucessoH46082,968055555646082,968055555646083,3506944444 | Q15: =_xlfn.CONCAT(H15,I15,J15) -> LIGRFOINT
B16: BC Bom Sucesso | C16: F | D16: 46082.968 | E16: 46082.968 | F16: 46083.351 | G16: =+F16-E16 -> 0.38263889 | H16: LIG | I16: RFO | J16: INT | K16: =_xlfn.XLOOKUP(J16,REF!$D$2:$D$12,REF!$E$2:$E$12) -> Internet | L16: Indisponibilidade de comunicação devido a problema no provedor de internet. | M16: Conexão c/ Internet | N16: Provedora de Internet | O16: Foi realizada inspeção visual no sistema, não sendo identificadas anomalias. Após a normalização do serviço de internet, a comunicação foi restabelecida e a usina voltou a operar normalmente. | P16: =_xlfn.CONCAT(B16,C16,D16,E16,F16) -> BC Bom SucessoF46082,968055555646082,968055555646083,3506944444 | Q16: =_xlfn.CONCAT(H16,I16,J16) -> LIGRFOINT
B17: BC Bom Sucesso | C17: D | D17: 46082.968 | E17: 46082.968 | F17: 46083.351 | G17: =+F17-E17 -> 0.38263889 | H17: LIG | I17: RFO | J17: INT | K17: =_xlfn.XLOOKUP(J17,REF!$D$2:$D$12,REF!$E$2:$E$12) -> Internet | L17: Indisponibilidade de comunicação devido a problema no provedor de internet. | M17: Conexão c/ Internet | N17: Provedora de Internet | O17: Foi realizada inspeção visual no sistema, não sendo identificadas anomalias. Após a normalização do serviço de internet, a comunicação foi restabelecida e a usina voltou a operar normalmente. | P17: =_xlfn.CONCAT(B17,C17,D17,E17,F17) -> BC Bom SucessoD46082,968055555646082,968055555646083,3506944444 | Q17: =_xlfn.CONCAT(H17,I17,J17) -> LIGRFOINT
B18: BC Bom Sucesso | C18: E | D18: 46082.968 | E18: 46082.968 | F18: 46083.351 | G18: =+F18-E18 -> 0.38263889 | H18: LIG | I18: RFO | J18: INT | K18: =_xlfn.XLOOKUP(J18,REF!$D$2:$D$12,REF!$E$2:$E$12) -> Internet | L18: Indisponibilidade de comunicação devido a problema no provedor de internet. | M18: Conexão c/ Internet | N18: Provedora de Internet | O18: Foi realizada inspeção visual no sistema, não sendo identificadas anomalias. Após a normalização do serviço de internet, a comunicação foi restabelecida e a usina voltou a operar normalmente. | P18: =_xlfn.CONCAT(B18,C18,D18,E18,F18) -> BC Bom SucessoE46082,968055555646082,968055555646083,3506944444 | Q18: =_xlfn.CONCAT(H18,I18,J18) -> LIGRFOINT
B19: BC Bom Sucesso | C19: C | D19: 46082.968 | E19: 46082.968 | F19: 46083.351 | G19: =+F19-E19 -> 0.38263889 | H19: LIG | I19: RFO | J19: INT | K19: =_xlfn.XLOOKUP(J19,REF!$D$2:$D$12,REF!$E$2:$E$12) -> Internet | L19: Indisponibilidade de comunicação devido a problema no provedor de internet. | M19: Conexão c/ Internet | N19: Provedora de Internet | O19: Foi realizada inspeção visual no sistema, não sendo identificadas anomalias. Após a normalização do serviço de internet, a comunicação foi restabelecida e a usina voltou a operar normalmente. | P19: =_xlfn.CONCAT(B19,C19,D19,E19,F19) -> BC Bom SucessoC46082,968055555646082,968055555646083,3506944444 | Q19: =_xlfn.CONCAT(H19,I19,J19) -> LIGRFOINT
B20: BC Bom Sucesso | C20: B | D20: 46082.968 | E20: 46082.968 | F20: 46083.351 | G20: =+F20-E20 -> 0.38263889 | H20: LIG | I20: RFO | J20: INT | K20: =_xlfn.XLOOKUP(J20,REF!$D$2:$D$12,REF!$E$2:$E$12) -> Internet | L20: Indisponibilidade de comunicação devido a problema no provedor de internet. | M20: Conexão c/ Internet | N20: Provedora de Internet | O20: Foi realizada inspeção visual no sistema, não sendo identificadas anomalias. Após a normalização do serviço de internet, a comunicação foi restabelecida e a usina voltou a operar normalmente. | P20: =_xlfn.CONCAT(B20,C20,D20,E20,F20) -> BC Bom SucessoB46082,968055555646082,968055555646083,3506944444 | Q20: =_xlfn.CONCAT(H20,I20,J20) -> LIGRFOINT
B21: BC Bom Sucesso | C21: A | D21: 46082.968 | E21: 46082.968 | F21: 46083.351 | G21: =+F21-E21 -> 0.38263889 | H21: LIG | I21: RFO | J21: INT | K21: =_xlfn.XLOOKUP(J21,REF!$D$2:$D$12,REF!$E$2:$E$12) -> Internet | L21: Indisponibilidade de comunicação devido a problema no provedor de internet. | M21: Conexão c/ Internet | N21: Provedora de Internet | O21: Foi realizada inspeção visual no sistema, não sendo identificadas anomalias. Após a normalização do serviço de internet, a comunicação foi restabelecida e a usina voltou a operar normalmente. | P21: =_xlfn.CONCAT(B21,C21,D21,E21,F21) -> BC Bom SucessoA46082,968055555646082,968055555646083,3506944444 | Q21: =_xlfn.CONCAT(H21,I21,J21) -> LIGRFOINT
B22: BC Bom Sucesso | C22: J | D22: 46082.968 | E22: 46082.968 | F22: 46083.351 | G22: =+F22-E22 -> 0.38263889 | H22: LIG | I22: RFO | J22: INT | K22: =_xlfn.XLOOKUP(J22,REF!$D$2:$D$12,REF!$E$2:$E$12) -> Internet | L22: Indisponibilidade de comunicação devido a problema no provedor de internet. | M22: Conexão c/ Internet | N22: Provedora de Internet | O22: Foi realizada inspeção visual no sistema, não sendo identificadas anomalias. Após a normalização do serviço de internet, a comunicação foi restabelecida e a usina voltou a operar normalmente. | P22: =_xlfn.CONCAT(B22,C22,D22,E22,F22) -> BC Bom SucessoJ46082,968055555646082,968055555646083,3506944444 | Q22: =_xlfn.CONCAT(H22,I22,J22) -> LIGRFOINT
... B27: BC Corumba2.2 | C27: U02.I05 | D27: 46083.455 | E27: 46083.455 | F27: 46083.5 | G27: =+F27-E27 -> 0.045138889 | H27: LIG | I27: RFO | J27: INT | K27: =_xlfn.XLOOKUP(J27,REF!$D$2:$D$12,REF!$E$2:$E$12) -> Internet | L27: Foi identificada instabilidade na comunicação do sistema. | M27: Falha Comunicação | N27: Auto-Restart | O27: A comunicação da UFV foi restabelecida automaticamente, retornando à operação normal. | P27: =_xlfn.CONCAT(B27,C27,D27,E27,F27) -> BC Corumba2.2U02.I0546083,454861111146083,454861111146083,5 | Q27: =_xlfn.CONCAT(H27,I27,J27) -> LIGRFOINT
B28: BC Formoso2.1 | C28: Inverter(MBUS-12) | D28: 46083.472 | E28: 46083.472 | F28: 46083.479 | G28: =+F28-E28 -> 0.0069444444 | H28: DAU | J28: RDE | K28: =_xlfn.XLOOKUP(J28,REF!$D$2:$D$12,REF!$E$2:$E$12) -> Rede | L28: Na Usina 2.1, o relé de proteção atuou nas funções 59B (sobretensão) e 27A (subtensão), ocasionando a atuação do sistema de proteção. | M28: Falha Rede | N28: Distribuidora | O28: Realizada inspeção visual no sistema, sem identificação de anomalias. Posteriormente, foi efetuado o reset dos relés de proteção e o rearme da usina, normalizando sua operação. | P28: =_xlfn.CONCAT(B28,C28,D28,E28,F28) -> BC Formoso2.1Inverter(MBUS-12)46083,472222222246083,472222222246083,4791666667 | Q28: =_xlfn.CONCAT(H28,I28,J28) -> DAURDE
B29: BC Formoso2.1 | C29: Inverter(MBUS-14) | D29: 46083.472 | E29: 46083.472 | F29: 46083.479 | G29: =+F29-E29 -> 0.0069444444 | H29: DAU | J29: RDE | K29: =_xlfn.XLOOKUP(J29,REF!$D$2:$D$12,REF!$E$2:$E$12) -> Rede | L29: Na Usina 2.1, o relé de proteção atuou nas funções 59B (sobretensão) e 27A (subtensão), ocasionando a atuação do sistema de proteção. | M29: Falha Rede | N29: Distribuidora | O29: Realizada inspeção visual no sistema, sem identificação de anomalias. Posteriormente, foi efetuado o reset dos relés de proteção e o rearme da usina, normalizando sua operação. | P29: =_xlfn.CONCAT(B29,C29,D29,E29,F29) -> BC Formoso2.1Inverter(MBUS-14)46083,472222222246083,472222222246083,4791666667 | Q29: =_xlfn.CONCAT(H29,I29,J29) -> DAURDE
B30: BC Formoso2.1 | C30: Inverter(MBUS-13) | D30: 46083.472 | E30: 46083.472 | F30: 46083.479 | G30: =+F30-E30 -> 0.0069444444 | H30: DAU | J30: RDE | K30: =_xlfn.XLOOKUP(J30,REF!$D$2:$D$12,REF!$E$2:$E$12) -> Rede | L30: Na Usina 2.1, o relé de proteção atuou nas funções 59B (sobretensão) e 27A (subtensão), ocasionando a atuação do sistema de proteção. | M30: Falha Rede | N30: Distribuidora | O30: Realizada inspeção visual no sistema, sem identificação de anomalias. Posteriormente, foi efetuado o reset dos relés de proteção e o rearme da usina, normalizando sua operação. | P30: =_xlfn.CONCAT(B30,C30,D30,E30,F30) -> BC Formoso2.1Inverter(MBUS-13)46083,472222222246083,472222222246083,4791666667 | Q30: =_xlfn.CONCAT(H30,I30,J30) -> DAURDE
B31: BC Formoso2.1 | C31: Inverter(MBUS-1) | D31: 46083.472 | E31: 46083.472 | F31: 46083.479 | G31: =+F31-E31 -> 0.0069444444 | H31: DAU | J31: RDE | K31: =_xlfn.XLOOKUP(J31,REF!$D$2:$D$12,REF!$E$2:$E$12) -> Rede | L31: Na Usina 2.1, o relé de proteção atuou nas funções 59B (sobretensão) e 27A (subtensão), ocasionando a atuação do sistema de proteção. | M31: Falha Rede | N31: Distribuidora | O31: Realizada inspeção visual no sistema, sem identificação de anomalias. Posteriormente, foi efetuado o reset dos relés de proteção e o rearme da usina, normalizando sua operação. | P31: =_xlfn.CONCAT(B31,C31,D31,E31,F31) -> BC Formoso2.1Inverter(MBUS-1)46083,472222222246083,472222222246083,4791666667 | Q31: =_xlfn.CONCAT(H31,I31,J31) -> DAURDE
B32: BC Formoso2.2 | C32: Inverter(MBUS-14) | D32: 46083.472 | E32: 46083.472 | F32: 46083.479 | G32: =+F32-E32 -> 0.0069444444 | H32: DAU | J32: RDE | K32: =_xlfn.XLOOKUP(J32,REF!$D$2:$D$12,REF!$E$2:$E$12) -> Rede | L32: Na Usina 2.2, o relé de proteção atuou nas funções 59A (sobretensão) e 27C (subtensão), ocasionando a atuação do sistema de proteção. | M32: Falha Rede | N32: Distribuidora | O32: Realizada inspeção visual no sistema, sem identificação de anomalias. Posteriormente, foi efetuado o reset dos relés de proteção e o rearme da usina, normalizando sua operação. | P32: =_xlfn.CONCAT(B32,C32,D32,E32,F32) -> BC Formoso2.2Inverter(MBUS-14)46083,472222222246083,472222222246083,4791666667 | Q32: =_xlfn.CONCAT(H32,I32,J32) -> DAURDE
B33: BC Formoso2.2 | C33: Inverter(MBUS-13) | D33: 46083.472 | E33: 46083.472 | F33: 46083.479 | G33: =+F33-E33 -> 0.0069444444 | H33: DAU | J33: RDE | K33: =_xlfn.XLOOKUP(J33,REF!$D$2:$D$12,REF!$E$2:$E$12) -> Rede | L33: Na Usina 2.2, o relé de proteção atuou nas funções 59A (sobretensão) e 27C (subtensão), ocasionando a atuação do sistema de proteção. | M33: Falha Rede | N33: Distribuidora | O33: Realizada inspeção visual no sistema, sem identificação de anomalias. Posteriormente, foi efetuado o reset dos relés de proteção e o rearme da usina, normalizando sua operação. | P33: =_xlfn.CONCAT(B33,C33,D33,E33,F33) -> BC Formoso2.2Inverter(MBUS-13)46083,472222222246083,472222222246083,4791666667 | Q33: =_xlfn.CONCAT(H33,I33,J33) -> DAURDE
B34: BC Formoso2.2 | C34: Inverter(MBUS-12) | D34: 46083.472 | E34: 46083.472 | F34: 46083.479 | G34: =+F34-E34 -> 0.0069444444 | H34: DAU | J34: RDE | K34: =_xlfn.XLOOKUP(J34,REF!$D$2:$D$12,REF!$E$2:$E$12) -> Rede | L34: Na Usina 2.2, o relé de proteção atuou nas funções 59A (sobretensão) e 27C (subtensão), ocasionando a atuação do sistema de proteção. | M34: Falha Rede | N34: Distribuidora | O34: Realizada inspeção visual no sistema, sem identificação de anomalias. Posteriormente, foi efetuado o reset dos relés de proteção e o rearme da usina, normalizando sua operação. | P34: =_xlfn.CONCAT(B34,C34,D34,E34,F34) -> BC Formoso2.2Inverter(MBUS-12)46083,472222222246083,472222222246083,4791666667 | Q34: =_xlfn.CONCAT(H34,I34,J34) -> DAURDE
B35: BC Formoso2.2 | C35: Inverter(MBUS-1) | D35: 46083.472 | E35: 46083.472 | F35: 46083.479 | G35: =+F35-E35 -> 0.0069444444 | H35: DAU | J35: RDE | K35: =_xlfn.XLOOKUP(J35,REF!$D$2:$D$12,REF!$E$2:$E$12) -> Rede | L35: Na Usina 2.2, o relé de proteção atuou nas funções 59A (sobretensão) e 27C (subtensão), ocasionando a atuação do sistema de proteção. | M35: Falha Rede | N35: Distribuidora | O35: Realizada inspeção visual no sistema, sem identificação de anomalias. Posteriormente, foi efetuado o reset dos relés de proteção e o rearme da usina, normalizando sua operação. | P35: =_xlfn.CONCAT(B35,C35,D35,E35,F35) -> BC Formoso2.2Inverter(MBUS-1)46083,472222222246083,472222222246083,4791666667 | Q35: =_xlfn.CONCAT(H35,I35,J35) -> DAURDE
B36: BC Formoso2.1 | C36: Inverter(MBUS-12) | D36: 46083.51 | E36: 46083.51 | F36: 46083.639 | G36: =+F36-E36 -> 0.12847222 | H36: DAU | J36: RDE | K36: =_xlfn.XLOOKUP(J36,REF!$D$2:$D$12,REF!$E$2:$E$12) -> Rede | L36: Na Usina 2.1, o relé de proteção atuou nas funções 59B (sobretensão) e 27A (subtensão), ocasionando a atuação do sistema de proteção. | M36: Falha Rede | N36: Distribuidora | O36: Realizada inspeção visual no sistema, sem identificação de anomalias. Posteriormente, foi efetuado o reset dos relés de proteção e o rearme da usina, normalizando sua operação. | P36: =_xlfn.CONCAT(B36,C36,D36,E36,F36) -> BC Formoso2.1Inverter(MBUS-12)46083,510416666746083,510416666746083,6388888889 | Q36: =_xlfn.CONCAT(H36,I36,J36) -> DAURDE
B37: BC Formoso2.1 | C37: Inverter(MBUS-14) | D37: 46083.51 | E37: 46083.51 | F37: 46083.639 | G37: =+F37-E37 -> 0.12847222 | H37: DAU | J37: RDE | K37: =_xlfn.XLOOKUP(J37,REF!$D$2:$D$12,REF!$E$2:$E$12) -> Rede | L37: Na Usina 2.1, o relé de proteção atuou nas funções 59B (sobretensão) e 27A (subtensão), ocasionando a atuação do sistema de proteção. | M37: Falha Rede | N37: Distribuidora | O37: Realizada inspeção visual no sistema, sem identificação de anomalias. Posteriormente, foi efetuado o reset dos relés de proteção e o rearme da usina, normalizando sua operação. | P37: =_xlfn.CONCAT(B37,C37,D37,E37,F37) -> BC Formoso2.1Inverter(MBUS-14)46083,510416666746083,510416666746083,6388888889 | Q37: =_xlfn.CONCAT(H37,I37,J37) -> DAURDE
B38: BC Formoso2.1 | C38: Inverter(MBUS-13) | D38: 46083.51 | E38: 46083.51 | F38: 46083.639 | G38: =+F38-E38 -> 0.12847222 | H38: DAU | J38: RDE | K38: =_xlfn.XLOOKUP(J38,REF!$D$2:$D$12,REF!$E$2:$E$12) -> Rede | L38: Na Usina 2.1, o relé de proteção atuou nas funções 59B (sobretensão) e 27A (subtensão), ocasionando a atuação do sistema de proteção. | M38: Falha Rede | N38: Distribuidora | O38: Realizada inspeção visual no sistema, sem identificação de anomalias. Posteriormente, foi efetuado o reset dos relés de proteção e o rearme da usina, normalizando sua operação. | P38: =_xlfn.CONCAT(B38,C38,D38,E38,F38) -> BC Formoso2.1Inverter(MBUS-13)46083,510416666746083,510416666746083,6388888889 | Q38: =_xlfn.CONCAT(H38,I38,J38) -> DAURDE
B39: BC Formoso2.1 | C39: Inverter(MBUS-1) | D39: 46083.51 | E39: 46083.51 | F39: 46083.639 | G39: =+F39-E39 -> 0.12847222 | H39: DAU | J39: RDE | K39: =_xlfn.XLOOKUP(J39,REF!$D$2:$D$12,REF!$E$2:$E$12) -> Rede | L39: Na Usina 2.1, o relé de proteção atuou nas funções 59B (sobretensão) e 27A (subtensão), ocasionando a atuação do sistema de proteção. | M39: Falha Rede | N39: Distribuidora | O39: Realizada inspeção visual no sistema, sem identificação de anomalias. Posteriormente, foi efetuado o reset dos relés de proteção e o rearme da usina, normalizando sua operação. | P39: =_xlfn.CONCAT(B39,C39,D39,E39,F39) -> BC Formoso2.1Inverter(MBUS-1)46083,510416666746083,510416666746083,6388888889 | Q39: =_xlfn.CONCAT(H39,I39,J39) -> DAURDE
... B67: BC Turvania1.3 | C67: Inverter(MBUS-13) | D67: 46084.288 | E67: 46084.288 | F67: 46084.354 | G67: =+F67-E67 -> 0.065972222 | H67: DAU | J67: STR | K67: =_xlfn.XLOOKUP(J67,REF!$D$2:$D$12,REF!$E$2:$E$12) -> String | L67: Durante a inspeção, foi identificado módulo danificado em curto-circuito. | M67: Falha String | N67: Prestador de Serviço O&M | O67: Foi realizada inspeção no inversor GR2449002585, sendo identificado um módulo em curto na string 3.1 da Usina 3. A string permanecerá desativada até que seja realizada a substituição do módulo danificado. Após a intervenção, o inversor voltou a operar com comunicação normal. | P67: =_xlfn.CONCAT(B67,C67,D67,E67,F67) -> BC Turvania1.3Inverter(MBUS-13)46084,288194444446084,288194444446084,3541666667 | Q67: =_xlfn.CONCAT(H67,I67,J67) -> DAUSTR
B68: BC Corumba2.2 | C68: U02.I01 | D68: 46084.292 | E68: 46084.292 | F68: 46084.333 | G68: =+F68-E68 -> 0.041666667 | H68: LIG | I68: RFO | J68: COM | K68: =_xlfn.XLOOKUP(J68,REF!$D$2:$D$12,REF!$E$2:$E$12) -> Comunicação | L68: Foi identificada uma interrupção na comunicação com o Smart Logger. | M68: Falha Comunicação | N68: Auto-Restart | O68: A comunicação da UFV foi restabelecida automaticamente, retornando à operação normal. | P68: =_xlfn.CONCAT(B68,C68,D68,E68,F68) -> BC Corumba2.2U02.I0146084,291666666746084,291666666746084,3333333333 | Q68: =_xlfn.CONCAT(H68,I68,J68) -> LIGRFOCOM
B69: BC Corumba2.2 | C69: U02.I02 | D69: 46084.292 | E69: 46084.292 | F69: 46084.333 | G69: =+F69-E69 -> 0.041666667 | H69: LIG | I69: RFO | J69: COM | K69: =_xlfn.XLOOKUP(J69,REF!$D$2:$D$12,REF!$E$2:$E$12) -> Comunicação | L69: Foi identificada uma interrupção na comunicação com o Smart Logger. | M69: Falha Comunicação | N69: Auto-Restart | O69: A comunicação da UFV foi restabelecida automaticamente, retornando à operação normal. | P69: =_xlfn.CONCAT(B69,C69,D69,E69,F69) -> BC Corumba2.2U02.I0246084,291666666746084,291666666746084,3333333333 | Q69: =_xlfn.CONCAT(H69,I69,J69) -> LIGRFOCOM
B70: BC Corumba2.2 | C70: U02.I03 | D70: 46084.292 | E70: 46084.292 | F70: 46084.333 | G70: =+F70-E70 -> 0.041666667 | H70: LIG | I70: RFO | J70: COM | K70: =_xlfn.XLOOKUP(J70,REF!$D$2:$D$12,REF!$E$2:$E$12) -> Comunicação | L70: Foi identificada uma interrupção na comunicação com o Smart Logger. | M70: Falha Comunicação | N70: Auto-Restart | O70: A comunicação da UFV foi restabelecida automaticamente, retornando à operação normal. | P70: =_xlfn.CONCAT(B70,C70,D70,E70,F70) -> BC Corumba2.2U02.I0346084,291666666746084,291666666746084,3333333333 | Q70: =_xlfn.CONCAT(H70,I70,J70) -> LIGRFOCOM
B71: BC Corumba2.2 | C71: U02.I04 | D71: 46084.292 | E71: 46084.292 | F71: 46084.333 | G71: =+F71-E71 -> 0.041666667 | H71: LIG | I71: RFO | J71: COM | K71: =_xlfn.XLOOKUP(J71,REF!$D$2:$D$12,REF!$E$2:$E$12) -> Comunicação | L71: Foi identificada uma interrupção na comunicação com o Smart Logger. | M71: Falha Comunicação | N71: Auto-Restart | O71: A comunicação da UFV foi restabelecida automaticamente, retornando à operação normal. | P71: =_xlfn.CONCAT(B71,C71,D71,E71,F71) -> BC Corumba2.2U02.I0446084,291666666746084,291666666746084,3333333333 | Q71: =_xlfn.CONCAT(H71,I71,J71) -> LIGRFOCOM
B72: BC Corumba2.2 | C72: U02.I05 | D72: 46084.292 | E72: 46084.292 | F72: 46084.333 | G72: =F72-E72 -> 0.041666667 | H72: LIG | I72: RFO | J72: COM | K72: =_xlfn.XLOOKUP(J72,REF!$D$2:$D$12,REF!$E$2:$E$12) -> Comunicação | L72: Foi identificada uma interrupção na comunicação com o Smart Logger. | M72: Falha Comunicação | N72: Auto-Restart | O72: A comunicação da UFV foi restabelecida automaticamente, retornando à operação normal. | P72: =_xlfn.CONCAT(B72,C72,D72,E72,F72) -> BC Corumba2.2U02.I0546084,291666666746084,291666666746084,3333333333 | Q72: =_xlfn.CONCAT(H72,I72,J72) -> LIGRFOCOM
B73: BC Aracu4 | C73: SG75CX(COM1-018)_001_018 | D73: 46084.299 | E73: 46084.299 | F73: 46084.354 | G73: =F73-E73 -> 0.055555556 | H73: DAU | J73: RDE | K73: =_xlfn.XLOOKUP(J73,REF!$D$2:$D$12,REF!$E$2:$E$12) -> Rede | L73: Queda de energia na UFV Aracu, o relé de proteção atuou na função 86, ocasionando a atuação do sistema de proteção. | M73: Falha Rede | N73: Distribuidora | O73: Realizada inspeção visual no sistema, sem identificação de anomalias. Posteriormente, foi efetuado o reset dos relés de proteção e o rearme da usina, normalizando sua operação. | P73: =_xlfn.CONCAT(B73,C73,D73,E73,F73) -> BC Aracu4SG75CX(COM1-018)_001_01846084,298611111146084,298611111146084,3541666667 | Q73: =_xlfn.CONCAT(H73,I73,J73) -> DAURDE
B74: BC Aracu4 | C74: SG75CX(COM1-019)_001_019 | D74: 46084.299 | E74: 46084.299 | F74: 46084.354 | G74: =F74-E74 -> 0.055555556 | H74: DAU | J74: RDE | K74: =_xlfn.XLOOKUP(J74,REF!$D$2:$D$12,REF!$E$2:$E$12) -> Rede | L74: Queda de energia na UFV Aracu, o relé de proteção atuou na função 86, ocasionando a atuação do sistema de proteção. | M74: Falha Rede | N74: Distribuidora | O74: Realizada inspeção visual no sistema, sem identificação de anomalias. Posteriormente, foi efetuado o reset dos relés de proteção e o rearme da usina, normalizando sua operação. | P74: =_xlfn.CONCAT(B74,C74,D74,E74,F74) -> BC Aracu4SG75CX(COM1-019)_001_01946084,298611111146084,298611111146084,3541666667 | Q74: =_xlfn.CONCAT(H74,I74,J74) -> DAURDE
B75: BC Aracu4 | C75: SG75CX(COM1-020)_001_020 | D75: 46084.299 | E75: 46084.299 | F75: 46084.354 | G75: =F75-E75 -> 0.055555556 | H75: DAU | J75: RDE | K75: =_xlfn.XLOOKUP(J75,REF!$D$2:$D$12,REF!$E$2:$E$12) -> Rede | L75: Queda de energia na UFV Aracu, o relé de proteção atuou na função 86, ocasionando a atuação do sistema de proteção. | M75: Falha Rede | N75: Distribuidora | O75: Realizada inspeção visual no sistema, sem identificação de anomalias. Posteriormente, foi efetuado o reset dos relés de proteção e o rearme da usina, normalizando sua operação. | P75: =_xlfn.CONCAT(B75,C75,D75,E75,F75) -> BC Aracu4SG75CX(COM1-020)_001_02046084,298611111146084,298611111146084,3541666667 | Q75: =_xlfn.CONCAT(H75,I75,J75) -> DAURDE
B76: BC Aracu4 | C76: SG75CX(COM1-021)_001_021 | D76: 46084.299 | E76: 46084.299 | F76: 46084.354 | G76: =F76-E76 -> 0.055555556 | H76: DAU | J76: RDE | K76: =_xlfn.XLOOKUP(J76,REF!$D$2:$D$12,REF!$E$2:$E$12) -> Rede | L76: Queda de energia na UFV Aracu, o relé de proteção atuou na função 86, ocasionando a atuação do sistema de proteção. | M76: Falha Rede | N76: Distribuidora | O76: Realizada inspeção visual no sistema, sem identificação de anomalias. Posteriormente, foi efetuado o reset dos relés de proteção e o rearme da usina, normalizando sua operação. | P76: =_xlfn.CONCAT(B76,C76,D76,E76,F76) -> BC Aracu4SG75CX(COM1-021)_001_02146084,298611111146084,298611111146084,3541666667 | Q76: =_xlfn.CONCAT(H76,I76,J76) -> DAURDE
B77: BC Aracu5.1 | C77: Inverter(MBUS-1) | D77: 46084.299 | E77: 46084.299 | F77: 46084.354 | G77: =F77-E77 -> 0.055555556 | H77: DAU | J77: RDE | K77: =_xlfn.XLOOKUP(J77,REF!$D$2:$D$12,REF!$E$2:$E$12) -> Rede | L77: Queda de energia na UFV Aracu, o relé de proteção atuou na função 86, ocasionando a atuação do sistema de proteção. | M77: Falha Rede | N77: Distribuidora | O77: Realizada inspeção visual no sistema, sem identificação de anomalias. Posteriormente, foi efetuado o reset dos relés de proteção e o rearme da usina, normalizando sua operação. | P77: =_xlfn.CONCAT(B77,C77,D77,E77,F77) -> BC Aracu5.1Inverter(MBUS-1)46084,298611111146084,298611111146084,3541666667 | Q77: =_xlfn.CONCAT(H77,I77,J77) -> DAURDE
B78: BC Aracu5.2 | C78: Inverter(MBUS-1) | D78: 46084.299 | E78: 46084.299 | F78: 46084.354 | G78: =F78-E78 -> 0.055555556 | H78: DAU | J78: RDE | K78: =_xlfn.XLOOKUP(J78,REF!$D$2:$D$12,REF!$E$2:$E$12) -> Rede | L78: Queda de energia na UFV Aracu, o relé de proteção atuou na função 86, ocasionando a atuação do sistema de proteção. | M78: Falha Rede | N78: Distribuidora | O78: Realizada inspeção visual no sistema, sem identificação de anomalias. Posteriormente, foi efetuado o reset dos relés de proteção e o rearme da usina, normalizando sua operação. | P78: =_xlfn.CONCAT(B78,C78,D78,E78,F78) -> BC Aracu5.2Inverter(MBUS-1)46084,298611111146084,298611111146084,3541666667 | Q78: =_xlfn.CONCAT(H78,I78,J78) -> DAURDE
B79: BC Aracu5.3 | C79: Inverter(MBUS-1) | D79: 46084.299 | E79: 46084.299 | F79: 46084.354 | G79: =F79-E79 -> 0.055555556 | H79: DAU | J79: RDE | K79: =_xlfn.XLOOKUP(J79,REF!$D$2:$D$12,REF!$E$2:$E$12) -> Rede | L79: Queda de energia na UFV Aracu, o relé de proteção atuou na função 86, ocasionando a atuação do sistema de proteção. | M79: Falha Rede | N79: Distribuidora | O79: Realizada inspeção visual no sistema, sem identificação de anomalias. Posteriormente, foi efetuado o reset dos relés de proteção e o rearme da usina, normalizando sua operação. | P79: =_xlfn.CONCAT(B79,C79,D79,E79,F79) -> BC Aracu5.3Inverter(MBUS-1)46084,298611111146084,298611111146084,3541666667 | Q79: =_xlfn.CONCAT(H79,I79,J79) -> DAURDE
B80: BC Aracu5.4 | C80: Inverter(MBUS-1) | D80: 46084.299 | E80: 46084.299 | F80: 46084.354 | G80: =F80-E80 -> 0.055555556 | H80: DAU | J80: RDE | K80: =_xlfn.XLOOKUP(J80,REF!$D$2:$D$12,REF!$E$2:$E$12) -> Rede | L80: Queda de energia na UFV Aracu, o relé de proteção atuou na função 86, ocasionando a atuação do sistema de proteção. | M80: Falha Rede | N80: Distribuidora | O80: Realizada inspeção visual no sistema, sem identificação de anomalias. Posteriormente, foi efetuado o reset dos relés de proteção e o rearme da usina, normalizando sua operação. | P80: =_xlfn.CONCAT(B80,C80,D80,E80,F80) -> BC Aracu5.4Inverter(MBUS-1)46084,298611111146084,298611111146084,3541666667 | Q80: =_xlfn.CONCAT(H80,I80,J80) -> DAURDE
B81: BC Aracu5.5 | C81: Inverter(MBUS-1) | D81: 46084.299 | E81: 46084.299 | F81: 46084.354 | G81: =F81-E81 -> 0.055555556 | H81: DAU | J81: RDE | K81: =_xlfn.XLOOKUP(J81,REF!$D$2:$D$12,REF!$E$2:$E$12) -> Rede | L81: Queda de energia na UFV Aracu, o relé de proteção atuou na função 86, ocasionando a atuação do sistema de proteção. | M81: Falha Rede | N81: Distribuidora | O81: Realizada inspeção visual no sistema, sem identificação de anomalias. Posteriormente, foi efetuado o reset dos relés de proteção e o rearme da usina, normalizando sua operação. | P81: =_xlfn.CONCAT(B81,C81,D81,E81,F81) -> BC Aracu5.5Inverter(MBUS-1)46084,298611111146084,298611111146084,3541666667 | Q81: =_xlfn.CONCAT(H81,I81,J81) -> DAURDE
B82: BC Varjao2.1 | C82: 215KTL-H0(MBUS-12) | D82: 46084.354 | E82: 46084.354 | F82: 46084.441 | G82: =F82-E82 -> 0.086805556 | H82: DAU | J82: RDE | K82: =_xlfn.XLOOKUP(J82,REF!$D$2:$D$12,REF!$E$2:$E$12) -> Rede | L82: Indisponibilidade de energia proveniente da concessionária. | M82: Falha Rede | N82: Distribuidora | O82: O fornecimento de energia foi restabelecido, normalizando a operação do sistema. | P82: =_xlfn.CONCAT(B82,C82,D82,E82,F82) -> BC Varjao2.1215KTL-H0(MBUS-12)46084,354166666746084,354166666746084,4409722222 | Q82: =_xlfn.CONCAT(H82,I82,J82) -> DAURDE
B83: BC Varjao2.1 | C83: 215KTL-H0(MBUS-13) | D83: 46084.354 | E83: 46084.354 | F83: 46084.441 | G83: =F83-E83 -> 0.086805556 | H83: DAU | J83: RDE | K83: =_xlfn.XLOOKUP(J83,REF!$D$2:$D$12,REF!$E$2:$E$12) -> Rede | L83: Indisponibilidade de energia proveniente da concessionária. | M83: Falha Rede | N83: Distribuidora | O83: O fornecimento de energia foi restabelecido, normalizando a operação do sistema. | P83: =_xlfn.CONCAT(B83,C83,D83,E83,F83) -> BC Varjao2.1215KTL-H0(MBUS-13)46084,354166666746084,354166666746084,4409722222 | Q83: =_xlfn.CONCAT(H83,I83,J83) -> DAURDE
B84: BC Varjao2.1 | C84: 215KTL-H0(MBUS-14) | D84: 46084.354 | E84: 46084.354 | F84: 46084.441 | G84: =F84-E84 -> 0.086805556 | H84: DAU | J84: RDE | K84: =_xlfn.XLOOKUP(J84,REF!$D$2:$D$12,REF!$E$2:$E$12) -> Rede | L84: Indisponibilidade de energia proveniente da concessionária. | M84: Falha Rede | N84: Distribuidora | O84: O fornecimento de energia foi restabelecido, normalizando a operação do sistema. | P84: =_xlfn.CONCAT(B84,C84,D84,E84,F84) -> BC Varjao2.1215KTL-H0(MBUS-14)46084,354166666746084,354166666746084,4409722222 | Q84: =_xlfn.CONCAT(H84,I84,J84) -> DAURDE
... B192: ARAGUATINS 2.3 | C192: Inverter(MBUS-13) | D192: 46087.368 | E192: 46087.368 | F192: 46087.406 | G192: =F192-E192 -> 0.038194444 | H192: DAU | J192: RDE | K192: =_xlfn.XLOOKUP(J192,REF!$D$2:$D$12,REF!$E$2:$E$12) -> Rede | L192: Queda de energia na UFV Araguatins, o relé de proteção atuou nas funções 50N e 27C e 67C, ocasionando a atuação do sistema de proteção. | M192: Falha Rede | N192: Distribuídora | O192: Realizada inspeção visual no sistema, sem identificação de anomalias. Posteriormente, foi efetuado o reset dos relés de proteção e o rearme da usina, normalizando sua operação. | P192: =_xlfn.CONCAT(B192,C192,D192,E192,F192) -> ARAGUATINS 2.3Inverter(MBUS-13)46087,368055555646087,368055555646087,40625 | Q192: =_xlfn.CONCAT(H192,I192,J192) -> DAURDE
B193: BC Aracu2 | C193: araçu 2.1 inversor 1 | D193: 46087.369 | E193: 46087.369 | F193: 46087.375 | G193: =F193-E193 -> 0.0055555556 | H193: LIG | I193: RFO | J193: INT | K193: =_xlfn.XLOOKUP(J193,REF!$D$2:$D$12,REF!$E$2:$E$12) -> Internet | L193: Indisponibilidade de comunicação devido a problema no provedor de internet. | M193: Conexão c/ Internet | N193: Auto-Restart | O193: A comunicação da UFV foi restabelecida automaticamente, retornando à operação normal. | P193: =_xlfn.CONCAT(B193,C193,D193,E193,F193) -> BC Aracu2araçu 2.1 inversor 146087,369444444446087,369444444446087,375 | Q193: =_xlfn.CONCAT(H193,I193,J193) -> LIGRFOINT
B194: BC Corumba1.1 | C194: U01.I04 | D194: 46087.153 | E194: 46087.153 | G194: =F194-E194 -> -46087.153 | H194: DEM | J194: UFV | K194: =_xlfn.XLOOKUP(J194,REF!$D$2:$D$12,REF!$E$2:$E$12) -> UFV | L194: Por volta das 08h, observou-se que a UFV 1.2 não apresentava geração, enquanto a UFV 1.1 operava parcialmente. A ocorrência foi causada por furto de cabos em algumas caixas de passagem. Após inspeção no local, confirmou-se a subtração de cabos CC no interior dessas caixas. | M194: Furto | N194: Manutenção Corretiva | O194: Por volta das 08h, observou-se que a UFV Corumbá 2.2 apresentou uma falha de comunicação pontual, com normalização às 16h. Em relação à UFV Corumbá 1.2, constatou-se a ocorrência de furto de cabos, permanecendo inoperante até o momento. A UFV Corumbá 1.1 opera parcialmente, visto que também houve subtração de cabeamento em algumas caixas de passagem. Assim que a interrupção da geração foi identificada, foi realizada uma inspeção no local, ocasião em que o crime foi confirmado. O supervisor responsável foi prontamente acionado e compareceu à planta para realizar o levantamento dos materiais subtraídos. As autoridades competentes foram notificadas por meio de Boletim de Ocorrência. No período da tarde, a Patrulha Rural realizou vistoria no local, seguida pela perícia da Polícia Científica. A equipe de O&M já concluiu o levantamento dos danos e encontra-se atuando na recuperação dos ativos, com o objetivo de restabelecer a operação total da usina. | P194: =_xlfn.CONCAT(B194,C194,D194,E194,F194) -> BC Corumba1.1U01.I0446087,153472222246087,1534722222 | Q194: =_xlfn.CONCAT(H194,I194,J194) -> DEMUFV
B195: BC Corumba1.1 | C195: U01.I05 | D195: 46087.153 | E195: 46087.153 | G195: =F195-E195 -> -46087.153 | H195: DEM | J195: UFV | K195: =_xlfn.XLOOKUP(J195,REF!$D$2:$D$12,REF!$E$2:$E$12) -> UFV | L195: Por volta das 08h, observou-se que a UFV 1.2 não apresentava geração, enquanto a UFV 1.1 operava parcialmente. A ocorrência foi causada por furto de cabos em algumas caixas de passagem. Após inspeção no local, confirmou-se a subtração de cabos CC no interior dessas caixas. | M195: Furto | N195: Manutenção Corretiva | O195: Por volta das 08h, observou-se que a UFV Corumbá 2.2 apresentou uma falha de comunicação pontual, com normalização às 16h. Em relação à UFV Corumbá 1.2, constatou-se a ocorrência de furto de cabos, permanecendo inoperante até o momento. A UFV Corumbá 1.1 opera parcialmente, visto que também houve subtração de cabeamento em algumas caixas de passagem. Assim que a interrupção da geração foi identificada, foi realizada uma inspeção no local, ocasião em que o crime foi confirmado. O supervisor responsável foi prontamente acionado e compareceu à planta para realizar o levantamento dos materiais subtraídos. As autoridades competentes foram notificadas por meio de Boletim de Ocorrência. No período da tarde, a Patrulha Rural realizou vistoria no local, seguida pela perícia da Polícia Científica. A equipe de O&M já concluiu o levantamento dos danos e encontra-se atuando na recuperação dos ativos, com o objetivo de restabelecer a operação total da usina. | P195: =_xlfn.CONCAT(B195,C195,D195,E195,F195) -> BC Corumba1.1U01.I0546087,153472222246087,1534722222 | Q195: =_xlfn.CONCAT(H195,I195,J195) -> DEMUFV
B196: BC Corumba1.2 | C196: U02.I01 | D196: 46087.153 | E196: 46087.153 | G196: =F196-E196 -> -46087.153 | H196: DEM | J196: UFV | K196: =_xlfn.XLOOKUP(J196,REF!$D$2:$D$12,REF!$E$2:$E$12) -> UFV | L196: Por volta das 08h, observou-se que a UFV 1.2 não apresentava geração, enquanto a UFV 1.1 operava parcialmente. A ocorrência foi causada por furto de cabos em algumas caixas de passagem. Após inspeção no local, confirmou-se a subtração de cabos CC no interior dessas caixas. | M196: Furto | N196: Manutenção Corretiva | O196: Por volta das 08h, observou-se que a UFV Corumbá 2.2 apresentou uma falha de comunicação pontual, com normalização às 16h. Em relação à UFV Corumbá 1.2, constatou-se a ocorrência de furto de cabos, permanecendo inoperante até o momento. A UFV Corumbá 1.1 opera parcialmente, visto que também houve subtração de cabeamento em algumas caixas de passagem. Assim que a interrupção da geração foi identificada, foi realizada uma inspeção no local, ocasião em que o crime foi confirmado. O supervisor responsável foi prontamente acionado e compareceu à planta para realizar o levantamento dos materiais subtraídos. As autoridades competentes foram notificadas por meio de Boletim de Ocorrência. No período da tarde, a Patrulha Rural realizou vistoria no local, seguida pela perícia da Polícia Científica. A equipe de O&M já concluiu o levantamento dos danos e encontra-se atuando na recuperação dos ativos, com o objetivo de restabelecer a operação total da usina. | P196: =_xlfn.CONCAT(B196,C196,D196,E196,F196) -> BC Corumba1.2U02.I0146087,153472222246087,1534722222 | Q196: =_xlfn.CONCAT(H196,I196,J196) -> DEMUFV
B197: BC Corumba1.2 | C197: U02.I02 | D197: 46087.153 | E197: 46087.153 | G197: =F197-E197 -> -46087.153 | H197: DEM | J197: UFV | K197: =_xlfn.XLOOKUP(J197,REF!$D$2:$D$12,REF!$E$2:$E$12) -> UFV | L197: Por volta das 08h, observou-se que a UFV 1.2 não apresentava geração, enquanto a UFV 1.1 operava parcialmente. A ocorrência foi causada por furto de cabos em algumas caixas de passagem. Após inspeção no local, confirmou-se a subtração de cabos CC no interior dessas caixas. | M197: Furto | N197: Manutenção Corretiva | O197: Por volta das 08h, observou-se que a UFV Corumbá 2.2 apresentou uma falha de comunicação pontual, com normalização às 16h. Em relação à UFV Corumbá 1.2, constatou-se a ocorrência de furto de cabos, permanecendo inoperante até o momento. A UFV Corumbá 1.1 opera parcialmente, visto que também houve subtração de cabeamento em algumas caixas de passagem. Assim que a interrupção da geração foi identificada, foi realizada uma inspeção no local, ocasião em que o crime foi confirmado. O supervisor responsável foi prontamente acionado e compareceu à planta para realizar o levantamento dos materiais subtraídos. As autoridades competentes foram notificadas por meio de Boletim de Ocorrência. No período da tarde, a Patrulha Rural realizou vistoria no local, seguida pela perícia da Polícia Científica. A equipe de O&M já concluiu o levantamento dos danos e encontra-se atuando na recuperação dos ativos, com o objetivo de restabelecer a operação total da usina. | P197: =_xlfn.CONCAT(B197,C197,D197,E197,F197) -> BC Corumba1.2U02.I0246087,153472222246087,1534722222 | Q197: =_xlfn.CONCAT(H197,I197,J197) -> DEMUFV
B198: BC Corumba1.2 | C198: U02.I03 | D198: 46087.153 | E198: 46087.153 | G198: =F198-E198 -> -46087.153 | H198: DEM | J198: UFV | K198: =_xlfn.XLOOKUP(J198,REF!$D$2:$D$12,REF!$E$2:$E$12) -> UFV | L198: Por volta das 08h, observou-se que a UFV 1.2 não apresentava geração, enquanto a UFV 1.1 operava parcialmente. A ocorrência foi causada por furto de cabos em algumas caixas de passagem. Após inspeção no local, confirmou-se a subtração de cabos CC no interior dessas caixas. | M198: Furto | N198: Manutenção Corretiva | O198: Por volta das 08h, observou-se que a UFV Corumbá 2.2 apresentou uma falha de comunicação pontual, com normalização às 16h. Em relação à UFV Corumbá 1.2, constatou-se a ocorrência de furto de cabos, permanecendo inoperante até o momento. A UFV Corumbá 1.1 opera parcialmente, visto que também houve subtração de cabeamento em algumas caixas de passagem. Assim que a interrupção da geração foi identificada, foi realizada uma inspeção no local, ocasião em que o crime foi confirmado. O supervisor responsável foi prontamente acionado e compareceu à planta para realizar o levantamento dos materiais subtraídos. As autoridades competentes foram notificadas por meio de Boletim de Ocorrência. No período da tarde, a Patrulha Rural realizou vistoria no local, seguida pela perícia da Polícia Científica. A equipe de O&M já concluiu o levantamento dos danos e encontra-se atuando na recuperação dos ativos, com o objetivo de restabelecer a operação total da usina. | P198: =_xlfn.CONCAT(B198,C198,D198,E198,F198) -> BC Corumba1.2U02.I0346087,153472222246087,1534722222 | Q198: =_xlfn.CONCAT(H198,I198,J198) -> DEMUFV
B199: BC Corumba1.2 | C199: U02.I04 | D199: 46087.153 | E199: 46087.153 | G199: =F199-E199 -> -46087.153 | H199: DEM | J199: UFV | K199: =_xlfn.XLOOKUP(J199,REF!$D$2:$D$12,REF!$E$2:$E$12) -> UFV | L199: Por volta das 08h, observou-se que a UFV 1.2 não apresentava geração, enquanto a UFV 1.1 operava parcialmente. A ocorrência foi causada por furto de cabos em algumas caixas de passagem. Após inspeção no local, confirmou-se a subtração de cabos CC no interior dessas caixas. | M199: Furto | N199: Manutenção Corretiva | O199: Por volta das 08h, observou-se que a UFV Corumbá 2.2 apresentou uma falha de comunicação pontual, com normalização às 16h. Em relação à UFV Corumbá 1.2, constatou-se a ocorrência de furto de cabos, permanecendo inoperante até o momento. A UFV Corumbá 1.1 opera parcialmente, visto que também houve subtração de cabeamento em algumas caixas de passagem. Assim que a interrupção da geração foi identificada, foi realizada uma inspeção no local, ocasião em que o crime foi confirmado. O supervisor responsável foi prontamente acionado e compareceu à planta para realizar o levantamento dos materiais subtraídos. As autoridades competentes foram notificadas por meio de Boletim de Ocorrência. No período da tarde, a Patrulha Rural realizou vistoria no local, seguida pela perícia da Polícia Científica. A equipe de O&M já concluiu o levantamento dos danos e encontra-se atuando na recuperação dos ativos, com o objetivo de restabelecer a operação total da usina. | P199: =_xlfn.CONCAT(B199,C199,D199,E199,F199) -> BC Corumba1.2U02.I0446087,153472222246087,1534722222 | Q199: =_xlfn.CONCAT(H199,I199,J199) -> DEMUFV
B200: BC Corumba1.2 | C200: U02.I05 | D200: 46087.153 | E200: 46087.153 | G200: =F200-E200 -> -46087.153 | H200: DEM | J200: UFV | K200: =_xlfn.XLOOKUP(J200,REF!$D$2:$D$12,REF!$E$2:$E$12) -> UFV | L200: Por volta das 08h, observou-se que a UFV 1.2 não apresentava geração, enquanto a UFV 1.1 operava parcialmente. A ocorrência foi causada por furto de cabos em algumas caixas de passagem. Após inspeção no local, confirmou-se a subtração de cabos CC no interior dessas caixas. | M200: Furto | N200: Manutenção Corretiva | O200: Por volta das 08h, observou-se que a UFV Corumbá 2.2 apresentou uma falha de comunicação pontual, com normalização às 16h. Em relação à UFV Corumbá 1.2, constatou-se a ocorrência de furto de cabos, permanecendo inoperante até o momento. A UFV Corumbá 1.1 opera parcialmente, visto que também houve subtração de cabeamento em algumas caixas de passagem. Assim que a interrupção da geração foi identificada, foi realizada uma inspeção no local, ocasião em que o crime foi confirmado. O supervisor responsável foi prontamente acionado e compareceu à planta para realizar o levantamento dos materiais subtraídos. As autoridades competentes foram notificadas por meio de Boletim de Ocorrência. No período da tarde, a Patrulha Rural realizou vistoria no local, seguida pela perícia da Polícia Científica. A equipe de O&M já concluiu o levantamento dos danos e encontra-se atuando na recuperação dos ativos, com o objetivo de restabelecer a operação total da usina. | P200: =_xlfn.CONCAT(B200,C200,D200,E200,F200) -> BC Corumba1.2U02.I0546087,153472222246087,1534722222 | Q200: =_xlfn.CONCAT(H200,I200,J200) -> DEMUFV
B201: BC Ibiuna 1.1 | C201: Inverter(MBUS-12) | D201: 46087.642 | E201: 46087.642 | F201: 46087.654 | G201: =F201-E201 -> 0.011805556 | H201: DAU | J201: RDE | K201: =_xlfn.XLOOKUP(J201,REF!$D$2:$D$12,REF!$E$2:$E$12) -> Rede | L201: Queda de energia na UFV Ibiuna, o relé de proteção atuou nas função 27B, ocasionando a atuação do sistema de proteção. | M201: Falha Rede | N201: Distribuídora | O201: Realizada inspeção visual no sistema, sem identificação de anomalias. Posteriormente, foi efetuado o reset dos relés de proteção e o rearme da usina, normalizando sua operação. | P201: =_xlfn.CONCAT(B201,C201,D201,E201,F201) -> BC Ibiuna 1.1Inverter(MBUS-12)46087,642361111146087,642361111146087,6541666667 | Q201: =_xlfn.CONCAT(H201,I201,J201) -> DAURDE
B202: BC Ibiuna 1.1 | C202: Inverter(MBUS-13) | D202: 46087.642 | E202: 46087.642 | F202: 46087.654 | G202: =F202-E202 -> 0.011805556 | H202: DAU | J202: RDE | K202: =_xlfn.XLOOKUP(J202,REF!$D$2:$D$12,REF!$E$2:$E$12) -> Rede | L202: Queda de energia na UFV Ibiuna, o relé de proteção atuou nas função 27B, ocasionando a atuação do sistema de proteção. | M202: Falha Rede | N202: Distribuídora | O202: Realizada inspeção visual no sistema, sem identificação de anomalias. Posteriormente, foi efetuado o reset dos relés de proteção e o rearme da usina, normalizando sua operação. | P202: =_xlfn.CONCAT(B202,C202,D202,E202,F202) -> BC Ibiuna 1.1Inverter(MBUS-13)46087,642361111146087,642361111146087,6541666667 | Q202: =_xlfn.CONCAT(H202,I202,J202) -> DAURDE
B203: BC Ibiuna 1.1 | C203: Inverter(MBUS-14) | D203: 46087.642 | E203: 46087.642 | F203: 46087.654 | G203: =F203-E203 -> 0.011805556 | H203: DAU | J203: RDE | K203: =_xlfn.XLOOKUP(J203,REF!$D$2:$D$12,REF!$E$2:$E$12) -> Rede | L203: Queda de energia na UFV Ibiuna, o relé de proteção atuou nas função 27B, ocasionando a atuação do sistema de proteção. | M203: Falha Rede | N203: Distribuídora | O203: Realizada inspeção visual no sistema, sem identificação de anomalias. Posteriormente, foi efetuado o reset dos relés de proteção e o rearme da usina, normalizando sua operação. | P203: =_xlfn.CONCAT(B203,C203,D203,E203,F203) -> BC Ibiuna 1.1Inverter(MBUS-14)46087,642361111146087,642361111146087,6541666667 | Q203: =_xlfn.CONCAT(H203,I203,J203) -> DAURDE
B204: BC Ibiuna 1.1 | C204: Inverter(MBUS-15) | D204: 46087.642 | E204: 46087.642 | F204: 46087.654 | G204: =F204-E204 -> 0.011805556 | H204: DAU | J204: RDE | K204: =_xlfn.XLOOKUP(J204,REF!$D$2:$D$12,REF!$E$2:$E$12) -> Rede | L204: Queda de energia na UFV Ibiuna, o relé de proteção atuou nas função 27B, ocasionando a atuação do sistema de proteção. | M204: Falha Rede | N204: Distribuídora | O204: Realizada inspeção visual no sistema, sem identificação de anomalias. Posteriormente, foi efetuado o reset dos relés de proteção e o rearme da usina, normalizando sua operação. | P204: =_xlfn.CONCAT(B204,C204,D204,E204,F204) -> BC Ibiuna 1.1Inverter(MBUS-15)46087,642361111146087,642361111146087,6541666667 | Q204: =_xlfn.CONCAT(H204,I204,J204) -> DAURDE
B205: BC Ibiuna 1.2 | C205: Inverter(MBUS-12) | D205: 46087.642 | E205: 46087.642 | F205: 46087.654 | G205: =F205-E205 -> 0.011805556 | H205: DAU | J205: RDE | K205: =_xlfn.XLOOKUP(J205,REF!$D$2:$D$12,REF!$E$2:$E$12) -> Rede | L205: Queda de energia na UFV Ibiuna, o relé de proteção atuou nas função 27B, ocasionando a atuação do sistema de proteção. | M205: Falha Rede | N205: Distribuídora | O205: Realizada inspeção visual no sistema, sem identificação de anomalias. Posteriormente, foi efetuado o reset dos relés de proteção e o rearme da usina, normalizando sua operação. | P205: =_xlfn.CONCAT(B205,C205,D205,E205,F205) -> BC Ibiuna 1.2Inverter(MBUS-12)46087,642361111146087,642361111146087,6541666667 | Q205: =_xlfn.CONCAT(H205,I205,J205) -> DAURDE
B206: BC Ibiuna 1.2 | C206: Inverter(MBUS-13) | D206: 46087.642 | E206: 46087.642 | F206: 46087.654 | G206: =F206-E206 -> 0.011805556 | H206: DAU | J206: RDE | K206: =_xlfn.XLOOKUP(J206,REF!$D$2:$D$12,REF!$E$2:$E$12) -> Rede | L206: Queda de energia na UFV Ibiuna, o relé de proteção atuou nas função 27B, ocasionando a atuação do sistema de proteção. | M206: Falha Rede | N206: Distribuídora | O206: Realizada inspeção visual no sistema, sem identificação de anomalias. Posteriormente, foi efetuado o reset dos relés de proteção e o rearme da usina, normalizando sua operação. | P206: =_xlfn.CONCAT(B206,C206,D206,E206,F206) -> BC Ibiuna 1.2Inverter(MBUS-13)46087,642361111146087,642361111146087,6541666667 | Q206: =_xlfn.CONCAT(H206,I206,J206) -> DAURDE
B207: BC Ibiuna 1.2 | C207: Inverter(MBUS-14) | D207: 46087.642 | E207: 46087.642 | F207: 46087.654 | G207: =F207-E207 -> 0.011805556 | H207: DAU | J207: RDE | K207: =_xlfn.XLOOKUP(J207,REF!$D$2:$D$12,REF!$E$2:$E$12) -> Rede | L207: Queda de energia na UFV Ibiuna, o relé de proteção atuou nas função 27B, ocasionando a atuação do sistema de proteção. | M207: Falha Rede | N207: Distribuídora | O207: Realizada inspeção visual no sistema, sem identificação de anomalias. Posteriormente, foi efetuado o reset dos relés de proteção e o rearme da usina, normalizando sua operação. | P207: =_xlfn.CONCAT(B207,C207,D207,E207,F207) -> BC Ibiuna 1.2Inverter(MBUS-14)46087,642361111146087,642361111146087,6541666667 | Q207: =_xlfn.CONCAT(H207,I207,J207) -> DAURDE
B208: BC Ibiuna 1.2 | C208: Inverter(MBUS-15) | D208: 46087.642 | E208: 46087.642 | F208: 46087.654 | G208: =F208-E208 -> 0.011805556 | H208: DAU | J208: RDE | K208: =_xlfn.XLOOKUP(J208,REF!$D$2:$D$12,REF!$E$2:$E$12) -> Rede | L208: Queda de energia na UFV Ibiuna, o relé de proteção atuou nas função 27B, ocasionando a atuação do sistema de proteção. | M208: Falha Rede | N208: Distribuídora | O208: Realizada inspeção visual no sistema, sem identificação de anomalias. Posteriormente, foi efetuado o reset dos relés de proteção e o rearme da usina, normalizando sua operação. | P208: =_xlfn.CONCAT(B208,C208,D208,E208,F208) -> BC Ibiuna 1.2Inverter(MBUS-15)46087,642361111146087,642361111146087,6541666667 | Q208: =_xlfn.CONCAT(H208,I208,J208) -> DAURDE
B209: BC Bom Sucesso | C209: J | D209: 46087.653 | E209: 46087.653 | F209: 46096.653 | G209: =F209-E209 -> 9 | H209: DAU | J209: INV | K209: =_xlfn.XLOOKUP(J209,REF!$D$2:$D$12,REF!$E$2:$E$12) -> Inversor | L209: Foi identificado curto-circuito na seccionadora ABB do inversor 12. O inversor permanece sem geração até a substituição da seccionadora | M209: Falha Inversor | N209: Prestador de Serviço O&M | O209: Realizada inspeção visual no sistema, realizada substituição da chave seccionadora. Posteriormente, foi efetuado o reset dos relés de proteção e o rearme da usina, normalizando sua operação. | P209: =_xlfn.CONCAT(B209,C209,D209,E209,F209) -> BC Bom SucessoJ46087,652777777846087,652777777846096,6527777778 | Q209: =_xlfn.CONCAT(H209,I209,J209) -> DAUINV
B210: BC Aracu4 | C210: SG75CX(COM1-018)_001_018 | D210: 46087.872 | E210: 46087.872 | F210: 46088.367 | G210: =F210-E210 -> 0.49583333 | H210: DAU | J210: RDE | K210: =_xlfn.XLOOKUP(J210,REF!$D$2:$D$12,REF!$E$2:$E$12) -> Rede | L210: Queda de energia na UFV Aracu, o relé de proteção atuou nas função 81 e 86, ocasionando a atuação do sistema de proteção. | M210: Falha Rede | N210: Distribuídora | O210: Realizada inspeção visual no sistema, sem identificação de anomalias. Posteriormente, foi efetuado o reset dos relés de proteção e o rearme da usina, normalizando sua operação. | P210: =_xlfn.CONCAT(B210,C210,D210,E210,F210) -> BC Aracu4SG75CX(COM1-018)_001_01846087,871527777846087,871527777846088,3673611111 | Q210: =_xlfn.CONCAT(H210,I210,J210) -> DAURDE
B211: BC Aracu4 | C211: SG75CX(COM1-019)_001_019 | D211: 46087.872 | E211: 46087.872 | F211: 46088.367 | G211: =F211-E211 -> 0.49583333 | H211: DAU | J211: RDE | K211: =_xlfn.XLOOKUP(J211,REF!$D$2:$D$12,REF!$E$2:$E$12) -> Rede | L211: Queda de energia na UFV Aracu, o relé de proteção atuou nas função 81 e 86, ocasionando a atuação do sistema de proteção. | M211: Falha Rede | N211: Distribuídora | O211: Realizada inspeção visual no sistema, sem identificação de anomalias. Posteriormente, foi efetuado o reset dos relés de proteção e o rearme da usina, normalizando sua operação. | P211: =_xlfn.CONCAT(B211,C211,D211,E211,F211) -> BC Aracu4SG75CX(COM1-019)_001_01946087,871527777846087,871527777846088,3673611111 | Q211: =_xlfn.CONCAT(H211,I211,J211) -> DAURDE
B212: BC Aracu4 | C212: SG75CX(COM1-020)_001_020 | D212: 46087.872 | E212: 46087.872 | F212: 46088.367 | G212: =F212-E212 -> 0.49583333 | H212: DAU | J212: RDE | K212: =_xlfn.XLOOKUP(J212,REF!$D$2:$D$12,REF!$E$2:$E$12) -> Rede | L212: Queda de energia na UFV Aracu, o relé de proteção atuou nas função 81 e 86, ocasionando a atuação do sistema de proteção. | M212: Falha Rede | N212: Distribuídora | O212: Realizada inspeção visual no sistema, sem identificação de anomalias. Posteriormente, foi efetuado o reset dos relés de proteção e o rearme da usina, normalizando sua operação. | P212: =_xlfn.CONCAT(B212,C212,D212,E212,F212) -> BC Aracu4SG75CX(COM1-020)_001_02046087,871527777846087,871527777846088,3673611111 | Q212: =_xlfn.CONCAT(H212,I212,J212) -> DAURDE
... B214: BC Aracu5.1 | C214: Inverter(MBUS-1) | D214: 46087.872 | E214: 46087.872 | F214: 46088.367 | G214: =F214-E214 -> 0.49583333 | H214: DAU | J214: RDE | K214: =_xlfn.XLOOKUP(J214,REF!$D$2:$D$12,REF!$E$2:$E$12) -> Rede | L214: Queda de energia na UFV Aracu, o relé de proteção atuou nas função 81 e 86, ocasionando a atuação do sistema de proteção. | M214: Falha Rede | N214: Distribuídora | O214: Realizada inspeção visual no sistema, sem identificação de anomalias. Posteriormente, foi efetuado o reset dos relés de proteção e o rearme da usina, normalizando sua operação. | P214: =_xlfn.CONCAT(B214,C214,D214,E214,F214) -> BC Aracu5.1Inverter(MBUS-1)46087,871527777846087,871527777846088,3673611111 | Q214: =_xlfn.CONCAT(H214,I214,J214) -> DAURDE
B215: BC Aracu5.2 | C215: Inverter(MBUS-1) | D215: 46087.872 | E215: 46087.872 | F215: 46088.367 | G215: =F215-E215 -> 0.49583333 | H215: DAU | J215: RDE | K215: =_xlfn.XLOOKUP(J215,REF!$D$2:$D$12,REF!$E$2:$E$12) -> Rede | L215: Queda de energia na UFV Aracu, o relé de proteção atuou nas função 81 e 86, ocasionando a atuação do sistema de proteção. | M215: Falha Rede | N215: Distribuídora | O215: Realizada inspeção visual no sistema, sem identificação de anomalias. Posteriormente, foi efetuado o reset dos relés de proteção e o rearme da usina, normalizando sua operação. | P215: =_xlfn.CONCAT(B215,C215,D216,E215,F215) -> BC Aracu5.2Inverter(MBUS-1)46087,871527777846087,871527777846088,3673611111 | Q215: =_xlfn.CONCAT(H215,I215,J215) -> DAURDE
B216: BC Aracu5.3 | C216: Inverter(MBUS-1) | D216: 46087.872 | E216: 46087.872 | F216: 46088.367 | G216: =F216-E216 -> 0.49583333 | H216: DAU | J216: RDE | K216: =_xlfn.XLOOKUP(J216,REF!$D$2:$D$12,REF!$E$2:$E$12) -> Rede | L216: Queda de energia na UFV Aracu, o relé de proteção atuou nas função 81 e 86, ocasionando a atuação do sistema de proteção. | M216: Falha Rede | N216: Distribuídora | O216: Realizada inspeção visual no sistema, sem identificação de anomalias. Posteriormente, foi efetuado o reset dos relés de proteção e o rearme da usina, normalizando sua operação. | P216: =_xlfn.CONCAT(B216,C216,D217,E216,F216) -> BC Aracu5.3Inverter(MBUS-1)46087,871527777846087,871527777846088,3673611111 | Q216: =_xlfn.CONCAT(H216,I216,J216) -> DAURDE
B217: BC Aracu5.4 | C217: Inverter(MBUS-1) | D217: 46087.872 | E217: 46087.872 | F217: 46088.367 | G217: =F217-E217 -> 0.49583333 | H217: DAU | J217: RDE | K217: =_xlfn.XLOOKUP(J217,REF!$D$2:$D$12,REF!$E$2:$E$12) -> Rede | L217: Queda de energia na UFV Aracu, o relé de proteção atuou nas função 81 e 86, ocasionando a atuação do sistema de proteção. | M217: Falha Rede | N217: Distribuídora | O217: Realizada inspeção visual no sistema, sem identificação de anomalias. Posteriormente, foi efetuado o reset dos relés de proteção e o rearme da usina, normalizando sua operação. | P217: =_xlfn.CONCAT(B217,C217,D218,E217,F217) -> BC Aracu5.4Inverter(MBUS-1)46087,871527777846087,871527777846088,3673611111 | Q217: =_xlfn.CONCAT(H217,I217,J217) -> DAURDE
B218: BC Aracu5.5 | C218: Inverter(MBUS-1) | D218: 46087.872 | E218: 46087.872 | F218: 46088.367 | G218: =F218-E218 -> 0.49583333 | H218: DAU | J218: RDE | K218: =_xlfn.XLOOKUP(J218,REF!$D$2:$D$12,REF!$E$2:$E$12) -> Rede | L218: Queda de energia na UFV Aracu, o relé de proteção atuou nas função 81 e 86, ocasionando a atuação do sistema de proteção. | M218: Falha Rede | N218: Distribuídora | O218: Realizada inspeção visual no sistema, sem identificação de anomalias. Posteriormente, foi efetuado o reset dos relés de proteção e o rearme da usina, normalizando sua operação. | P218: =_xlfn.CONCAT(B218,C218,D219,E218,F218) -> BC Aracu5.5Inverter(MBUS-1)46088,385416666746087,871527777846088,3673611111 | Q218: =_xlfn.CONCAT(H218,I218,J218) -> DAURDE
B219: BC Camarao1.1 | C219: Inverter(MBUS-1) | D219: 46088.385 | E219: 46088.385 | F219: 46088.476 | G219: =F219-E219 -> 0.090277778 | H219: DAU | J219: RDE | K219: =_xlfn.XLOOKUP(J219,REF!$D$2:$D$12,REF!$E$2:$E$12) -> Rede | L219: Queda de energia na UFV Aracu, o relé de proteção atuou nas função 47, ocasionando a atuação do sistema de proteção. | M219: Falha Rede | N219: Distribuídora | O219: Realizada inspeção visual no sistema, sem identificação de anomalias. Posteriormente, foi efetuado o reset dos relés de proteção e o rearme da usina, normalizando sua operação. | P219: =_xlfn.CONCAT(B219,C219,D219,E219,F219) -> BC Camarao1.1Inverter(MBUS-1)46088,385416666746088,385416666746088,4756944444 | Q219: =_xlfn.CONCAT(H219,I219,J219) -> DAURDE
B220: BC Camarao1.1 | C220: 215KTL-H3(MBUS-12) | D220: 46088.385 | E220: 46088.385 | F220: 46088.476 | G220: =F220-E220 -> 0.090277778 | H220: DAU | J220: RDE | K220: =_xlfn.XLOOKUP(J220,REF!$D$2:$D$12,REF!$E$2:$E$12) -> Rede | L220: Queda de energia na UFV Aracu, o relé de proteção atuou nas função 47, ocasionando a atuação do sistema de proteção. | M220: Falha Rede | N220: Distribuídora | O220: Realizada inspeção visual no sistema, sem identificação de anomalias. Posteriormente, foi efetuado o reset dos relés de proteção e o rearme da usina, normalizando sua operação. | P220: =_xlfn.CONCAT(B220,C220,D220,E220,F220) -> BC Camarao1.1215KTL-H3(MBUS-12)46088,385416666746088,385416666746088,4756944444 | Q220: =_xlfn.CONCAT(H220,I220,J220) -> DAURDE
B221: BC Camarao1.1 | C221: 215KTL-H3(MBUS-13) | D221: 46088.385 | E221: 46088.385 | F221: 46088.476 | G221: =F221-E221 -> 0.090277778 | H221: DAU | J221: RDE | K221: =_xlfn.XLOOKUP(J221,REF!$D$2:$D$12,REF!$E$2:$E$12) -> Rede | L221: Queda de energia na UFV Aracu, o relé de proteção atuou nas função 47, ocasionando a atuação do sistema de proteção. | M221: Falha Rede | N221: Distribuídora | O221: Realizada inspeção visual no sistema, sem identificação de anomalias. Posteriormente, foi efetuado o reset dos relés de proteção e o rearme da usina, normalizando sua operação. | P221: =_xlfn.CONCAT(B221,C221,D221,E221,F221) -> BC Camarao1.1215KTL-H3(MBUS-13)46088,385416666746088,385416666746088,4756944444 | Q221: =_xlfn.CONCAT(H221,I221,J221) -> DAURDE
B222: BC Camarao1.1 | C222: 215KTL-H3(MBUS-16) | D222: 46088.385 | E222: 46088.385 | F222: 46088.476 | G222: =F222-E222 -> 0.090277778 | H222: DAU | J222: RDE | K222: =_xlfn.XLOOKUP(J222,REF!$D$2:$D$12,REF!$E$2:$E$12) -> Rede | L222: Queda de energia na UFV Aracu, o relé de proteção atuou nas função 47, ocasionando a atuação do sistema de proteção. | M222: Falha Rede | N222: Distribuídora | O222: Realizada inspeção visual no sistema, sem identificação de anomalias. Posteriormente, foi efetuado o reset dos relés de proteção e o rearme da usina, normalizando sua operação. | P222: =_xlfn.CONCAT(B222,C222,D222,E222,F222) -> BC Camarao1.1215KTL-H3(MBUS-16)46088,385416666746088,385416666746088,4756944444 | Q222: =_xlfn.CONCAT(H222,I222,J222) -> DAURDE
B223: BC Camarao1.1 | C223: 215KTL-H3(MBUS-15) | D223: 46088.385 | E223: 46088.385 | F223: 46088.476 | G223: =F223-E223 -> 0.090277778 | H223: DAU | J223: RDE | K223: =_xlfn.XLOOKUP(J223,REF!$D$2:$D$12,REF!$E$2:$E$12) -> Rede | L223: Queda de energia na UFV Aracu, o relé de proteção atuou nas função 47, ocasionando a atuação do sistema de proteção. | M223: Falha Rede | N223: Distribuídora | O223: Realizada inspeção visual no sistema, sem identificação de anomalias. Posteriormente, foi efetuado o reset dos relés de proteção e o rearme da usina, normalizando sua operação. | P223: =_xlfn.CONCAT(B223,C223,D223,E223,F223) -> BC Camarao1.1215KTL-H3(MBUS-15)46088,385416666746088,385416666746088,4756944444 | Q223: =_xlfn.CONCAT(H223,I223,J223) -> DAURDE
B224: BC Camarao1.3 | C224: 215KTL-H3(MBUS-16) | D224: 46088.385 | E224: 46088.385 | F224: 46088.476 | G224: =F224-E224 -> 0.090277778 | H224: DAU | J224: RDE | K224: =_xlfn.XLOOKUP(J224,REF!$D$2:$D$12,REF!$E$2:$E$12) -> Rede | L224: Queda de energia na UFV Aracu, o relé de proteção atuou nas função 47, ocasionando a atuação do sistema de proteção. | M224: Falha Rede | N224: Distribuídora | O224: Realizada inspeção visual no sistema, sem identificação de anomalias. Posteriormente, foi efetuado o reset dos relés de proteção e o rearme da usina, normalizando sua operação. | P224: =_xlfn.CONCAT(B224,C224,D224,E224,F224) -> BC Camarao1.3215KTL-H3(MBUS-16)46088,385416666746088,385416666746088,4756944444 | Q224: =_xlfn.CONCAT(H224,I224,J224) -> DAURDE
B225: BC Camarao1.3 | C225: 215KTL-H3(MBUS-14) | D225: 46088.385 | E225: 46088.385 | F225: 46088.476 | G225: =F225-E225 -> 0.090277778 | H225: DAU | J225: RDE | K225: =_xlfn.XLOOKUP(J225,REF!$D$2:$D$12,REF!$E$2:$E$12) -> Rede | L225: Queda de energia na UFV Aracu, o relé de proteção atuou nas função 47, ocasionando a atuação do sistema de proteção. | M225: Falha Rede | N225: Distribuídora | O225: Realizada inspeção visual no sistema, sem identificação de anomalias. Posteriormente, foi efetuado o reset dos relés de proteção e o rearme da usina, normalizando sua operação. | P225: =_xlfn.CONCAT(B225,C225,D225,E225,F225) -> BC Camarao1.3215KTL-H3(MBUS-14)46088,385416666746088,385416666746088,4756944444 | Q225: =_xlfn.CONCAT(H225,I225,J225) -> DAURDE
B226: BC Camarao1.3 | C226: 215KTL-H3(MBUS-15) | D226: 46088.385 | E226: 46088.385 | F226: 46088.476 | G226: =F226-E226 -> 0.090277778 | H226: DAU | J226: RDE | K226: =_xlfn.XLOOKUP(J226,REF!$D$2:$D$12,REF!$E$2:$E$12) -> Rede | L226: Queda de energia na UFV Aracu, o relé de proteção atuou nas função 47, ocasionando a atuação do sistema de proteção. | M226: Falha Rede | N226: Distribuídora | O226: Realizada inspeção visual no sistema, sem identificação de anomalias. Posteriormente, foi efetuado o reset dos relés de proteção e o rearme da usina, normalizando sua operação. | P226: =_xlfn.CONCAT(B226,C226,D226,E226,F226) -> BC Camarao1.3215KTL-H3(MBUS-15)46088,385416666746088,385416666746088,4756944444 | Q226: =_xlfn.CONCAT(H226,I226,J226) -> DAURDE
B227: BC Camarao1.3 | C227: 215KTL-H3(MBUS-12) | D227: 46088.385 | E227: 46088.385 | F227: 46088.476 | G227: =F227-E227 -> 0.090277778 | H227: DAU | J227: RDE | K227: =_xlfn.XLOOKUP(J227,REF!$D$2:$D$12,REF!$E$2:$E$12) -> Rede | L227: Queda de energia na UFV Aracu, o relé de proteção atuou nas função 47, ocasionando a atuação do sistema de proteção. | M227: Falha Rede | N227: Distribuídora | O227: Realizada inspeção visual no sistema, sem identificação de anomalias. Posteriormente, foi efetuado o reset dos relés de proteção e o rearme da usina, normalizando sua operação. | P227: =_xlfn.CONCAT(B227,C227,D228,E227,F227) -> BC Camarao1.3215KTL-H3(MBUS-12)46088,385416666746088,385416666746088,4756944444 | Q227: =_xlfn.CONCAT(H227,I227,J227) -> DAURDE
B228: BC Camarao1.3 | C228: 215KTL-H3(MBUS-13) | D228: 46088.385 | E228: 46088.385 | F228: 46088.476 | G228: =F228-E228 -> 0.090277778 | H228: DAU | J228: RDE | K228: =_xlfn.XLOOKUP(J228,REF!$D$2:$D$12,REF!$E$2:$E$12) -> Rede | L228: Queda de energia na UFV Aracu, o relé de proteção atuou nas função 47, ocasionando a atuação do sistema de proteção. | M228: Falha Rede | N228: Distribuídora | O228: Realizada inspeção visual no sistema, sem identificação de anomalias. Posteriormente, foi efetuado o reset dos relés de proteção e o rearme da usina, normalizando sua operação. | P228: =_xlfn.CONCAT(B228,C228,#REF!,E228,F228) -> #REF! | Q228: =_xlfn.CONCAT(H228,I228,J228) -> DAURDE
B229: BC Ibiuna 1.1 | C229: Inverter(MBUS-12) | D229: 46088.733 | E229: 46088.733 | F229: 46088.89 | G229: =F229-E229 -> 0.15763889 | H229: DAU | J229: RDE | K229: =_xlfn.XLOOKUP(J229,REF!$D$2:$D$12,REF!$E$2:$E$12) -> Rede | L229: Queda de energia na UFV Ibiuna, o relé de proteção atuou na função 86, ocasionando a atuação do sistema de proteção. | M229: Falha Rede | N229: Distribuídora | O229: Realizada inspeção visual no sistema, sem identificação de anomalias. Posteriormente, foi efetuado o reset dos relés de proteção e o rearme da usina, normalizando sua operação. | P229: =_xlfn.CONCAT(B229,C229,D230,E229,F229) -> BC Ibiuna 1.1Inverter(MBUS-12)46088,732638888946088,732638888946088,8902777778 | Q229: =_xlfn.CONCAT(H229,I229,J229) -> DAURDE
B230: BC Ibiuna 1.1 | C230: Inverter(MBUS-13) | D230: 46088.733 | E230: 46088.733 | F230: 46088.89 | G230: =F230-E230 -> 0.15763889 | H230: DAU | J230: RDE | K230: =_xlfn.XLOOKUP(J230,REF!$D$2:$D$12,REF!$E$2:$E$12) -> Rede | L230: Queda de energia na UFV Ibiuna, o relé de proteção atuou na função 86, ocasionando a atuação do sistema de proteção. | M230: Falha Rede | N230: Distribuídora | O230: Realizada inspeção visual no sistema, sem identificação de anomalias. Posteriormente, foi efetuado o reset dos relés de proteção e o rearme da usina, normalizando sua operação. | P230: =_xlfn.CONCAT(B230,C230,D230,E230,F230) -> BC Ibiuna 1.1Inverter(MBUS-13)46088,732638888946088,732638888946088,8902777778 | Q230: =_xlfn.CONCAT(H230,I230,J230) -> DAURDE
B231: BC Ibiuna 1.1 | C231: Inverter(MBUS-14) | D231: 46088.733 | E231: 46088.733 | F231: 46088.89 | G231: =F231-E231 -> 0.15763889 | H231: DAU | J231: RDE | K231: =_xlfn.XLOOKUP(J231,REF!$D$2:$D$12,REF!$E$2:$E$12) -> Rede | L231: Queda de energia na UFV Ibiuna, o relé de proteção atuou na função 86, ocasionando a atuação do sistema de proteção. | M231: Falha Rede | N231: Distribuídora | O231: Realizada inspeção visual no sistema, sem identificação de anomalias. Posteriormente, foi efetuado o reset dos relés de proteção e o rearme da usina, normalizando sua operação. | P231: =_xlfn.CONCAT(B231,C231,D231,E231,F231) -> BC Ibiuna 1.1Inverter(MBUS-14)46088,732638888946088,732638888946088,8902777778 | Q231: =_xlfn.CONCAT(H231,I231,J231) -> DAURDE
B232: BC Ibiuna 1.1 | C232: Inverter(MBUS-15) | D232: 46088.733 | E232: 46088.733 | F232: 46088.89 | G232: =F232-E232 -> 0.15763889 | H232: DAU | J232: RDE | K232: =_xlfn.XLOOKUP(J232,REF!$D$2:$D$12,REF!$E$2:$E$12) -> Rede | L232: Queda de energia na UFV Ibiuna, o relé de proteção atuou na função 86, ocasionando a atuação do sistema de proteção. | M232: Falha Rede | N232: Distribuídora | O232: Realizada inspeção visual no sistema, sem identificação de anomalias. Posteriormente, foi efetuado o reset dos relés de proteção e o rearme da usina, normalizando sua operação. | P232: =_xlfn.CONCAT(B232,C232,D232,E232,F232) -> BC Ibiuna 1.1Inverter(MBUS-15)46088,732638888946088,732638888946088,8902777778 | Q232: =_xlfn.CONCAT(H232,I232,J232) -> DAURDE
B233: BC Camarao1.3 | C233: 215KTL-H3(MBUS-16) | D233: 46089.037 | E233: 46089.037 | F233: 46089.396 | G233: =F233-E233 -> 0.35902778 | H233: DAU | J233: RDE | K233: =_xlfn.XLOOKUP(J233,REF!$D$2:$D$12,REF!$E$2:$E$12) -> Rede | L233: O cliente 3 apresentou desligamento dos inversores devido à atuação do relé de proteção, que não registrou nenhum código de segurança. | M233: Falha Rede | N233: Distribuídora | O233: Realizada inspeção visual no sistema, sem identificação de anomalias. Posteriormente, foi efetuado o reset dos relés de proteção e o rearme da usina, normalizando sua operação. | P233: =_xlfn.CONCAT(B233,C233,D233,E233,F233) -> BC Camarao1.3215KTL-H3(MBUS-16)46089,036805555646089,036805555646089,3958333333 | Q233: =_xlfn.CONCAT(H233,I233,J233) -> DAURDE
B234: BC Camarao1.3 | C234: 215KTL-H3(MBUS-14) | D234: 46089.037 | E234: 46089.037 | F234: 46089.396 | G234: =F234-E234 -> 0.35902778 | H234: DAU | J234: RDE | K234: =_xlfn.XLOOKUP(J234,REF!$D$2:$D$12,REF!$E$2:$E$12) -> Rede | L234: O cliente 3 apresentou desligamento dos inversores devido à atuação do relé de proteção, que não registrou nenhum código de segurança. | M234: Falha Rede | N234: Distribuídora | O234: Realizada inspeção visual no sistema, sem identificação de anomalias. Posteriormente, foi efetuado o reset dos relés de proteção e o rearme da usina, normalizando sua operação. | P234: =_xlfn.CONCAT(B234,C234,D234,E234,F234) -> BC Camarao1.3215KTL-H3(MBUS-14)46089,036805555646089,036805555646089,3958333333 | Q234: =_xlfn.CONCAT(H234,I234,J234) -> DAURDE
B235: BC Camarao1.3 | C235: 215KTL-H3(MBUS-15) | D235: 46089.037 | E235: 46089.037 | F235: 46089.396 | G235: =F235-E235 -> 0.35902778 | H235: DAU | J235: RDE | K235: =_xlfn.XLOOKUP(J235,REF!$D$2:$D$12,REF!$E$2:$E$12) -> Rede | L235: O cliente 3 apresentou desligamento dos inversores devido à atuação do relé de proteção, que não registrou nenhum código de segurança. | M235: Falha Rede | N235: Distribuídora | O235: Realizada inspeção visual no sistema, sem identificação de anomalias. Posteriormente, foi efetuado o reset dos relés de proteção e o rearme da usina, normalizando sua operação. | P235: =_xlfn.CONCAT(B235,C235,D235,E235,F235) -> BC Camarao1.3215KTL-H3(MBUS-15)46089,036805555646089,036805555646089,3958333333 | Q235: =_xlfn.CONCAT(H235,I235,J235) -> DAURDE
B236: BC Camarao1.3 | C236: 215KTL-H3(MBUS-12) | D236: 46089.037 | E236: 46089.037 | F236: 46089.396 | G236: =F236-E236 -> 0.35902778 | H236: DAU | J236: RDE | K236: =_xlfn.XLOOKUP(J236,REF!$D$2:$D$12,REF!$E$2:$E$12) -> Rede | L236: O cliente 3 apresentou desligamento dos inversores devido à atuação do relé de proteção, que não registrou nenhum código de segurança. | M236: Falha Rede | N236: Distribuídora | O236: Realizada inspeção visual no sistema, sem identificação de anomalias. Posteriormente, foi efetuado o reset dos relés de proteção e o rearme da usina, normalizando sua operação. | P236: =_xlfn.CONCAT(B236,C236,D236,E236,F236) -> BC Camarao1.3215KTL-H3(MBUS-12)46089,036805555646089,036805555646089,3958333333 | Q236: =_xlfn.CONCAT(H236,I236,J236) -> DAURDE
B237: BC Camarao1.3 | C237: 215KTL-H3(MBUS-13) | D237: 46089.037 | E237: 46089.037 | F237: 46089.396 | G237: =F237-E237 -> 0.35902778 | H237: DAU | J237: RDE | K237: =_xlfn.XLOOKUP(J237,REF!$D$2:$D$12,REF!$E$2:$E$12) -> Rede | L237: O cliente 3 apresentou desligamento dos inversores devido à atuação do relé de proteção, que não registrou nenhum código de segurança. | M237: Falha Rede | N237: Distribuídora | O237: Realizada inspeção visual no sistema, sem identificação de anomalias. Posteriormente, foi efetuado o reset dos relés de proteção e o rearme da usina, normalizando sua operação. | P237: =_xlfn.CONCAT(B237,C237,D237,E237,F237) -> BC Camarao1.3215KTL-H3(MBUS-13)46089,036805555646089,036805555646089,3958333333 | Q237: =_xlfn.CONCAT(H237,I237,J237) -> DAURDE
B238: BC Vazante1.3 | C238: Inversor 1 | D238: 46089.049 | E238: 46089.049 | F238: 46089.26 | G238: =F238-E238 -> 0.21180556 | H238: LIG | I238: RFO | J238: INT | K238: =_xlfn.XLOOKUP(J238,REF!$D$2:$D$12,REF!$E$2:$E$12) -> Internet | L238: Indisponibilidade de comunicação devido a problema no provedor de internet. | M238: Conexão c/ Internet | N238: Auto-Restart | O238: A comunicação da UFV foi restabelecida automaticamente, retornando à operação normal. | P238: =_xlfn.CONCAT(B238,C238,D239,E238,F238) -> BC Vazante1.3Inversor 146089,228472222246089,048611111146089,2604166667 | Q238: =_xlfn.CONCAT(H238,I238,J238) -> LIGRFOINT
B239: BC Ibiuna 1.1 | C239: Inverter(MBUS-12) | D239: 46089.228 | E239: 46089.228 | F239: 46089.411 | G239: =F239-E239 -> 0.18263889 | H239: DAU | J239: RDE | K239: =_xlfn.XLOOKUP(J239,REF!$D$2:$D$12,REF!$E$2:$E$12) -> Rede | L239: Queda de energia na UFV Ibiuna, o relé de proteção atuou na função 86, ocasionando a atuação do sistema de proteção. | M239: Falha Rede | N239: Distribuídora | O239: Realizada inspeção visual no sistema, sem identificação de anomalias. Posteriormente, foi efetuado o reset dos relés de proteção e o rearme da usina, normalizando sua operação. | P239: =_xlfn.CONCAT(B239,C239,D239,E239,F239) -> BC Ibiuna 1.1Inverter(MBUS-12)46089,228472222246089,228472222246089,4111111111 | Q239: =_xlfn.CONCAT(H239,I239,J239) -> DAURDE
...

Sheet Fevereiro 2026
A1: UC | B1: UFV | C1: Tag | D1: Início Real do Evento | E1: Início | F1: Fim | G1: Duração | H1: Estado Operativo | I1: Condição Operativa | J1: Origem | K1: Equipamento | L1: Causa | M1: Causas Padrão | N1: Resolução | O1: Observação | P1: Concat - duplicata | Q1: Combinação
B2: BC Aracu5.2 | C2: Inverter(MBUS-1) | D2: 46027.385 | E2: 46054 | F2: 46081.999 | G2: 27.999988 | H2: DEM | J2: TRF | K2: Transformador | L2: Inversor 1 apresentou falha. Ao realizar a análise em campo, verificou-se curto circuito em uma das fases do trafo. | M2: Falha Inversor | N2: Prestador de Serviço O&M | O2: Após a retirada das strings que estavam em curto, foi realizado os testes e normalizado o inversor que segue operando sem anomalia. As strings serão reconectadas após realização de correção das strings. | P2: =_xlfn.CONCAT(B2,C2,D2,E2,F2) -> BC Aracu5.2Inverter(MBUS-1)46027,38541666674605446081,9993055556 | Q2: =_xlfn.CONCAT(H2,I2,J2) -> DEMTRF
B3: BC Aracu5.3 | C3: Inverter(MBUS-1) | D3: 46050.361 | E3: 46054 | F3: 46081.999 | G3: 27.999988 | H3: LIG | I3: RFO | J3: COM | K3: Comunicação | L3: Falha de comunicação | M3: Falha Rede | N3: Distribuidora | O3: Foi feito inspeção em todo complexo, checado nível de tensão e resetado relé e rearmado os disjuntores. | P3: =_xlfn.CONCAT(B3,C3,D3,E3,F3) -> BC Aracu5.3Inverter(MBUS-1)46050,36111111114605446081,9993055556 | Q3: =_xlfn.CONCAT(H3,I3,J3) -> LIGRFOCOM
B4: BC Turvania1.3 | C4: Inverter(MBUS-13) | D4: 46054.273 | E4: 46054.273 | F4: 46054.434 | G4: 0.16111111 | H4: DAU | J4: INV | K4: Inversor | L4: Inversor acusou falha de baixa impedância de isolamento, inicialmente, precedida das falhas de falha de energia de rede elétrica (indicando desligamento do inversor) e entrada DC é anormal (indicando anormalidade em algum componente CC). Durante inspeção em campo foi identificado que três strings do inversor estavam em curto. | M4: Falha Comunicação | N4: Auto-Restart | O4: Foi normalizado por si só. | P4: =_xlfn.CONCAT(B4,C4,D4,E4,F4) -> BC Turvania1.3Inverter(MBUS-13)46054,272916666746054,272916666746054,4340277778 | Q4: =_xlfn.CONCAT(H4,I4,J4) -> DAUINV
B5: BC Turvania1.3 | C5: Inverter(MBUS-13) | D5: 46054.434 | E5: 46054.434 | F5: 46081.999 | G5: 27.565961 | H5: LIG | I5: RFO | J5: STR | K5: String | L5: Inversor acusou falha de baixa impedância de isolamento, inicialmente, precedida das falhas de falha de energia de rede elétrica (indicando desligamento do inversor) e entrada DC é anormal (indicando anormalidade em algum componente CC). Durante inspeção em campo foi identificado que três strings do inversor estavam em curto. Strings ainda estão fora de operação. | M5: Falha Comunicação | N5: Auto-Restart | O5: Foi normalizado por si só. | P5: =_xlfn.CONCAT(B5,C5,D5,E5,F5) -> BC Turvania1.3Inverter(MBUS-13)46054,434027777846054,434027777846081,9993055556 | Q5: =_xlfn.CONCAT(H5,I5,J5) -> LIGRFOSTR
B6: BC Aracu5.1 | C6: Inverter(MBUS-1) | D6: 46054.36 | E6: 46054.36 | F6: 46054.387 | G6: 0.027083333 | H6: DAU | J6: RDE | K6: Rede | L6: Função 81 e 86 atuada no relé. | M6: Falha Comunicação | N6: Auto-Restart | O6: Foi normalizado por si só. | P6: =_xlfn.CONCAT(B6,C6,D6,E6,F6) -> BC Aracu5.1Inverter(MBUS-1)46054,360416666746054,360416666746054,3875 | Q6: =_xlfn.CONCAT(H6,I6,J6) -> DAURDE
B7: BC Aracu5.3 | C7: Inverter(MBUS-1) | D7: 46054.36 | E7: 46054.36 | F7: 46054.387 | G7: 0.027083333 | H7: DAU | J7: RDE | K7: Rede | L7: Função 81 e 86 atuada no relé. | M7: Falha Comunicação | N7: Auto-Restart | O7: Foi normalizado por si só. | P7: =_xlfn.CONCAT(B7,C7,D7,E7,F7) -> BC Aracu5.3Inverter(MBUS-1)46054,360416666746054,360416666746054,3875 | Q7: =_xlfn.CONCAT(H7,I7,J7) -> DAURDE
B8: BC Aracu5.4 | C8: Inverter(MBUS-1) | D8: 46054.36 | E8: 46054.36 | F8: 46054.387 | G8: 0.027083333 | H8: DAU | J8: RDE | K8: Rede | L8: Função 81 e 86 atuada no relé. | M8: Falha Comunicação | N8: Auto-Restart | O8: Foi normalizado por si só. | P8: =_xlfn.CONCAT(B8,C8,D8,E8,F8) -> BC Aracu5.4Inverter(MBUS-1)46054,360416666746054,360416666746054,3875 | Q8: =_xlfn.CONCAT(H8,I8,J8) -> DAURDE
B9: BC Aracu5.5 | C9: Inverter(MBUS-1) | D9: 46054.36 | E9: 46054.36 | F9: 46054.387 | G9: 0.027083333 | H9: DAU | J9: RDE | K9: Rede | L9: Função 81 e 86 atuada no relé. | M9: Falha Rede | N9: Distribuidora | O9: Foi feito inspeção em todo complexo, checado nível de tensão e resetado relé e rearmado os disjuntores. | P9: =_xlfn.CONCAT(B9,C9,D9,E9,F9) -> BC Aracu5.5Inverter(MBUS-1)46054,360416666746054,360416666746054,3875 | Q9: =_xlfn.CONCAT(H9,I9,J9) -> DAURDE
B10: BC Corumba2.2 | C10: U02.I01 | D10: 46054.384 | E10: 46054.384 | F10: 46054.417 | G10: 0.032638889 | H10: DAU | I10: RFO | J10: COM | K10: Comunicação | L10: Falha de comunicação no Smart Logger | M10: Falha Rede | N10: Distribuidora | O10: Inspecionado todo complexo, não foi identificado nenhuma anomalia, foi rearmado o disjuntor | P10: =_xlfn.CONCAT(B10,C10,D10,E10,F10) -> BC Corumba2.2U02.I0146054,384027777846054,384027777846054,4166666667 | Q10: =_xlfn.CONCAT(H10,I10,J10) -> DAURFOCOM
B11: BC Corumba2.2 | C11: U02.I02 | D11: 46054.384 | E11: 46054.384 | F11: 46054.417 | G11: 0.032638889 | H11: DAU | I11: RFO | J11: COM | K11: Comunicação | L11: Falha de comunicação no Smart Logger | M11: Falha Rede | N11: Distribuidora | O11: Inspecionado todo complexo, não foi identificado nenhuma anomalia, foi rearmado o disjuntor | P11: =_xlfn.CONCAT(B11,C11,D11,E11,F11) -> BC Corumba2.2U02.I0246054,384027777846054,384027777846054,4166666667 | Q11: =_xlfn.CONCAT(H11,I11,J11) -> DAURFOCOM
B12: BC Corumba2.2 | C12: U02.I03 | D12: 46054.384 | E12: 46054.384 | F12: 46054.417 | G12: 0.032638889 | H12: DAU | I12: RFO | J12: COM | K12: Comunicação | L12: Falha de comunicação no Smart Logger | M12: Falha Rede | N12: Distribuidora | O12: Inspecionado todo complexo, não foi identificado nenhuma anomalia, foi rearmado o disjuntor | P12: =_xlfn.CONCAT(B12,C12,D12,E12,F12) -> BC Corumba2.2U02.I0346054,384027777846054,384027777846054,4166666667 | Q12: =_xlfn.CONCAT(H12,I12,J12) -> DAURFOCOM
B13: BC Corumba2.2 | C13: U02.I04 | D13: 46054.384 | E13: 46054.384 | F13: 46054.417 | G13: 0.032638889 | H13: DAU | I13: RFO | J13: COM | K13: Comunicação | L13: Falha de comunicação no Smart Logger | M13: Falha Rede | N13: Distribuidora | O13: Inspecionado todo complexo, não foi identificado nenhuma anomalia, foi rearmado o disjuntor | P13: =_xlfn.CONCAT(B13,C13,D13,E13,F13) -> BC Corumba2.2U02.I0446054,384027777846054,384027777846054,4166666667 | Q13: =_xlfn.CONCAT(H13,I13,J13) -> DAURFOCOM
B14: BC Corumba2.2 | C14: U02.I05 | D14: 46054.384 | E14: 46054.384 | F14: 46054.417 | G14: 0.032638889 | H14: DAU | I14: RFO | J14: COM | K14: Comunicação | L14: Falha de comunicação no Smart Logger | M14: Falha Inversor | N14: Troca em Garantia | O14: Aguardando a garantia para efetuar a reposição do inversor | P14: =_xlfn.CONCAT(B14,C14,D14,E14,F14) -> BC Corumba2.2U02.I0546054,384027777846054,384027777846054,4166666667 | Q14: =_xlfn.CONCAT(H14,I14,J14) -> DAURFOCOM
B15: BC Vazante 1.1 | C15: Inverter12 | D15: 46054.415 | E15: 46054.415 | F15: 46054.443 | G15: 0.028472222 | H15: DAU | J15: RDE | K15: Rede | L15: Trip no disjuntor | M15: Manutenção | N15: Manutenção Corretiva | O15: Feita a manutenção do curto circuito. Inspecionado todo o complexo, tirado a oscilografia do relé de proteção. | P15: =_xlfn.CONCAT(B15,C15,D15,E15,F15) -> BC Vazante 1.1Inverter1246054,414583333346054,414583333346054,4430555556 | Q15: =_xlfn.CONCAT(H15,I15,J15) -> DAURDE
B16: ARAGUATINS 2.1 | C16: Inverter(MBUS-12) | D16: 46054.417 | E16: 46054.417 | F16: 46054.74 | G16: 0.32291667 | H16: DAU | J16: RDE | K16: Rede | L16: Queda de rede, sem função ativa no relé de proteção. Alarme 2032, indicando que a rede elétrica sofre uma interrupção ou o circuito CA está desconectado ou o disjuntor CA está desligado. | M16: Manutenção | N16: Manutenção Corretiva | O16: Feita a manutenção do curto circuito. Inspecionado todo o complexo, tirado a oscilografia do relé de proteção. | P16: =_xlfn.CONCAT(B16,C16,D16,E16,F16) -> ARAGUATINS 2.1Inverter(MBUS-12)46054,416666666746054,416666666746054,7395833333 | Q16: =_xlfn.CONCAT(H16,I16,J16) -> DAURDE
B17: ARAGUATINS 2.1 | C17: Inverter(MBUS-15) | D17: 46054.417 | E17: 46054.417 | F17: 46054.74 | G17: 0.32291667 | H17: DAU | J17: RDE | K17: Rede | L17: Queda de rede, sem função ativa no relé de proteção. Alarme 2032, indicando que a rede elétrica sofre uma interrupção ou o circuito CA está desconectado ou o disjuntor CA está desligado. | M17: Manutenção | N17: Manutenção Corretiva | O17: Feita a manutenção do curto circuito. Inspecionado todo o complexo, tirado a oscilografia do relé de proteção. | P17: =_xlfn.CONCAT(B17,C17,D17,E17,F17) -> ARAGUATINS 2.1Inverter(MBUS-15)46054,416666666746054,416666666746054,7395833333 | Q17: =_xlfn.CONCAT(H17,I17,J17) -> DAURDE
B18: ARAGUATINS 2.1 | C18: Inverter(MBUS-14) | D18: 46054.417 | E18: 46054.417 | F18: 46054.74 | G18: 0.32291667 | H18: DAU | J18: RDE | K18: Rede | L18: Queda de rede, sem função ativa no relé de proteção. Alarme 2032, indicando que a rede elétrica sofre uma interrupção ou o circuito CA está desconectado ou o disjuntor CA está desligado. | M18: Manutenção | N18: Manutenção Corretiva | O18: Feita a manutenção do curto circuito. Inspecionado todo o complexo, tirado a oscilografia do relé de proteção. | P18: =_xlfn.CONCAT(B18,C18,D18,E18,F18) -> ARAGUATINS 2.1Inverter(MBUS-14)46054,416666666746054,416666666746054,7395833333 | Q18: =_xlfn.CONCAT(H18,I18,J18) -> DAURDE
B19: ARAGUATINS 2.1 | C19: Inverter(MBUS-1) | D19: 46054.417 | E19: 46054.417 | F19: 46054.74 | G19: 0.32291667 | H19: DAU | J19: RDE | K19: Rede | L19: Queda de rede, sem função ativa no relé de proteção. Alarme 2032, indicando que a rede elétrica sofre uma interrupção ou o circuito CA está desconectado ou o disjuntor CA está desligado. | M19: Falha Comunicação | N19: Prestador de Serviço O&M | O19: Feito uma avaliação em todo o complexo, e identificado que o problema estava relacionado a comunicação. Após reiniciar o sistema, os inversores voltaram a comunicar no supervisorio | P19: =_xlfn.CONCAT(B19,C19,D19,E19,F19) -> ARAGUATINS 2.1Inverter(MBUS-1)46054,416666666746054,416666666746054,7395833333 | Q19: =_xlfn.CONCAT(H19,I19,J19) -> DAURDE
B20: BC Varjao1.3 | C20: 215KTL-H0(MBUS-14) | D20: 46055.299 | E20: 46055.299 | F20: 46081.999 | G20: 26.701377 | H20: LIG | I20: RFO | J20: INV | K20: Inversor | L20: Inversor com alarme acionado (2064), oscilando geração e não atinge potência nominal. Em tratativa sob o chamado 15218400. A Equipe de O&M está aguardando a emissão de notas de remessa pendentes para a huawei, com mais de 100 dias de atraso. Por conta dos atrasos, a huawei responde que "Em caso da falta de retorno das peças defeituosas em 30 dias o cliente estará sujeito a suspensão do envio de novas peças em garantias futuras. Caso o equipamento não seja devolvido dentro deste período, a Huawei reserva-se o direito de cobrar o preço de compra do produto / peças fornecido, degradar o SLA ou até mesmo parar com o envio de peças sobressalentes.". | M20: Falha Comunicação | N20: Prestador de Serviço O&M | O20: Feito uma avaliação em todo o complexo, e identificado que o problema estava relacionado a comunicação. Após reiniciar o sistema, os inversores voltaram a comunicar no supervisorio | P20: =_xlfn.CONCAT(B20,C20,D20,E20,F20) -> BC Varjao1.3215KTL-H0(MBUS-14)46055,298611111146055,298611111146081,9993055556 | Q20: =_xlfn.CONCAT(H20,I20,J20) -> LIGRFOINV
B21: ARAGUATINS 2.1 | C21: Inverter(MBUS-12) | D21: 46055.351 | E21: 46055.351 | F21: 46055.503 | G21: 0.15277778 | H21: DAU | J21: UFV | K21: UFV | L21: Desarme, sem nenhuma função ativa no relé de proteção. Identificado curto circuito na regua do borne do circuito de iluminação. | M21: Falha Comunicação | N21: Prestador de Serviço O&M | O21: Feito uma avaliação em todo o complexo, e identificado que o problema estava relacionado a comunicação. Após reiniciar o sistema, os inversores voltaram a comunicar no supervisorio | P21: =_xlfn.CONCAT(B21,C21,D21,E21,F21) -> ARAGUATINS 2.1Inverter(MBUS-12)46055,350694444446055,350694444446055,5034722222 | Q21: =_xlfn.CONCAT(H21,I21,J21) -> DAUUFV
B22: ARAGUATINS 2.1 | C22: Inverter(MBUS-15) | D22: 46055.351 | E22: 46055.351 | F22: 46055.503 | G22: 0.15277778 | H22: DAU | J22: UFV | K22: UFV | L22: Desarme, sem nenhuma função ativa no relé de proteção. Identificado curto circuito na regua do borne do circuito de iluminação. | M22: Falha Comunicação | N22: Prestador de Serviço O&M | O22: Feito uma avaliação em todo o complexo, e identificado que o problema estava relacionado a comunicação. Após reiniciar o sistema, os inversores voltaram a comunicar no supervisorio | P22: =_xlfn.CONCAT(B22,C22,D22,E22,F22) -> ARAGUATINS 2.1Inverter(MBUS-15)46055,350694444446055,350694444446055,5034722222 | Q22: =_xlfn.CONCAT(H22,I22,J22) -> DAUUFV
B23: ARAGUATINS 2.1 | C23: Inverter(MBUS-14) | D23: 46055.351 | E23: 46055.351 | F23: 46055.503 | G23: 0.15277778 | H23: DAU | J23: UFV | K23: UFV | L23: Desarme, sem nenhuma função ativa no relé de proteção. Identificado curto circuito na regua do borne do circuito de iluminação. | M23: Falha Comunicação | N23: Prestador de Serviço O&M | O23: Feito uma avaliação em todo o complexo, e identificado que o problema estava relacionado a comunicação. Após reiniciar o sistema, os inversores voltaram a comunicar no supervisorio | P23: =_xlfn.CONCAT(B23,C23,D23,E23,F23) -> ARAGUATINS 2.1Inverter(MBUS-14)46055,350694444446055,350694444446055,5034722222 | Q23: =_xlfn.CONCAT(H23,I23,J23) -> DAUUFV
B24: ARAGUATINS 2.1 | C24: Inverter(MBUS-1) | D24: 46055.351 | E24: 46055.351 | F24: 46055.503 | G24: 0.15277778 | H24: DAU | J24: UFV | K24: UFV | L24: Desarme, sem nenhuma função ativa no relé de proteção. Identificado curto circuito na regua do borne do circuito de iluminação. | M24: Falha Comunicação | N24: Prestador de Serviço O&M | O24: Feito uma avaliação em todo o complexo, e identificado que o problema estava relacionado a comunicação. Após reiniciar o sistema, os inversores voltaram a comunicar no supervisorio | P24: =_xlfn.CONCAT(B24,C24,D24,E24,F24) -> ARAGUATINS 2.1Inverter(MBUS-1)46055,350694444446055,350694444446055,5034722222 | Q24: =_xlfn.CONCAT(H24,I24,J24) -> DAUUFV
B25: BC Bom Sucesso | C25: SG60KTL | D25: 46055.382 | E25: 46055.382 | F25: 46055.447 | G25: 0.064583333 | H25: DAU | I25: RFO | J25: COM | K25: Comunicação | L25: Foi identificado que o supervisório e as câmeras estão funcionando parcialmente, câmeras ativas 2-6-10 | M25: Falha Comunicação | N25: Prestador de Serviço O&M | O25: Feito uma avaliação em todo o complexo, e identificado que o problema estava relacionado a comunicação. Após reiniciar o sistema, os inversores voltaram a comunicar no supervisorio | P25: =_xlfn.CONCAT(B25,C25,D25,E25,F25) -> BC Bom SucessoSG60KTL46055,381944444446055,381944444446055,4465277778 | Q25: =_xlfn.CONCAT(H25,I25,J25) -> DAURFOCOM
B26: BC Bom Sucesso | C26: I | D26: 46055.382 | E26: 46055.382 | F26: 46055.447 | G26: 0.064583333 | H26: DAU | I26: RFO | J26: COM | K26: Comunicação | L26: Foi identificado que o supervisório e as câmeras estão funcionando parcialmente, câmeras ativas 2-6-10 | M26: Falha Comunicação | N26: Prestador de Serviço O&M | O26: Feito uma avaliação em todo o complexo, e identificado que o problema estava relacionado a comunicação. Após reiniciar o sistema, os inversores voltaram a comunicar no supervisorio | P26: =_xlfn.CONCAT(B26,C26,D26,E26,F26) -> BC Bom SucessoI46055,381944444446055,381944444446055,4465277778 | Q26: =_xlfn.CONCAT(H26,I26,J26) -> DAURFOCOM
B27: BC Bom Sucesso | C27: G | D27: 46055.382 | E27: 46055.382 | F27: 46055.447 | G27: 0.064583333 | H27: DAU | I27: RFO | J27: COM | K27: Comunicação | L27: Foi identificado que o supervisório e as câmeras estão funcionando parcialmente, câmeras ativas 2-6-10 | M27: Falha Comunicação | N27: Prestador de Serviço O&M | O27: Feito uma avaliação em todo o complexo, e identificado que o problema estava relacionado a comunicação. Após reiniciar o sistema, os inversores voltaram a comunicar no supervisorio | P27: =_xlfn.CONCAT(B27,C27,D27,E27,F27) -> BC Bom SucessoG46055,381944444446055,381944444446055,4465277778 | Q27: =_xlfn.CONCAT(H27,I27,J27) -> DAURFOCOM
B28: BC Bom Sucesso | C28: K | D28: 46055.382 | E28: 46055.382 | F28: 46055.447 | G28: 0.064583333 | H28: DAU | I28: RFO | J28: COM | K28: Comunicação | L28: Foi identificado que o supervisório e as câmeras estão funcionando parcialmente, câmeras ativas 2-6-10 | M28: Falha Comunicação | N28: Prestador de Serviço O&M | O28: Feito uma avaliação em todo o complexo, e identificado que o problema estava relacionado a comunicação. Após reiniciar o sistema, os inversores voltaram a comunicar no supervisorio | P28: =_xlfn.CONCAT(B28,C28,D28,E28,F28) -> BC Bom SucessoK46055,381944444446055,381944444446055,4465277778 | Q28: =_xlfn.CONCAT(H28,I28,J28) -> DAURFOCOM
B29: BC Bom Sucesso | C29: H | D29: 46055.382 | E29: 46055.382 | F29: 46055.447 | G29: 0.064583333 | H29: DAU | I29: RFO | J29: COM | K29: Comunicação | L29: Foi identificado que o supervisório e as câmeras estão funcionando parcialmente, câmeras ativas 2-6-10 | M29: Falha Comunicação | N29: Prestador de Serviço O&M | O29: Feito uma avaliação em todo o complexo, e identificado que o problema estava relacionado a comunicação. Após reiniciar o sistema, os inversores voltaram a comunicar no supervisorio | P29: =_xlfn.CONCAT(B29,C29,D29,E29,F29) -> BC Bom SucessoH46055,381944444446055,381944444446055,4465277778 | Q29: =_xlfn.CONCAT(H29,I29,J29) -> DAURFOCOM
B30: BC Bom Sucesso | C30: F | D30: 46055.382 | E30: 46055.382 | F30: 46055.447 | G30: 0.064583333 | H30: DAU | I30: RFO | J30: COM | K30: Comunicação | L30: Foi identificado que o supervisório e as câmeras estão funcionando parcialmente, câmeras ativas 2-6-10 | M30: Falha Comunicação | N30: Prestador de Serviço O&M | O30: Feito uma avaliação em todo o complexo, e identificado que o problema estava relacionado a comunicação. Após reiniciar o sistema, os inversores voltaram a comunicar no supervisorio | P30: =_xlfn.CONCAT(B30,C30,D30,E30,F30) -> BC Bom SucessoF46055,381944444446055,381944444446055,4465277778 | Q30: =_xlfn.CONCAT(H30,I30,J30) -> DAURFOCOM
B31: BC Bom Sucesso | C31: D | D31: 46055.382 | E31: 46055.382 | F31: 46055.447 | G31: 0.064583333 | H31: DAU | I31: RFO | J31: COM | K31: Comunicação | L31: Foi identificado que o supervisório e as câmeras estão funcionando parcialmente, câmeras ativas 2-6-10 | M31: Falha Comunicação | N31: Prestador de Serviço O&M | O31: Foi feito uma inspeçao no CFTV no roteador e no suite, foi constatado problema de comunicação - queda de internet | P31: =_xlfn.CONCAT(B31,C31,D31,E31,F31) -> BC Bom SucessoD46055,381944444446055,381944444446055,4465277778 | Q31: =_xlfn.CONCAT(H31,I31,J31) -> DAURFOCOM
B32: BC Bom Sucesso | C32: E | D32: 46055.382 | E32: 46055.382 | F32: 46055.447 | G32: 0.064583333 | H32: DAU | I32: RFO | J32: COM | K32: Comunicação | L32: Foi identificado que o supervisório e as câmeras estão funcionando parcialmente, câmeras ativas 2-6-10 | M32: Falha Comunicação | N32: Prestador de Serviço O&M | O32: Foi feito uma inspeçao no CFTV no roteador e no suite, foi constatado problema de comunicação - queda de internet | P32: =_xlfn.CONCAT(B32,C32,D32,E32,F32) -> BC Bom SucessoE46055,381944444446055,381944444446055,4465277778 | Q32: =_xlfn.CONCAT(H32,I32,J32) -> DAURFOCOM
B33: BC Bom Sucesso | C33: C | D33: 46055.382 | E33: 46055.382 | F33: 46055.447 | G33: 0.064583333 | H33: DAU | I33: RFO | J33: COM | K33: Comunicação | L33: Foi identificado que o supervisório e as câmeras estão funcionando parcialmente, câmeras ativas 2-6-10 | M33: Falha Comunicação | N33: Prestador de Serviço O&M | O33: Foi feito uma inspeçao no CFTV no roteador e no suite, foi constatado problema de comunicação - queda de internet | P33: =_xlfn.CONCAT(B33,C33,D33,E33,F33) -> BC Bom SucessoC46055,381944444446055,381944444446055,4465277778 | Q33: =_xlfn.CONCAT(H33,I33,J33) -> DAURFOCOM
B34: BC Bom Sucesso | C34: B | D34: 46055.382 | E34: 46055.382 | F34: 46055.447 | G34: 0.064583333 | H34: DAU | I34: RFO | J34: COM | K34: Comunicação | L34: Foi identificado que o supervisório e as câmeras estão funcionando parcialmente, câmeras ativas 2-6-10 | M34: Falha Comunicação | N34: Prestador de Serviço O&M | O34: Foi feito uma inspeçao no CFTV no roteador e no suite, foi constatado problema de comunicação - queda de internet | P34: =_xlfn.CONCAT(B34,C34,D34,E34,F34) -> BC Bom SucessoB46055,381944444446055,381944444446055,4465277778 | Q34: =_xlfn.CONCAT(H34,I34,J34) -> DAURFOCOM
B35: BC Bom Sucesso | C35: A | D35: 46055.382 | E35: 46055.382 | F35: 46055.447 | G35: 0.064583333 | H35: DAU | I35: RFO | J35: COM | K35: Comunicação | L35: Foi identificado que o supervisório e as câmeras estão funcionando parcialmente, câmeras ativas 2-6-10 | M35: Falha Comunicação | N35: Prestador de Serviço O&M | O35: Foi feito uma inspeçao no CFTV no roteador e no suite, foi constatado problema de comunicação - queda de internet | P35: =_xlfn.CONCAT(B35,C35,D35,E35,F35) -> BC Bom SucessoA46055,381944444446055,381944444446055,4465277778 | Q35: =_xlfn.CONCAT(H35,I35,J35) -> DAURFOCOM
B36: BC Bom Sucesso | C36: J | D36: 46055.382 | E36: 46055.382 | F36: 46055.447 | G36: 0.064583333 | H36: DAU | I36: RFO | J36: COM | K36: Comunicação | L36: Foi identificado que o supervisório e as câmeras estão funcionando parcialmente, câmeras ativas 2-6-10 | M36: Manutenção | N36: Manutenção Preventiva | O36: Foi realizado limpeza nos coolers e nos inversores | P36: =_xlfn.CONCAT(B36,C36,D36,E36,F36) -> BC Bom SucessoJ46055,381944444446055,381944444446055,4465277778 | Q36: =_xlfn.CONCAT(H36,I36,J36) -> DAURFOCOM
... B40: BC Aracu5.5 | C40: Inverter(MBUS-1) | D40: 46055.389 | E40: 46055.389 | F40: 46055.457 | G40: 0.068055556 | H40: DAU | I40: RFO | J40: INT | K40: Internet | L40: Foi identificado no supervisório que todos as câmeras e inversores estão Off-line | M40: Falha Rede | N40: Distribuidora | O40: Normalizou sozinho com o retorno da energia | P40: =_xlfn.CONCAT(B40,C40,D40,E40,F40) -> BC Aracu5.5Inverter(MBUS-1)46055,388888888946055,388888888946055,4569444444 | Q40: =_xlfn.CONCAT(H40,I40,J40) -> DAURFOINT
B41: BC Aracu4 | C41: SG75CX(COM1-018)_001_018 | D41: 46055.667 | E41: 46055.667 | F41: 46055.715 | G41: 0.047916667 | H41: DPR | J41: INV | K41: Inversor | L41: Desligamento programado para manutenção preventiva nos inversores. | M41: Falha Rede | N41: Distribuidora | O41: Normalizou sozinho com o retorno da energia | P41: =_xlfn.CONCAT(B41,C41,D41,E41,F41) -> BC Aracu4SG75CX(COM1-018)_001_01846055,666666666746055,666666666746055,7145833333 | Q41: =_xlfn.CONCAT(H41,I41,J41) -> DPRINV
B42: BC Aracu4 | C42: SG75CX(COM1-019)_001_019 | D42: 46055.667 | E42: 46055.667 | F42: 46055.715 | G42: 0.047916667 | H42: DPR | J42: INV | K42: Inversor | L42: Desligamento programado para manutenção preventiva nos inversores. | M42: Falha Rede | N42: Distribuidora | O42: Normalizou sozinho com o retorno da energia | P42: =_xlfn.CONCAT(B42,C42,D42,E42,F42) -> BC Aracu4SG75CX(COM1-019)_001_01946055,666666666746055,666666666746055,7145833333 | Q42: =_xlfn.CONCAT(H42,I42,J42) -> DPRINV
B43: BC Aracu4 | C43: SG75CX(COM1-020)_001_020 | D43: 46055.667 | E43: 46055.667 | F43: 46055.715 | G43: 0.047916667 | H43: DPR | J43: INV | K43: Inversor | L43: Desligamento programado para manutenção preventiva nos inversores. | M43: Falha Rede | N43: Distribuidora | O43: Normalizou sozinho com o retorno da energia | P43: =_xlfn.CONCAT(B43,C43,D43,E43,F43) -> BC Aracu4SG75CX(COM1-020)_001_02046055,666666666746055,666666666746055,7145833333 | Q43: =_xlfn.CONCAT(H43,I43,J43) -> DPRINV
B44: BC Aracu4 | C44: SG75CX(COM1-021)_001_021 | D44: 46055.667 | E44: 46055.667 | F44: 46055.715 | G44: 0.047916667 | H44: DPR | J44: INV | K44: Inversor | L44: Desligamento programado para manutenção preventiva nos inversores. | M44: Falha Rede | N44: Distribuidora | O44: Normalizou sozinho com o retorno da energia | P44: =_xlfn.CONCAT(B44,C44,D44,E44,F44) -> BC Aracu4SG75CX(COM1-021)_001_02146055,666666666746055,666666666746055,7145833333 | Q44: =_xlfn.CONCAT(H44,I44,J44) -> DPRINV
B45: BC Panama1.1 | C45: ITAPOAN 001 (COM1-001)_001_001 | D45: 46055.826 | E45: 46055.826 | F45: 46055.955 | G45: 0.12847222 | H45: DAU | J45: RDE | K45: Rede | L45: Queda de rede da concessionária. | M45: Falha Rede | N45: Distribuidora | O45: Normalizou sozinho com o retorno da energia | P45: =_xlfn.CONCAT(B45,C45,D45,E45,F45) -> BC Panama1.1ITAPOAN 001 (COM1-001)_001_00146055,826388888946055,826388888946055,9548611111 | Q45: =_xlfn.CONCAT(H45,I45,J45) -> DAURDE
B46: BC Panama1.1 | C46: CEREAL_002 | D46: 46055.826 | E46: 46055.826 | F46: 46055.955 | G46: 0.12847222 | H46: DAU | J46: RDE | K46: Rede | L46: Queda de rede da concessionária. | M46: Falha Rede | N46: Distribuidora | O46: Normalizou sozinho com o retorno da energia | P46: =_xlfn.CONCAT(B46,C46,D46,E46,F46) -> BC Panama1.1CEREAL_00246055,826388888946055,826388888946055,9548611111 | Q46: =_xlfn.CONCAT(H46,I46,J46) -> DAURDE
B47: BC Panama1.1 | C47: ITAPOAN_003 | D47: 46055.826 | E47: 46055.826 | F47: 46055.955 | G47: 0.12847222 | H47: DAU | J47: RDE | K47: Rede | L47: Queda de rede da concessionária. | M47: Falha Rede | N47: Distribuidora | O47: Foi feito inspeção em todo complexo, checado nível de tensão e resetado relé e rearmado os disjuntores. | P47: =_xlfn.CONCAT(B47,C47,D47,E47,F47) -> BC Panama1.1ITAPOAN_00346055,826388888946055,826388888946055,9548611111 | Q47: =_xlfn.CONCAT(H47,I47,J47) -> DAURDE
B48: BC Panama1.2 | C48: ART_004 | D48: 46055.826 | E48: 46055.826 | F48: 46055.955 | G48: 0.12847222 | H48: DAU | J48: RDE | K48: Rede | L48: Queda de rede da concessionária. | M48: Falha Rede | N48: Distribuidora | O48: Foi feito inspeção em todo complexo, checado nível de tensão e resetado relé e rearmado os disjuntores. | P48: =_xlfn.CONCAT(B48,C48,D48,E48,F48) -> BC Panama1.2ART_00446055,826388888946055,826388888946055,9548611111 | Q48: =_xlfn.CONCAT(H48,I48,J48) -> DAURDE
B49: BC Panama1.2 | C49: COOGED_005 | D49: 46055.826 | E49: 46055.826 | F49: 46055.955 | G49: 0.12847222 | H49: DAU | J49: RDE | K49: Rede | L49: Queda de rede da concessionária. | M49: Falha Rede | N49: Distribuidora | O49: Foi feito inspeção em todo complexo, checado nível de tensão e resetado relé e rearmado os disjuntores. | P49: =_xlfn.CONCAT(B49,C49,D49,E49,F49) -> BC Panama1.2COOGED_00546055,826388888946055,826388888946055,9548611111 | Q49: =_xlfn.CONCAT(H49,I49,J49) -> DAURDE
B50: BC Panama1.2 | C50: ART_006 | D50: 46055.826 | E50: 46055.826 | F50: 46055.955 | G50: 0.12847222 | H50: DAU | J50: RDE | K50: Rede | L50: Queda de rede da concessionária. | M50: Falha Rede | N50: Distribuidora | O50: Foi feito inspeção em todo complexo, checado nível de tensão e resetado relé e rearmado os disjuntores. | P50: =_xlfn.CONCAT(B50,C50,D50,E50,F50) -> BC Panama1.2ART_00646055,826388888946055,826388888946055,9548611111 | Q50: =_xlfn.CONCAT(H50,I50,J50) -> DAURDE
B51: BC Panama1.2 | C51: RADIO_007 | D51: 46055.826 | E51: 46055.826 | F51: 46055.955 | G51: 0.12847222 | H51: DAU | J51: RDE | K51: Rede | L51: Queda de rede da concessionária. | M51: Falha Rede | N51: Distribuidora | O51: Foi feito inspeção em todo complexo, checado nível de tensão e resetado relé e rearmado os disjuntores. | P51: =_xlfn.CONCAT(B51,C51,D51,E51,F51) -> BC Panama1.2RADIO_00746055,826388888946055,826388888946055,9548611111 | Q51: =_xlfn.CONCAT(H51,I51,J51) -> DAURDE
B52: BC Formoso2.1 | C52: Inverter(MBUS-12) | D52: 46055.872 | E52: 46055.872 | F52: 46056.312 | G52: 0.44097222 | H52: DAU | J52: RDE | K52: Rede | L52: Relé atuado na função 59 | M52: Falha Rede | N52: Distribuidora | O52: Foi feito inspeção em todo complexo, checado nível de tensão e resetado relé e rearmado os disjuntores. | P52: =_xlfn.CONCAT(B52,C52,D52,E52,F52) -> BC Formoso2.1Inverter(MBUS-12)46055,871527777846055,871527777846056,3125 | Q52: =_xlfn.CONCAT(H52,I52,J52) -> DAURDE
... B84: BC Paranoa | C84: SG60KTL(COM1-001)_002_006 | D84: 46056.53 | E84: 46056.53 | F84: 46056.539 | G84: 0.0090277778 | H84: DAU | J84: RDE | K84: Rede | L84: Disjuntor geral do cubículo foi desarmado após uma queda de energia. | M84: Falha Rede | N84: Distribuidora | O84: Foi feito inspeção em todo complexo, checado nível de tensão e resetado relé e rearmado os disjuntores. | P84: =_xlfn.CONCAT(B84,C84,D84,E84,F84) -> BC ParanoaSG60KTL(COM1-001)_002_00646056,529861111146056,529861111146056,5388888889 | Q84: =_xlfn.CONCAT(H84,I84,J84) -> DAURDE
B85: BC Paranoa | C85: SG60KTL(COM1-002)_002_016 | D85: 46056.53 | E85: 46056.53 | F85: 46056.539 | G85: 0.0090277778 | H85: DAU | J85: RDE | K85: Rede | L85: Disjuntor geral do cubículo foi desarmado após uma queda de energia. | M85: Falha Rede | N85: Distribuidora | O85: Foi feito inspeção em todo complexo, checado nível de tensão e resetado relé e rearmado os disjuntores. | P85: =_xlfn.CONCAT(B85,C85,D86,E85,F85) -> BC ParanoaSG60KTL(COM1-002)_002_01646056,529861111146056,529861111146056,5388888889 | Q85: =_xlfn.CONCAT(H85,I85,J85) -> DAURDE
B86: BC Paranoa | C86: SG50CX(COM2-003)_002_021 | D86: 46056.53 | E86: 46056.53 | F86: 46056.539 | G86: 0.0090277778 | H86: DAU | J86: RDE | K86: Rede | L86: Disjuntor geral do cubículo foi desarmado após uma queda de energia. | M86: Falha Rede | N86: Distribuidora | O86: Foi feito inspeção em todo complexo, checado nível de tensão e resetado relé e rearmado os disjuntores. | P86: =_xlfn.CONCAT(B86,C86,D87,E86,F86) -> BC ParanoaSG50CX(COM2-003)_002_02146056,529861111146056,529861111146056,5388888889 | Q86: =_xlfn.CONCAT(H86,I86,J86) -> DAURDE
B87: BC Paranoa | C87: SG50CX(COM2-004)_002_023 | D87: 46056.53 | E87: 46056.53 | F87: 46056.539 | G87: 0.0090277778 | H87: DAU | J87: RDE | K87: Rede | L87: Disjuntor geral do cubículo foi desarmado após uma queda de energia. | M87: Falha Rede | N87: Distribuidora | O87: Foi feito inspeção em todo complexo, checado nível de tensão e resetado relé e rearmado os disjuntores. | P87: =_xlfn.CONCAT(B87,C87,D88,E87,F87) -> BC ParanoaSG50CX(COM2-004)_002_02346056,529861111146056,529861111146056,5388888889 | Q87: =_xlfn.CONCAT(H87,I87,J87) -> DAURDE
B88: BC Paranoa | C88: SG60KTL(COM1-005)_002_009 | D88: 46056.53 | E88: 46056.53 | F88: 46056.539 | G88: 0.0090277778 | H88: DAU | J88: RDE | K88: Rede | L88: Disjuntor geral do cubículo foi desarmado após uma queda de energia. | M88: Falha Rede | N88: Distribuidora | O88: Foi feito inspeção em todo complexo, checado nível de tensão e resetado relé e rearmado os disjuntores. | P88: =_xlfn.CONCAT(B88,C88,D89,E88,F88) -> BC ParanoaSG60KTL(COM1-005)_002_00946056,529861111146056,529861111146056,5388888889 | Q88: =_xlfn.CONCAT(H88,I88,J88) -> DAURDE
B89: BC Paranoa | C89: SG60KTL(COM1-006)_002_001 | D89: 46056.53 | E89: 46056.53 | F89: 46056.539 | G89: 0.0090277778 | H89: DAU | J89: RDE | K89: Rede | L89: Disjuntor geral do cubículo foi desarmado após uma queda de energia. | M89: Falha Rede | N89: Distribuidora | O89: Foi feito inspeção em todo complexo, checado nível de tensão e resetado relé e rearmado os disjuntores. | P89: =_xlfn.CONCAT(B89,C89,D90,E89,F89) -> BC ParanoaSG60KTL(COM1-006)_002_00146056,529861111146056,529861111146056,5388888889 | Q89: =_xlfn.CONCAT(H89,I89,J89) -> DAURDE
B90: BC Paranoa | C90: SG60KTL(COM1-013)_002_004 | D90: 46056.53 | E90: 46056.53 | F90: 46056.539 | G90: 0.0090277778 | H90: DAU | J90: RDE | K90: Rede | L90: Disjuntor geral do cubículo foi desarmado após uma queda de energia. | M90: Falha Rede | N90: Distribuidora | O90: Foi feito inspeção em todo complexo, checado nível de tensão e resetado relé e rearmado os disjuntores. | P90: =_xlfn.CONCAT(B90,C90,D91,E90,F90) -> BC ParanoaSG60KTL(COM1-013)_002_00446056,529861111146056,529861111146056,5388888889 | Q90: =_xlfn.CONCAT(H90,I90,J90) -> DAURDE
B91: BC Paranoa | C91: SG60KTL(COM1-014)_002_019 | D91: 46056.53 | E91: 46056.53 | F91: 46056.539 | G91: 0.0090277778 | H91: DAU | J91: RDE | K91: Rede | L91: Disjuntor geral do cubículo foi desarmado após uma queda de energia. | M91: Falha Rede | N91: Distribuidora | O91: Foi feito inspeção em todo complexo, checado nível de tensão e resetado relé e rearmado os disjuntores. | P91: =_xlfn.CONCAT(B91,C91,D92,E91,F91) -> BC ParanoaSG60KTL(COM1-014)_002_01946056,529861111146056,529861111146056,5388888889 | Q91: =_xlfn.CONCAT(H91,I91,J91) -> DAURDE
B92: BC Paranoa | C92: SG60KTL(COM1-015)_002_018 | D92: 46056.53 | E92: 46056.53 | F92: 46056.539 | G92: 0.0090277778 | H92: DAU | J92: RDE | K92: Rede | L92: Disjuntor geral do cubículo foi desarmado após uma queda de energia. | M92: Falha Rede | N92: Distribuidora | O92: Foi feito inspeção em todo complexo, checado nível de tensão e resetado relé e rearmado os disjuntores. | P92: =_xlfn.CONCAT(B92,C92,D93,E92,F92) -> BC ParanoaSG60KTL(COM1-015)_002_01846056,529861111146056,529861111146056,5388888889 | Q92: =_xlfn.CONCAT(H92,I92,J92) -> DAURDE
B93: BC Paranoa | C93: SG60KTL(COM1-016)_002_014 | D93: 46056.53 | E93: 46056.53 | F93: 46056.539 | G93: 0.0090277778 | H93: DAU | J93: RDE | K93: Rede | L93: Disjuntor geral do cubículo foi desarmado após uma queda de energia. | M93: Falha Rede | N93: Distribuidora | O93: Foi feito inspeção em todo complexo, checado nível de tensão e resetado relé e rearmado os disjuntores. | P93: =_xlfn.CONCAT(B93,C93,D94,E93,F93) -> BC ParanoaSG60KTL(COM1-016)_002_01446056,529861111146056,529861111146056,5388888889 | Q93: =_xlfn.CONCAT(H93,I93,J93) -> DAURDE
B94: BC Paranoa | C94: SG60KTL(COM1-017)_002_015 | D94: 46056.53 | E94: 46056.53 | F94: 46056.539 | G94: 0.0090277778 | H94: DAU | J94: RDE | K94: Rede | L94: Disjuntor geral do cubículo foi desarmado após uma queda de energia. | M94: Falha Rede | N94: Distribuidora | O94: Foi aberto um chamado junto à concessionária. Após o restabelecimento da energia, foi realizada a inspeção de todo o complexo, com verificação dos níveis de tensão, reset do relé e rearme dos disjuntores. | P94: =_xlfn.CONCAT(B94,C94,D94,E94,F94) -> BC ParanoaSG60KTL(COM1-017)_002_01546056,529861111146056,529861111146056,5388888889 | Q94: =_xlfn.CONCAT(H94,I94,J94) -> DAURDE
B95: BC Paranoa | C95: SG60KTL(COM1-018)_002_012 | D95: 46056.53 | E95: 46056.53 | F95: 46056.539 | G95: 0.0090277778 | H95: DAU | J95: RDE | K95: Rede | L95: Disjuntor geral do cubículo foi desarmado após uma queda de energia. | M95: Falha Rede | N95: Distribuidora | O95: Foi aberto um chamado junto à concessionária. Após o restabelecimento da energia, foi realizada a inspeção de todo o complexo, com verificação dos níveis de tensão, reset do relé e rearme dos disjuntores. | P95: =_xlfn.CONCAT(B95,C95,D95,E95,F95) -> BC ParanoaSG60KTL(COM1-018)_002_01246056,529861111146056,529861111146056,5388888889 | Q95: =_xlfn.CONCAT(H95,I95,J95) -> DAURDE
B96: BC Paranoa | C96: SG50CX(COM2-004)_001_018 | D96: 46056.53 | E96: 46056.53 | F96: 46056.539 | G96: 0.0090277778 | H96: DAU | J96: RDE | K96: Rede | L96: Disjuntor geral do cubículo foi desarmado após uma queda de energia. | M96: Falha Rede | N96: Distribuidora | O96: Foi aberto um chamado junto à concessionária. Após o restabelecimento da energia, foi realizada a inspeção de todo o complexo, com verificação dos níveis de tensão, reset do relé e rearme dos disjuntores. | P96: =_xlfn.CONCAT(B96,C96,D96,E96,F96) -> BC ParanoaSG50CX(COM2-004)_001_01846056,529861111146056,529861111146056,5388888889 | Q96: =_xlfn.CONCAT(H96,I96,J96) -> DAURDE
B97: BC Paranoa | C97: SG50CX(COM2-003)_001_016 | D97: 46056.53 | E97: 46056.53 | F97: 46056.539 | G97: 0.0090277778 | H97: DAU | J97: RDE | K97: Rede | L97: Disjuntor geral do cubículo foi desarmado após uma queda de energia. | M97: Falha Rede | N97: Distribuidora | O97: Foi aberto um chamado junto à concessionária. Após o restabelecimento da energia, foi realizada a inspeção de todo o complexo, com verificação dos níveis de tensão, reset do relé e rearme dos disjuntores. | P97: =_xlfn.CONCAT(B97,C97,D97,E97,F97) -> BC ParanoaSG50CX(COM2-003)_001_01646056,529861111146056,529861111146056,5388888889 | Q97: =_xlfn.CONCAT(H97,I97,J97) -> DAURDE
B98: BC Paranoa | C98: SG60KTL(COM1-002)_001_008 | D98: 46056.53 | E98: 46056.53 | F98: 46056.539 | G98: 0.0090277778 | H98: DAU | J98: RDE | K98: Rede | L98: Disjuntor geral do cubículo foi desarmado após uma queda de energia. | M98: Falha Rede | N98: Distribuidora | O98: Foi aberto um chamado junto à concessionária. Após o restabelecimento da energia, foi realizada a inspeção de todo o complexo, com verificação dos níveis de tensão, reset do relé e rearme dos disjuntores. | P98: =_xlfn.CONCAT(B98,C98,D98,E98,F98) -> BC ParanoaSG60KTL(COM1-002)_001_00846056,529861111146056,529861111146056,5388888889 | Q98: =_xlfn.CONCAT(H98,I98,J98) -> DAURDE
B99: BC Paranoa | C99: SG60KTL(COM1-014)_001_013 | D99: 46056.651 | E99: 46056.651 | F99: 46056.75 | G99: 0.098611111 | H99: DAU | J99: RDE | K99: Rede | L99: Falta de energia na UFV. | M99: Falha Rede | N99: Distribuidora | O99: Foi aberto um chamado junto à concessionária. Após o restabelecimento da energia, foi realizada a inspeção de todo o complexo, com verificação dos níveis de tensão, reset do relé e rearme dos disjuntores. | P99: =_xlfn.CONCAT(B99,C99,D99,E99,F99) -> BC ParanoaSG60KTL(COM1-014)_001_01346056,651388888946056,651388888946056,75 | Q99: =_xlfn.CONCAT(H99,I99,J99) -> DAURDE
B100: BC Paranoa | C100: SG60KTL(COM1-013)_001_010 | D100: 46056.651 | E100: 46056.651 | F100: 46056.75 | G100: 0.098611111 | H100: DAU | J100: RDE | K100: Rede | L100: Falta de energia na UFV. | M100: Falha Rede | N100: Distribuidora | O100: Foi aberto um chamado junto à concessionária. Após o restabelecimento da energia, foi realizada a inspeção de todo o complexo, com verificação dos níveis de tensão, reset do relé e rearme dos disjuntores. | P100: =_xlfn.CONCAT(B100,C100,D100,E100,F100) -> BC ParanoaSG60KTL(COM1-013)_001_01046056,651388888946056,651388888946056,75 | Q100: =_xlfn.CONCAT(H100,I100,J100) -> DAURDE
B101: BC Paranoa | C101: SG60KTL(COM1-012)_001_011 | D101: 46056.651 | E101: 46056.651 | F101: 46056.75 | G101: 0.098611111 | H101: DAU | J101: RDE | K101: Rede | L101: Falta de energia na UFV. | M101: Falha Rede | N101: Distribuidora | O101: Foi aberto um chamado junto à concessionária. Após o restabelecimento da energia, foi realizada a inspeção de todo o complexo, com verificação dos níveis de tensão, reset do relé e rearme dos disjuntores. | P101: =_xlfn.CONCAT(B101,C101,D101,E101,F101) -> BC ParanoaSG60KTL(COM1-012)_001_01146056,651388888946056,651388888946056,75 | Q101: =_xlfn.CONCAT(H101,I101,J101) -> DAURDE
B102: BC Paranoa | C102: SG60KTL(COM1-011)_001_005 | D102: 46056.651 | E102: 46056.651 | F102: 46056.75 | G102: 0.098611111 | H102: DAU | J102: RDE | K102: Rede | L102: Falta de energia na UFV. | M102: Falha Rede | N102: Distribuidora | O102: Foi aberto um chamado junto à concessionária. Após o restabelecimento da energia, foi realizada a inspeção de todo o complexo, com verificação dos níveis de tensão, reset do relé e rearme dos disjuntores. | P102: =_xlfn.CONCAT(B102,C102,D102,E102,F102) -> BC ParanoaSG60KTL(COM1-011)_001_00546056,651388888946056,651388888946056,75 | Q102: =_xlfn.CONCAT(H102,I102,J102) -> DAURDE
B103: BC Paranoa | C103: SG60KTL(COM1-010)_001_003 | D103: 46056.651 | E103: 46056.651 | F103: 46056.75 | G103: 0.098611111 | H103: DAU | J103: RDE | K103: Rede | L103: Falta de energia na UFV. | M103: Falha Rede | N103: Distribuidora | O103: Foi aberto um chamado junto à concessionária. Após o restabelecimento da energia, foi realizada a inspeção de todo o complexo, com verificação dos níveis de tensão, reset do relé e rearme dos disjuntores. | P103: =_xlfn.CONCAT(B103,C103,D103,E103,F103) -> BC ParanoaSG60KTL(COM1-010)_001_00346056,651388888946056,651388888946056,75 | Q103: =_xlfn.CONCAT(H103,I103,J103) -> DAURDE
B104: BC Paranoa | C104: SG60KTL(COM1-018)_001_012 | D104: 46056.651 | E104: 46056.651 | F104: 46056.75 | G104: 0.098611111 | H104: DAU | J104: RDE | K104: Rede | L104: Falta de energia na UFV. | M104: Falha Rede | N104: Distribuidora | O104: Foi aberto um chamado junto à concessionária. Após o restabelecimento da energia, foi realizada a inspeção de todo o complexo, com verificação dos níveis de tensão, reset do relé e rearme dos disjuntores. | P104: =_xlfn.CONCAT(B104,C104,D104,E104,F104) -> BC ParanoaSG60KTL(COM1-018)_001_01246056,651388888946056,651388888946056,75 | Q104: =_xlfn.CONCAT(H104,I104,J104) -> DAURDE
B105: BC Paranoa | C105: SG60KTL(COM1-017)_001_007 | D105: 46056.651 | E105: 46056.651 | F105: 46056.75 | G105: 0.098611111 | H105: DAU | J105: RDE | K105: Rede | L105: Falta de energia na UFV. | M105: Falha Rede | N105: Distribuidora | O105: Foi aberto um chamado junto à concessionária. Após o restabelecimento da energia, foi realizada a inspeção de todo o complexo, com verificação dos níveis de tensão, reset do relé e rearme dos disjuntores. | P105: =_xlfn.CONCAT(B105,C105,D105,E105,F105) -> BC ParanoaSG60KTL(COM1-017)_001_00746056,651388888946056,651388888946056,75 | Q105: =_xlfn.CONCAT(H105,I105,J105) -> DAURDE
... B164: BC Aracu5.1 | C164: Inverter(MBUS-1) | D164: 46057.639 | E164: 46057.639 | F164: 46057.674 | G164: 0.034722222 | H164: DPR | J164: INV | K164: Inversor | L164: Desligamento programado | M164: Falha Comunicação | N164: Prestador de Serviço O&M | O164: Foi feito inspeções nos componentes relacionados a geração, e foi constatado que houve somente falha de comunicação | P164: =_xlfn.CONCAT(B164,C164,D164,E164,F164) -> BC Aracu5.1Inverter(MBUS-1)46057,638888888946057,638888888946057,6736111111 | Q164: =_xlfn.CONCAT(H164,I164,J164) -> DPRINV
B165: BC Aracu5.3 | C165: Inverter(MBUS-1) | D165: 46057.639 | E165: 46057.639 | F165: 46057.674 | G165: 0.034722222 | H165: DPR | J165: INV | K165: Inversor | L165: Desligamento programado | P165: =_xlfn.CONCAT(B165,C165,D165,E165,F165) -> BC Aracu5.3Inverter(MBUS-1)46057,638888888946057,638888888946057,6736111111 | Q165: =_xlfn.CONCAT(H165,I165,J165) -> DPRINV
B166: BC Aracu5.5 | C166: Inverter(MBUS-1) | D166: 46057.639 | E166: 46057.639 | F166: 46057.674 | G166: 0.034722222 | H166: DPR | J166: INV | K166: Inversor | L166: Desligamento programado | P166: =_xlfn.CONCAT(B166,C166,D166,E166,F166) -> BC Aracu5.5Inverter(MBUS-1)46057,638888888946057,638888888946057,6736111111 | Q166: =_xlfn.CONCAT(H166,I166,J166) -> DPRINV
B167: BC Camarao1.3 | C167: 215KTL-H3(MBUS-16) | D167: 46057.661 | E167: 46057.661 | F167: 46057.674 | G167: 0.0125 | H167: DAU | I167: RFO | J167: COM | K167: Comunicação | L167: Falha de comunicação com o logger da usina. | P167: =_xlfn.CONCAT(B167,C167,D167,E167,F167) -> BC Camarao1.3215KTL-H3(MBUS-16)46057,661111111146057,661111111146057,6736111111 | Q167: =_xlfn.CONCAT(H167,I167,J167) -> DAURFOCOM
B168: BC Camarao1.3 | C168: 215KTL-H3(MBUS-14) | D168: 46057.661 | E168: 46057.661 | F168: 46057.674 | G168: 0.0125 | H168: DAU | I168: RFO | J168: COM | K168: Comunicação | L168: Falha de comunicação com o logger da usina. | P168: =_xlfn.CONCAT(B168,C168,D168,E168,F168) -> BC Camarao1.3215KTL-H3(MBUS-14)46057,661111111146057,661111111146057,6736111111 | Q168: =_xlfn.CONCAT(H168,I168,J168) -> DAURFOCOM
B169: BC Camarao1.3 | C169: 215KTL-H3(MBUS-15) | D169: 46057.661 | E169: 46057.661 | F169: 46057.674 | G169: 0.0125 | H169: DAU | I169: RFO | J169: COM | K169: Comunicação | L169: Falha de comunicação com o logger da usina. | P169: =_xlfn.CONCAT(B169,C169,D169,E169,F169) -> BC Camarao1.3215KTL-H3(MBUS-15)46057,661111111146057,661111111146057,6736111111 | Q169: =_xlfn.CONCAT(H169,I169,J169) -> DAURFOCOM
B170: BC Camarao1.3 | C170: 215KTL-H3(MBUS-12) | D170: 46057.661 | E170: 46057.661 | F170: 46057.674 | G170: 0.0125 | H170: DAU | I170: RFO | J170: COM | K170: Comunicação | L170: Falha de comunicação com o logger da usina. | P170: =_xlfn.CONCAT(B170,C170,D170,E170,F170) -> BC Camarao1.3215KTL-H3(MBUS-12)46057,661111111146057,661111111146057,6736111111 | Q170: =_xlfn.CONCAT(H170,I170,J170) -> DAURFOCOM
B171: BC Camarao1.3 | C171: 215KTL-H3(MBUS-13) | D171: 46057.661 | E171: 46057.661 | F171: 46057.674 | G171: 0.0125 | H171: DAU | I171: RFO | J171: COM | K171: Comunicação | L171: Falha de comunicação com o logger da usina. | P171: =_xlfn.CONCAT(B171,C171,D171,E171,F171) -> BC Camarao1.3215KTL-H3(MBUS-13)46057,661111111146057,661111111146057,6736111111 | Q171: =_xlfn.CONCAT(H171,I171,J171) -> DAURFOCOM
B172: BC Aracu5.1 | C172: Inverter(MBUS-1) | D172: 46057.972 | E172: 46057.972 | F172: 46058.299 | G172: 0.32638889 | H172: DAU | J172: RDE | K172: Rede | L172: Relé atuado na função 81 e 86 | P172: =_xlfn.CONCAT(B172,C172,D172,E172,F172) -> BC Aracu5.1Inverter(MBUS-1)46057,972222222246057,972222222246058,2986111111 | Q172: =_xlfn.CONCAT(H172,I172,J172) -> DAURDE
B173: BC Aracu5.3 | C173: Inverter(MBUS-1) | D173: 46057.972 | E173: 46057.972 | F173: 46058.299 | G173: 0.32638889 | H173: DAU | J173: RDE | K173: Rede | L173: Relé atuado na função 81 e 86 | P173: =_xlfn.CONCAT(B173,C173,D173,E173,F173) -> BC Aracu5.3Inverter(MBUS-1)46057,972222222246057,972222222246058,2986111111 | Q173: =_xlfn.CONCAT(H173,I173,J173) -> DAURDE
B174: BC Aracu5.4 | C174: Inverter(MBUS-1) | D174: 46057.972 | E174: 46057.972 | F174: 46058.299 | G174: 0.32638889 | H174: DAU | J174: RDE | K174: Rede | L174: Relé atuado na função 81 e 86 | M174: Manutenção | N174: Manutenção Preventiva | O174: Foi realizado os seguintes serviços: Inspeção no componentes de conexão; Torquiamento em todos os parafusos de conexão; Limpeza da cabine de média tensão. Após procedimentos a UFV foi ligada e segue operando normalmente. | P174: =_xlfn.CONCAT(B174,C174,D174,E174,F174) -> BC Aracu5.4Inverter(MBUS-1)46057,972222222246057,972222222246058,2986111111 | Q174: =_xlfn.CONCAT(H174,I174,J174) -> DAURDE
B175: BC Aracu5.5 | C175: Inverter(MBUS-1) | D175: 46057.972 | E175: 46057.972 | F175: 46058.299 | G175: 0.32638889 | H175: DAU | J175: RDE | K175: Rede | L175: Relé atuado na função 81 e 86 | M175: Falha Rede | N175: Distribuídora | O175: Foi feito inspeção em todo complexo, checado nível de tensão e realizado a manobra de normalização da geração. | P175: =_xlfn.CONCAT(B175,C175,D175,E175,F175) -> BC Aracu5.5Inverter(MBUS-1)46057,972222222246057,972222222246058,2986111111 | Q175: =_xlfn.CONCAT(H175,I175,J175) -> DAURDE
B176: BC Caiaponia1 | C176: SG60KTL(COM1-001)_001_007 | D176: 46058.058 | E176: 46058.058 | F176: 46058.366 | G176: 0.30763889 | H176: DAU | J176: RDE | K176: Rede | L176: Queda da rede da concessionária. | M176: Falha Rede | N176: Distribuídora | O176: Foi feito inspeção em todo complexo, checado nível de tensão e realizado a manobra de normalização da geração. | P176: =_xlfn.CONCAT(B176,C176,D176,E176,F176) -> BC Caiaponia1SG60KTL(COM1-001)_001_00746058,058333333346058,058333333346058,3659722222 | Q176: =_xlfn.CONCAT(H176,I176,J176) -> DAURDE
B177: BC Caiaponia1 | C177: SG60KTL(COM1-002)_001_010 | D177: 46058.058 | E177: 46058.058 | F177: 46058.366 | G177: 0.30763889 | H177: DAU | J177: RDE | K177: Rede | L177: Queda da rede da concessionária. | M177: Falha Rede | N177: Distribuídora | O177: Foi feito inspeção em todo complexo, checado nível de tensão e realizado a manobra de normalização da geração. | P177: =_xlfn.CONCAT(B177,C177,D177,E177,F177) -> BC Caiaponia1SG60KTL(COM1-002)_001_01046058,058333333346058,058333333346058,3659722222 | Q177: =_xlfn.CONCAT(H177,I177,J177) -> DAURDE
B178: BC Caiaponia1 | C178: SG60KTL(COM1-003)_001_011 | D178: 46058.058 | E178: 46058.058 | F178: 46058.366 | G178: 0.30763889 | H178: DAU | J178: RDE | K178: Rede | L178: Queda da rede da concessionária. | M178: Falha Rede | N178: Distribuídora | O178: Foi feito inspeção em todo complexo, checado nível de tensão e realizado a manobra de normalização da geração. | P178: =_xlfn.CONCAT(B178,C178,D178,E178,F178) -> BC Caiaponia1SG60KTL(COM1-003)_001_01146058,058333333346058,058333333346058,3659722222 | Q178: =_xlfn.CONCAT(H178,I178,J178) -> DAURDE
B179: BC Caiaponia1 | C179: SG60KTL(COM1-004)_001_014 | D179: 46058.058 | E179: 46058.058 | F179: 46058.366 | G179: 0.30763889 | H179: DAU | J179: RDE | K179: Rede | L179: Queda da rede da concessionária. | M179: Falha Rede | N179: Distribuídora | O179: Foi feito inspeção em todo complexo, checado nível de tensão e realizado a manobra de normalização da geração. | P179: =_xlfn.CONCAT(B179,C179,D179,E179,F179) -> BC Caiaponia1SG60KTL(COM1-004)_001_01446058,058333333346058,058333333346058,3659722222 | Q179: =_xlfn.CONCAT(H179,I179,J179) -> DAURDE
B180: BC Caiaponia1 | C180: SG60KTL(COM1-005)_001_017 | D180: 46058.058 | E180: 46058.058 | F180: 46058.366 | G180: 0.30763889 | H180: DAU | J180: RDE | K180: Rede | L180: Queda da rede da concessionária. | M180: Falha Rede | N180: Distribuídora | O180: Foi feito inspeção em todo complexo, checado nível de tensão e realizado a manobra de normalização da geração. | P180: =_xlfn.CONCAT(B180,C180,D180,E180,F180) -> BC Caiaponia1SG60KTL(COM1-005)_001_01746058,058333333346058,058333333346058,3659722222 | Q180: =_xlfn.CONCAT(H180,I180,J180) -> DAURDE
B181: BC Caiaponia1 | C181: SG60KTL(COM1-006)_001_016 | D181: 46058.058 | E181: 46058.058 | F181: 46058.366 | G181: 0.30763889 | H181: DAU | J181: RDE | K181: Rede | L181: Queda da rede da concessionária. | M181: Falha Rede | N181: Distribuídora | O181: Foi feito inspeção em todo complexo, checado nível de tensão e realizado a manobra de normalização da geração. | P181: =_xlfn.CONCAT(B181,C181,D181,E181,F181) -> BC Caiaponia1SG60KTL(COM1-006)_001_01646058,058333333346058,058333333346058,3659722222 | Q181: =_xlfn.CONCAT(H181,I181,J181) -> DAURDE
B182: BC Caiaponia1 | C182: SG60KTL(COM1-007)_001_013 | D182: 46058.058 | E182: 46058.058 | F182: 46058.366 | G182: 0.30763889 | H182: DAU | J182: RDE | K182: Rede | L182: Queda da rede da concessionária. | M182: Falha Rede | N182: Distribuídora | O182: Foi feito inspeção em todo complexo, checado nível de tensão e realizado a manobra de normalização da geração. | P182: =_xlfn.CONCAT(B182,C182,D182,E182,F182) -> BC Caiaponia1SG60KTL(COM1-007)_001_01346058,058333333346058,058333333346058,3659722222 | Q182: =_xlfn.CONCAT(H182,I182,J182) -> DAURDE
B183: BC Caiaponia1 | C183: SG60KTL(COM1-008)_001_001 | D183: 46058.058 | E183: 46058.058 | F183: 46058.366 | G183: 0.30763889 | H183: DAU | J183: RDE | K183: Rede | L183: Queda da rede da concessionária. | M183: Falha Rede | N183: Distribuídora | O183: Foi feito inspeção em todo complexo, checado nível de tensão e realizado a manobra de normalização da geração. | P183: =_xlfn.CONCAT(B183,C183,D183,E183,F183) -> BC Caiaponia1SG60KTL(COM1-008)_001_00146058,058333333346058,058333333346058,3659722222 | Q183: =_xlfn.CONCAT(H183,I183,J183) -> DAURDE
B184: BC Caiaponia1 | C184: SG60KTL(COM1-009) | D184: 46058.058 | E184: 46058.058 | F184: 46058.366 | G184: 0.30763889 | H184: DAU | J184: RDE | K184: Rede | L184: Queda da rede da concessionária. | M184: Falha Rede | N184: Distribuídora | O184: Foi feito inspeção em todo complexo, checado nível de tensão e realizado a manobra de normalização da geração. | P184: =_xlfn.CONCAT(B184,C184,D184,E184,F184) -> BC Caiaponia1SG60KTL(COM1-009)46058,058333333346058,058333333346058,3659722222 | Q184: =_xlfn.CONCAT(H184,I184,J184) -> DAURDE
B185: BC Caiaponia1 | C185: SG60KTL(COM1-010) | D185: 46058.058 | E185: 46058.058 | F185: 46058.366 | G185: 0.30763889 | H185: DAU | J185: RDE | K185: Rede | L185: Queda da rede da concessionária. | M185: Falha Rede | N185: Distribuídora | O185: Foi feito inspeção em todo complexo, checado nível de tensão e realizado a manobra de normalização da geração. | P185: =_xlfn.CONCAT(B185,C185,D185,E185,F185) -> BC Caiaponia1SG60KTL(COM1-010)46058,058333333346058,058333333346058,3659722222 | Q185: =_xlfn.CONCAT(H185,I185,J185) -> DAURDE
... B187: BC Caiaponia1 | C187: SG60KTL(COM1-012) | D187: 46058.058 | E187: 46058.058 | F187: 46058.366 | G187: 0.30763889 | H187: DAU | J187: RDE | K187: Rede | L187: Queda da rede da concessionária. | M187: Falha Rede | N187: Distribuídora | O187: Foi feito inspeção em todo complexo, checado nível de tensão e realizado a manobra de normalização da geração. | P187: =_xlfn.CONCAT(B187,C187,D187,E187,F187) -> BC Caiaponia1SG60KTL(COM1-012)46058,058333333346058,058333333346058,3659722222 | Q187: =_xlfn.CONCAT(H187,I187,J187) -> DAURDE
B188: BC Caiaponia1 | C188: SG60KTL(COM1-013) | D188: 46058.058 | E188: 46058.058 | F188: 46058.366 | G188: 0.30763889 | H188: DAU | J188: RDE | K188: Rede | L188: Queda da rede da concessionária. | M188: Manutenção | N188: Prestador de Serviço O&M | O188: Foi realizado a configuração das antenas e postes e realinhamento | P188: =_xlfn.CONCAT(B188,C188,D189,E188,F188) -> BC Caiaponia1SG60KTL(COM1-013)46058,058333333346058,058333333346058,3659722222 | Q188: =_xlfn.CONCAT(H188,I188,J188) -> DAURDE
B189: BC Caiaponia1 | C189: SG60KTL(COM1-014) | D189: 46058.058 | E189: 46058.058 | F189: 46058.366 | G189: 0.30763889 | H189: DAU | J189: RDE | K189: Rede | L189: Queda da rede da concessionária. | M189: Manutenção | N189: Prestador de Serviço O&M | O189: Foi realizado a configuração das antenas e postes e realinhamento | P189: =_xlfn.CONCAT(B189,C189,D190,E189,F189) -> BC Caiaponia1SG60KTL(COM1-014)46058,058333333346058,058333333346058,3659722222 | Q189: =_xlfn.CONCAT(H189,I189,J189) -> DAURDE
B190: BC Caiaponia1 | C190: SG60KTL(COM1-015) | D190: 46058.058 | E190: 46058.058 | F190: 46058.366 | G190: 0.30763889 | H190: DAU | J190: RDE | K190: Rede | L190: Queda da rede da concessionária. | M190: Manutenção | N190: Prestador de Serviço O&M | O190: Foi realizado a configuração das antenas e postes e realinhamento | P190: =_xlfn.CONCAT(B190,C190,D191,E190,F190) -> BC Caiaponia1SG60KTL(COM1-015)46058,058333333346058,058333333346058,3659722222 | Q190: =_xlfn.CONCAT(H190,I190,J190) -> DAURDE
B191: BC Caiaponia1 | C191: SG60KTL(COM3-016)_001_009 | D191: 46058.058 | E191: 46058.058 | F191: 46058.366 | G191: 0.30763889 | H191: DAU | J191: RDE | K191: Rede | L191: Queda da rede da concessionária. | M191: Manutenção | N191: Prestador de Serviço O&M | O191: Foi realizado a configuração das antenas e postes e realinhamento | P191: =_xlfn.CONCAT(B191,C191,D192,E191,F191) -> BC Caiaponia1SG60KTL(COM3-016)_001_00946058,058333333346058,058333333346058,3659722222 | Q191: =_xlfn.CONCAT(H191,I191,J191) -> DAURDE
B192: BC Caiaponia1 | C192: SG60KTL(COM3-017)_001_012 | D192: 46058.058 | E192: 46058.058 | F192: 46058.366 | G192: 0.30763889 | H192: DAU | J192: RDE | K192: Rede | L192: Queda da rede da concessionária. | M192: Manutenção | N192: Prestador de Serviço O&M | O192: Foi realizado a configuração das antenas e postes e realinhamento | P192: =_xlfn.CONCAT(B192,C192,D193,E192,F192) -> BC Caiaponia1SG60KTL(COM3-017)_001_01246058,058333333346058,058333333346058,3659722222 | Q192: =_xlfn.CONCAT(H192,I192,J192) -> DAURDE
B193: BC Caiaponia1 | C193: SG60KTL(COM3-018)_001_008 | D193: 46058.058 | E193: 46058.058 | F193: 46058.366 | G193: 0.30763889 | H193: DAU | J193: RDE | K193: Rede | L193: Queda da rede da concessionária. | M193: Manutenção | N193: Prestador de Serviço O&M | O193: Foi realizado a configuração das antenas e postes e realinhamento | P193: =_xlfn.CONCAT(B193,C193,D194,E193,F193) -> BC Caiaponia1SG60KTL(COM3-018)_001_00846058,058333333346058,058333333346058,3659722222 | Q193: =_xlfn.CONCAT(H193,I193,J193) -> DAURDE
...

Sheet  Janeiro 2026
A1: UC | B1: UFV | C1: Tag | D1: Início Real do Evento | E1: Início | F1: Fim | G1: Duração | H1: Estado Operativo | I1: Condição Operativa | J1: Origem | K1: Equipamento | L1: Causa | M1: Causas Padrão | N1: Resolução | O1: Observação | P1: Concat - duplicata | Q1: Combinação
B2: BC Caiaponia2.1 | C2: 215KTL-H3(MBUS-12) | D2: 46023.088 | E2: 46023.088 | F2: 46023.901 | G2: =F2-E2 -> 0.81388889 | H2: DAU | J2: RDE | K2: =_xlfn.XLOOKUP(J2,REF!$D$2:$D$12,REF!$E$2:$E$12) -> Rede | L2: Queda de rede da concessionária. | M2: Falha Rede | N2: Distribuidora | O2: Foi feito inspeção em todo complexo, checado nível de tensão e resetado relé e rearmado os disjuntores. | P2: =_xlfn.CONCAT(B2,C2,D2,E2,F2) -> BC Caiaponia2.1215KTL-H3(MBUS-12)46023,087546023,087546023,9013888889 | Q2: =_xlfn.CONCAT(H2,I2,J2) -> DAURDE
B3: BC Caiaponia2.1 | C3: 215KTL-H3(MBUS-13) | D3: 46023.088 | E3: 46023.088 | F3: 46023.901 | G3: =F3-E3 -> 0.81388889 | H3: DAU | J3: RDE | K3: =_xlfn.XLOOKUP(J3,REF!$D$2:$D$12,REF!$E$2:$E$12) -> Rede | L3: Queda de rede da concessionária. | M3: Falha Rede | N3: Distribuidora | O3: Foi feito inspeção em todo complexo, checado nível de tensão e resetado relé e rearmado os disjuntores. | P3: =_xlfn.CONCAT(B3,C3,D3,E3,F3) -> BC Caiaponia2.1215KTL-H3(MBUS-13)46023,087546023,087546023,9013888889 | Q3: =_xlfn.CONCAT(H3,I3,J3) -> DAURDE
B4: BC Caiaponia2.1 | C4: 215KTL-H3(MBUS-14) | D4: 46023.088 | E4: 46023.088 | F4: 46023.901 | G4: =F4-E4 -> 0.81388889 | H4: DAU | J4: RDE | K4: =_xlfn.XLOOKUP(J4,REF!$D$2:$D$12,REF!$E$2:$E$12) -> Rede | L4: Queda de rede da concessionária. | M4: Falha Rede | N4: Distribuidora | O4: Foi feito inspeção em todo complexo, checado nível de tensão e resetado relé e rearmado os disjuntores. | P4: =_xlfn.CONCAT(B4,C4,D4,E4,F4) -> BC Caiaponia2.1215KTL-H3(MBUS-14)46023,087546023,087546023,9013888889 | Q4: =_xlfn.CONCAT(H4,I4,J4) -> DAURDE
B5: BC Caiaponia2.1 | C5: 215KTL-H3(MBUS-15) | D5: 46023.088 | E5: 46023.088 | F5: 46023.901 | G5: =F5-E5 -> 0.81388889 | H5: DAU | J5: RDE | K5: =_xlfn.XLOOKUP(J5,REF!$D$2:$D$12,REF!$E$2:$E$12) -> Rede | L5: Queda de rede da concessionária. | M5: Falha Rede | N5: Distribuidora | O5: Foi feito inspeção em todo complexo, checado nível de tensão e resetado relé e rearmado os disjuntores. | P5: =_xlfn.CONCAT(B5,C5,D5,E5,F5) -> BC Caiaponia2.1215KTL-H3(MBUS-15)46023,087546023,087546023,9013888889 | Q5: =_xlfn.CONCAT(H5,I5,J5) -> DAURDE
B6: BC Caiaponia2.1 | C6: 215KTL-H3(MBUS-16) | D6: 46023.088 | E6: 46023.088 | F6: 46023.901 | G6: =F6-E6 -> 0.81388889 | H6: DAU | J6: RDE | K6: =_xlfn.XLOOKUP(J6,REF!$D$2:$D$12,REF!$E$2:$E$12) -> Rede | L6: Queda de rede da concessionária. | M6: Falha Rede | N6: Distribuidora | O6: Foi feito inspeção em todo complexo, checado nível de tensão e resetado relé e rearmado os disjuntores. | P6: =_xlfn.CONCAT(B6,C6,D6,E6,F6) -> BC Caiaponia2.1215KTL-H3(MBUS-16)46023,087546023,087546023,9013888889 | Q6: =_xlfn.CONCAT(H6,I6,J6) -> DAURDE
B7: BC Caiaponia2.2 | C7: 215KTL-H3(MBUS-12) | D7: 46023.088 | E7: 46023.088 | F7: 46023.901 | G7: =F7-E7 -> 0.81388889 | H7: DAU | J7: RDE | K7: =_xlfn.XLOOKUP(J7,REF!$D$2:$D$12,REF!$E$2:$E$12) -> Rede | L7: Queda de rede da concessionária. | M7: Falha Rede | N7: Distribuidora | O7: Foi feito inspeção em todo complexo, checado nível de tensão e resetado relé e rearmado os disjuntores. | P7: =_xlfn.CONCAT(B7,C7,D7,E7,F7) -> BC Caiaponia2.2215KTL-H3(MBUS-12)46023,087546023,087546023,9013888889 | Q7: =_xlfn.CONCAT(H7,I7,J7) -> DAURDE
B8: BC Caiaponia2.2 | C8: 215KTL-H3(MBUS-13) | D8: 46023.088 | E8: 46023.088 | F8: 46023.901 | G8: =F8-E8 -> 0.81388889 | H8: DAU | J8: RDE | K8: =_xlfn.XLOOKUP(J8,REF!$D$2:$D$12,REF!$E$2:$E$12) -> Rede | L8: Queda de rede da concessionária. | M8: Falha Rede | N8: Distribuidora | O8: Foi feito inspeção em todo complexo, checado nível de tensão e resetado relé e rearmado os disjuntores. | P8: =_xlfn.CONCAT(B8,C8,D8,E8,F8) -> BC Caiaponia2.2215KTL-H3(MBUS-13)46023,087546023,087546023,9013888889 | Q8: =_xlfn.CONCAT(H8,I8,J8) -> DAURDE
B9: BC Caiaponia2.2 | C9: 215KTL-H3(MBUS-14) | D9: 46023.088 | E9: 46023.088 | F9: 46023.901 | G9: =F9-E9 -> 0.81388889 | H9: DAU | J9: RDE | K9: =_xlfn.XLOOKUP(J9,REF!$D$2:$D$12,REF!$E$2:$E$12) -> Rede | L9: Queda de rede da concessionária. | M9: Falha Rede | N9: Distribuidora | O9: Foi feito inspeção em todo complexo, checado nível de tensão e resetado relé e rearmado os disjuntores. | P9: =_xlfn.CONCAT(B9,C9,D9,E9,F9) -> BC Caiaponia2.2215KTL-H3(MBUS-14)46023,087546023,087546023,9013888889 | Q9: =_xlfn.CONCAT(H9,I9,J9) -> DAURDE
B10: BC Caiaponia2.2 | C10: 215KTL-H3(MBUS-15) | D10: 46023.088 | E10: 46023.088 | F10: 46023.901 | G10: =F10-E10 -> 0.81388889 | H10: DAU | J10: RDE | K10: =_xlfn.XLOOKUP(J10,REF!$D$2:$D$12,REF!$E$2:$E$12) -> Rede | L10: Queda de rede da concessionária. | M10: Falha Rede | N10: Distribuidora | O10: Foi feito inspeção em todo complexo, checado nível de tensão e resetado relé e rearmado os disjuntores. | P10: =_xlfn.CONCAT(B10,C10,D10,E10,F10) -> BC Caiaponia2.2215KTL-H3(MBUS-15)46023,087546023,087546023,9013888889 | Q10: =_xlfn.CONCAT(H10,I10,J10) -> DAURDE
B11: BC Caiaponia2.2 | C11: 215KTL-H3(MBUS-16) | D11: 46023.088 | E11: 46023.088 | F11: 46023.901 | G11: =F11-E11 -> 0.81388889 | H11: DAU | J11: RDE | K11: =_xlfn.XLOOKUP(J11,REF!$D$2:$D$12,REF!$E$2:$E$12) -> Rede | L11: Queda de rede da concessionária. | M11: Falha Rede | N11: Distribuidora | O11: Foi feito inspeção em todo complexo, checado nível de tensão e resetado relé e rearmado os disjuntores. | P11: =_xlfn.CONCAT(B11,C11,D11,E11,F11) -> BC Caiaponia2.2215KTL-H3(MBUS-16)46023,087546023,087546023,9013888889 | Q11: =_xlfn.CONCAT(H11,I11,J11) -> DAURDE
B12: BC Caiaponia2.3 | C12: 215KTL-H3(MBUS-12) | D12: 46023.088 | E12: 46023.088 | F12: 46023.901 | G12: =F12-E12 -> 0.81388889 | H12: DAU | J12: RDE | K12: =_xlfn.XLOOKUP(J12,REF!$D$2:$D$12,REF!$E$2:$E$12) -> Rede | L12: Queda de rede da concessionária. | M12: Falha Rede | N12: Distribuidora | O12: Foi feito inspeção em todo complexo, checado nível de tensão e resetado relé e rearmado os disjuntores. | P12: =_xlfn.CONCAT(B12,C12,D12,E12,F12) -> BC Caiaponia2.3215KTL-H3(MBUS-12)46023,087546023,087546023,9013888889 | Q12: =_xlfn.CONCAT(H12,I12,J12) -> DAURDE
B13: BC Caiaponia2.3 | C13: 215KTL-H3(MBUS-13) | D13: 46023.088 | E13: 46023.088 | F13: 46023.901 | G13: =F13-E13 -> 0.81388889 | H13: DAU | J13: RDE | K13: =_xlfn.XLOOKUP(J13,REF!$D$2:$D$12,REF!$E$2:$E$12) -> Rede | L13: Queda de rede da concessionária. | M13: Falha Rede | N13: Distribuidora | O13: Foi feito inspeção em todo complexo, checado nível de tensão e resetado relé e rearmado os disjuntores. | P13: =_xlfn.CONCAT(B13,C13,D13,E13,F13) -> BC Caiaponia2.3215KTL-H3(MBUS-13)46023,087546023,087546023,9013888889 | Q13: =_xlfn.CONCAT(H13,I13,J13) -> DAURDE
... B16: BC Caiaponia2.3 | C16: 215KTL-H3(MBUS-16) | D16: 46023.088 | E16: 46023.088 | F16: 46023.901 | G16: =F16-E16 -> 0.81388889 | H16: DAU | J16: RDE | K16: =_xlfn.XLOOKUP(J16,REF!$D$2:$D$12,REF!$E$2:$E$12) -> Rede | L16: Queda de rede da concessionária. | M16: Falha Rede | N16: Distribuidora | O16: Foi feito inspeção em todo complexo, checado nível de tensão e resetado relé e rearmado os disjuntores. | P16: =_xlfn.CONCAT(B16,C16,D16,E16,F16) -> BC Caiaponia2.3215KTL-H3(MBUS-16)46023,087546023,087546023,9013888889 | Q16: =_xlfn.CONCAT(H16,I16,J16) -> DAURDE
B17: BC Aracu5.1 | C17: Inverter(MBUS-1) | D17: 46023.265 | E17: 46023.265 | F17: 46023.368 | G17: =F17-E17 -> 0.10347222 | H17: DAU | J17: RDE | K17: Rede | L17: Função 81 e 86 atuada no relé. | M17: Falha Rede | N17: Distribuídora | O17: Foi feito inspeção em todo complexo, checado nível de tensão e realizado a manobra de normalização da geração. | P17: =_xlfn.CONCAT(B17,C17,D17,E17,F17) -> BC Aracu5.1Inverter(MBUS-1)46023,264583333346023,264583333346023,3680555556 | Q17: =_xlfn.CONCAT(H17,I17,J17) -> DAURDE
B18: BC Aracu5.2 | C18: Inverter(MBUS-1) | D18: 46023.265 | E18: 46023.265 | F18: 46023.368 | G18: =F18-E18 -> 0.10347222 | H18: DAU | J18: RDE | K18: Rede | L18: Função 81 e 86 atuada no relé. | M18: Falha Rede | N18: Distribuídora | O18: Foi feito inspeção em todo complexo, checado nível de tensão e realizado a manobra de normalização da geração. | P18: =_xlfn.CONCAT(B18,C18,D18,E18,F18) -> BC Aracu5.2Inverter(MBUS-1)46023,264583333346023,264583333346023,3680555556 | Q18: =_xlfn.CONCAT(H18,I18,J18) -> DAURDE
B19: BC Aracu5.3 | C19: Inverter(MBUS-1) | D19: 46023.265 | E19: 46023.265 | F19: 46023.368 | G19: =F19-E19 -> 0.10347222 | H19: DAU | J19: RDE | K19: Rede | L19: Função 81 e 86 atuada no relé. | M19: Falha Rede | N19: Distribuídora | O19: Foi feito inspeção em todo complexo, checado nível de tensão e realizado a manobra de normalização da geração. | P19: =_xlfn.CONCAT(B19,C19,D19,E19,F19) -> BC Aracu5.3Inverter(MBUS-1)46023,264583333346023,264583333346023,3680555556 | Q19: =_xlfn.CONCAT(H19,I19,J19) -> DAURDE
B20: BC Aracu5.4 | C20: Inverter(MBUS-1) | D20: 46023.265 | E20: 46023.265 | F20: 46023.368 | G20: =F20-E20 -> 0.10347222 | H20: DAU | J20: RDE | K20: Rede | L20: Função 81 e 86 atuada no relé. | M20: Falha Rede | N20: Distribuídora | O20: Foi feito inspeção em todo complexo, checado nível de tensão e realizado a manobra de normalização da geração. | P20: =_xlfn.CONCAT(B20,C20,D20,E20,F20) -> BC Aracu5.4Inverter(MBUS-1)46023,264583333346023,264583333346023,3680555556 | Q20: =_xlfn.CONCAT(H20,I20,J20) -> DAURDE
B21: BC Aracu5.5 | C21: Inverter(MBUS-1) | D21: 46023.265 | E21: 46023.265 | F21: 46023.368 | G21: =F21-E21 -> 0.10347222 | H21: DAU | J21: RDE | K21: Rede | L21: Função 81 e 86 atuada no relé. | M21: Falha Rede | N21: Distribuídora | O21: Foi feito inspeção em todo complexo, checado nível de tensão e realizado a manobra de normalização da geração. | P21: =_xlfn.CONCAT(B21,C21,D21,E21,F21) -> BC Aracu5.5Inverter(MBUS-1)46023,264583333346023,264583333346023,3680555556 | Q21: =_xlfn.CONCAT(H21,I21,J21) -> DAURDE
B22: BC Rio Monte1 | C22: Inverter35 | D22: 46023.27 | E22: 46023.27 | F22: 46023.278 | G22: =F22-E22 -> 0.0076388889 | H22: DAU | J22: RDE | K22: Rede | L22: Queda de rede da concessionária | M22: Falha Rede | N22: Distribuídora | O22: Foi feito inspeção em todo complexo, checado nível de tensão e realizado a manobra de normalização da geração. | P22: =_xlfn.CONCAT(B22,C22,D22,E22,F22) -> BC Rio Monte1Inverter3546023,270138888946023,270138888946023,2777777778 | Q22: =_xlfn.CONCAT(H22,I22,J22) -> DAURDE
B23: BC Rio Monte1 | C23: Inverter40 | D23: 46023.27 | E23: 46023.27 | F23: 46023.278 | G23: =F23-E23 -> 0.0076388889 | H23: DAU | J23: RDE | K23: Rede | L23: Queda de rede da concessionária | M23: Falha Rede | N23: Distribuídora | O23: Foi feito inspeção em todo complexo, checado nível de tensão e realizado a manobra de normalização da geração. | P23: =_xlfn.CONCAT(B23,C23,D23,E23,F23) -> BC Rio Monte1Inverter4046023,270138888946023,270138888946023,2777777778 | Q23: =_xlfn.CONCAT(H23,I23,J23) -> DAURDE
B24: BC Rio Monte1 | C24: Inverter42 | D24: 46023.27 | E24: 46023.27 | F24: 46023.278 | G24: =F24-E24 -> 0.0076388889 | H24: DAU | J24: RDE | K24: Rede | L24: Queda de rede da concessionária | M24: Falha Rede | N24: Distribuídora | O24: Foi feito inspeção em todo complexo, checado nível de tensão e realizado a manobra de normalização da geração. | P24: =_xlfn.CONCAT(B24,C24,D24,E24,F24) -> BC Rio Monte1Inverter4246023,270138888946023,270138888946023,2777777778 | Q24: =_xlfn.CONCAT(H24,I24,J24) -> DAURDE
B25: BC Rio Monte1 | C25: Inverter41 | D25: 46023.27 | E25: 46023.27 | F25: 46023.278 | G25: =F25-E25 -> 0.0076388889 | H25: DAU | J25: RDE | K25: Rede | L25: Queda de rede da concessionária | M25: Falha Rede | N25: Distribuídora | O25: Foi feito inspeção em todo complexo, checado nível de tensão e realizado a manobra de normalização da geração. | P25: =_xlfn.CONCAT(B25,C25,D25,E25,F25) -> BC Rio Monte1Inverter4146023,270138888946023,270138888946023,2777777778 | Q25: =_xlfn.CONCAT(H25,I25,J25) -> DAURDE
B26: BC Rio Monte1 | C26: Inverter44 | D26: 46023.27 | E26: 46023.27 | F26: 46023.278 | G26: =F26-E26 -> 0.0076388889 | H26: DAU | J26: RDE | K26: Rede | L26: Queda de rede da concessionária | M26: Falha Rede | N26: Distribuídora | O26: Foi feito inspeção em todo complexo, checado nível de tensão e realizado a manobra de normalização da geração. | P26: =_xlfn.CONCAT(B26,C26,D26,E26,F26) -> BC Rio Monte1Inverter4446023,270138888946023,270138888946023,2777777778 | Q26: =_xlfn.CONCAT(H26,I26,J26) -> DAURDE
B27: BC Rio Monte1 | C27: Inverter43 | D27: 46023.27 | E27: 46023.27 | F27: 46023.278 | G27: =F27-E27 -> 0.0076388889 | H27: DAU | J27: RDE | K27: Rede | L27: Queda de rede da concessionária | M27: Falha Rede | N27: Distribuídora | O27: Foi feito inspeção em todo complexo, checado nível de tensão e realizado a manobra de normalização da geração. | P27: =_xlfn.CONCAT(B27,C27,D27,E27,F27) -> BC Rio Monte1Inverter4346023,270138888946023,270138888946023,2777777778 | Q27: =_xlfn.CONCAT(H27,I27,J27) -> DAURDE
B28: BC Rio Monte1 | C28: Inverter45 | D28: 46023.27 | E28: 46023.27 | F28: 46023.278 | G28: =F28-E28 -> 0.0076388889 | H28: DAU | J28: RDE | K28: Rede | L28: Queda de rede da concessionária | M28: Falha Rede | N28: Distribuídora | O28: Foi feito inspeção em todo complexo, checado nível de tensão e realizado a manobra de normalização da geração. | P28: =_xlfn.CONCAT(B28,C28,D28,E28,F28) -> BC Rio Monte1Inverter4546023,270138888946023,270138888946023,2777777778 | Q28: =_xlfn.CONCAT(H28,I28,J28) -> DAURDE
B29: BC Rio Bonito2 | C29: INV-001 | D29: 46023.283 | E29: 46023.283 | F29: 46023.365 | G29: =F29-E29 -> 0.08125 | H29: LIG | I29: RFO | J29: COM | K29: Comunicação | L29: Configuração do sistema de comunicação | M29: Falha Comunicação | N29: Prestador de Serviço O&M | O29: Configurado sistema de comunicação | P29: =_xlfn.CONCAT(B29,C29,D29,E29,F29) -> BC Rio Bonito2INV-00146023,283333333346023,283333333346023,3645833333 | Q29: =_xlfn.CONCAT(H29,I29,J29) -> LIGRFOCOM
B30: BC Rio Bonito2 | C30: INV-002 | D30: 46023.283 | E30: 46023.283 | F30: 46023.365 | G30: =F30-E30 -> 0.08125 | H30: LIG | I30: RFO | J30: COM | K30: Comunicação | L30: Configuração do sistema de comunicação | M30: Falha Comunicação | N30: Prestador de Serviço O&M | O30: Configurado sistema de comunicação | P30: =_xlfn.CONCAT(B30,C30,D30,E30,F30) -> BC Rio Bonito2INV-00246023,283333333346023,283333333346023,3645833333 | Q30: =_xlfn.CONCAT(H30,I30,J30) -> LIGRFOCOM
B31: BC Rio Bonito2 | C31: INV-003 | D31: 46023.283 | E31: 46023.283 | F31: 46023.365 | G31: =F31-E31 -> 0.08125 | H31: LIG | I31: RFO | J31: COM | K31: Comunicação | L31: Configuração do sistema de comunicação | M31: Falha Comunicação | N31: Prestador de Serviço O&M | O31: Configurado sistema de comunicação | P31: =_xlfn.CONCAT(B31,C31,D31,E31,F31) -> BC Rio Bonito2INV-00346023,283333333346023,283333333346023,3645833333 | Q31: =_xlfn.CONCAT(H31,I31,J31) -> LIGRFOCOM
B32: BC Rio Bonito2 | C32: INV-004 | D32: 46023.283 | E32: 46023.283 | F32: 46023.365 | G32: =F32-E32 -> 0.08125 | H32: LIG | I32: RFO | J32: COM | K32: Comunicação | L32: Configuração do sistema de comunicação | M32: Falha Comunicação | N32: Prestador de Serviço O&M | O32: Configurado sistema de comunicação | P32: =_xlfn.CONCAT(B32,C32,D32,E32,F32) -> BC Rio Bonito2INV-00446023,283333333346023,283333333346023,3645833333 | Q32: =_xlfn.CONCAT(H32,I32,J32) -> LIGRFOCOM
B33: BC Caiaponia1 | C33: SG60KTL(COM1-001)_001_007 | D33: 46023.287 | E33: 46023.287 | F33: 46023.901 | G33: =F33-E33 -> 0.61388889 | H33: DAU | J33: RDE | K33: =_xlfn.XLOOKUP(J33,REF!$D$2:$D$12,REF!$E$2:$E$12) -> Rede | L33: Queda de rede da concessionária. | M33: Falha Rede | N33: Distribuidora | O33: Foi feito inspeção em todo complexo, checado nível de tensão e resetado relé e rearmado os disjuntores. | P33: =_xlfn.CONCAT(B33,C33,D33,E33,F33) -> BC Caiaponia1SG60KTL(COM1-001)_001_00746023,287546023,287546023,9013888889 | Q33: =_xlfn.CONCAT(H33,I33,J33) -> DAURDE
B34: BC Caiaponia1 | C34: SG60KTL(COM1-002)_001_010 | D34: 46023.287 | E34: 46023.287 | F34: 46023.901 | G34: =F34-E34 -> 0.61388889 | H34: DAU | J34: RDE | K34: =_xlfn.XLOOKUP(J34,REF!$D$2:$D$12,REF!$E$2:$E$12) -> Rede | L34: Queda de rede da concessionária. | M34: Falha Rede | N34: Distribuidora | O34: Foi feito inspeção em todo complexo, checado nível de tensão e resetado relé e rearmado os disjuntores. | P34: =_xlfn.CONCAT(B34,C34,D34,E34,F34) -> BC Caiaponia1SG60KTL(COM1-002)_001_01046023,287546023,287546023,9013888889 | Q34: =_xlfn.CONCAT(H34,I34,J34) -> DAURDE
B35: BC Caiaponia1 | C35: SG60KTL(COM1-003)_001_011 | D35: 46023.287 | E35: 46023.287 | F35: 46023.901 | G35: =F35-E35 -> 0.61388889 | H35: DAU | J35: RDE | K35: =_xlfn.XLOOKUP(J35,REF!$D$2:$D$12,REF!$E$2:$E$12) -> Rede | L35: Queda de rede da concessionária. | M35: Falha Rede | N35: Distribuidora | O35: Foi feito inspeção em todo complexo, checado nível de tensão e resetado relé e rearmado os disjuntores. | P35: =_xlfn.CONCAT(B35,C35,D35,E35,F35) -> BC Caiaponia1SG60KTL(COM1-003)_001_01146023,287546023,287546023,9013888889 | Q35: =_xlfn.CONCAT(H35,I35,J35) -> DAURDE
B36: BC Caiaponia1 | C36: SG60KTL(COM1-004)_001_014 | D36: 46023.287 | E36: 46023.287 | F36: 46023.901 | G36: =F36-E36 -> 0.61388889 | H36: DAU | J36: RDE | K36: =_xlfn.XLOOKUP(J36,REF!$D$2:$D$12,REF!$E$2:$E$12) -> Rede | L36: Queda de rede da concessionária. | M36: Falha Rede | N36: Distribuidora | O36: Foi feito inspeção em todo complexo, checado nível de tensão e resetado relé e rearmado os disjuntores. | P36: =_xlfn.CONCAT(B36,C36,D36,E36,F36) -> BC Caiaponia1SG60KTL(COM1-004)_001_01446023,287546023,287546023,9013888889 | Q36: =_xlfn.CONCAT(H36,I36,J36) -> DAURDE
B37: BC Caiaponia1 | C37: SG60KTL(COM1-005)_001_017 | D37: 46023.287 | E37: 46023.287 | F37: 46023.901 | G37: =F37-E37 -> 0.61388889 | H37: DAU | J37: RDE | K37: =_xlfn.XLOOKUP(J37,REF!$D$2:$D$12,REF!$E$2:$E$12) -> Rede | L37: Queda de rede da concessionária. | M37: Falha Rede | N37: Distribuidora | O37: Foi feito inspeção em todo complexo, checado nível de tensão e resetado relé e rearmado os disjuntores. | P37: =_xlfn.CONCAT(B37,C37,D37,E37,F37) -> BC Caiaponia1SG60KTL(COM1-005)_001_01746023,287546023,287546023,9013888889 | Q37: =_xlfn.CONCAT(H37,I37,J37) -> DAURDE
B38: BC Caiaponia1 | C38: SG60KTL(COM1-006)_001_016 | D38: 46023.287 | E38: 46023.287 | F38: 46023.901 | G38: =F38-E38 -> 0.61388889 | H38: DAU | J38: RDE | K38: =_xlfn.XLOOKUP(J38,REF!$D$2:$D$12,REF!$E$2:$E$12) -> Rede | L38: Queda de rede da concessionária. | M38: Falha Rede | N38: Distribuidora | O38: Foi feito inspeção em todo complexo, checado nível de tensão e resetado relé e rearmado os disjuntores. | P38: =_xlfn.CONCAT(B38,C38,D38,E38,F38) -> BC Caiaponia1SG60KTL(COM1-006)_001_01646023,287546023,287546023,9013888889 | Q38: =_xlfn.CONCAT(H38,I38,J38) -> DAURDE
B39: BC Caiaponia1 | C39: SG60KTL(COM1-007)_001_013 | D39: 46023.287 | E39: 46023.287 | F39: 46023.901 | G39: =F39-E39 -> 0.61388889 | H39: DAU | J39: RDE | K39: =_xlfn.XLOOKUP(J39,REF!$D$2:$D$12,REF!$E$2:$E$12) -> Rede | L39: Queda de rede da concessionária. | M39: Falha Rede | N39: Distribuidora | O39: Foi feito inspeção em todo complexo, checado nível de tensão e resetado relé e rearmado os disjuntores. | P39: =_xlfn.CONCAT(B39,C39,D39,E39,F39) -> BC Caiaponia1SG60KTL(COM1-007)_001_01346023,287546023,287546023,9013888889 | Q39: =_xlfn.CONCAT(H39,I39,J39) -> DAURDE
B40: BC Caiaponia1 | C40: SG60KTL(COM1-008)_001_001 | D40: 46023.287 | E40: 46023.287 | F40: 46023.901 | G40: =F40-E40 -> 0.61388889 | H40: DAU | J40: RDE | K40: =_xlfn.XLOOKUP(J40,REF!$D$2:$D$12,REF!$E$2:$E$12) -> Rede | L40: Queda de rede da concessionária. | M40: Falha Rede | N40: Distribuidora | O40: Foi feito inspeção em todo complexo, checado nível de tensão e resetado relé e rearmado os disjuntores. | P40: =_xlfn.CONCAT(B40,C40,D40,E40,F40) -> BC Caiaponia1SG60KTL(COM1-008)_001_00146023,287546023,287546023,9013888889 | Q40: =_xlfn.CONCAT(H40,I40,J40) -> DAURDE
B41: BC Caiaponia1 | C41: SG60KTL(COM1-009) | D41: 46023.287 | E41: 46023.287 | F41: 46023.901 | G41: =F41-E41 -> 0.61388889 | H41: DAU | J41: RDE | K41: =_xlfn.XLOOKUP(J41,REF!$D$2:$D$12,REF!$E$2:$E$12) -> Rede | L41: Queda de rede da concessionária. | M41: Falha Rede | N41: Distribuidora | O41: Foi feito inspeção em todo complexo, checado nível de tensão e resetado relé e rearmado os disjuntores. | P41: =_xlfn.CONCAT(B41,C41,D41,E41,F41) -> BC Caiaponia1SG60KTL(COM1-009)46023,287546023,287546023,9013888889 | Q41: =_xlfn.CONCAT(H41,I41,J41) -> DAURDE
B42: BC Caiaponia1 | C42: SG60KTL(COM1-010) | D42: 46023.287 | E42: 46023.287 | F42: 46023.901 | G42: =F42-E42 -> 0.61388889 | H42: DAU | J42: RDE | K42: =_xlfn.XLOOKUP(J42,REF!$D$2:$D$12,REF!$E$2:$E$12) -> Rede | L42: Queda de rede da concessionária. | M42: Falha Rede | N42: Distribuidora | O42: Foi feito inspeção em todo complexo, checado nível de tensão e resetado relé e rearmado os disjuntores. | P42: =_xlfn.CONCAT(B42,C42,D42,E42,F42) -> BC Caiaponia1SG60KTL(COM1-010)46023,287546023,287546023,9013888889 | Q42: =_xlfn.CONCAT(H42,I42,J42) -> DAURDE
B43: BC Caiaponia1 | C43: SG60KTL(COM1-011) | D43: 46023.287 | E43: 46023.287 | F43: 46023.901 | G43: =F43-E43 -> 0.61388889 | H43: DAU | J43: RDE | K43: =_xlfn.XLOOKUP(J43,REF!$D$2:$D$12,REF!$E$2:$E$12) -> Rede | L43: Queda de rede da concessionária. | M43: Falha Rede | N43: Distribuidora | O43: Foi feito inspeção em todo complexo, checado nível de tensão e resetado relé e rearmado os disjuntores. | P43: =_xlfn.CONCAT(B43,C43,D43,E43,F43) -> BC Caiaponia1SG60KTL(COM1-011)46023,287546023,287546023,9013888889 | Q43: =_xlfn.CONCAT(H43,I43,J43) -> DAURDE
B44: BC Caiaponia1 | C44: SG60KTL(COM1-012) | D44: 46023.287 | E44: 46023.287 | F44: 46023.901 | G44: =F44-E44 -> 0.61388889 | H44: DAU | J44: RDE | K44: =_xlfn.XLOOKUP(J44,REF!$D$2:$D$12,REF!$E$2:$E$12) -> Rede | L44: Queda de rede da concessionária. | M44: Falha Rede | N44: Distribuidora | O44: Foi feito inspeção em todo complexo, checado nível de tensão e resetado relé e rearmado os disjuntores. | P44: =_xlfn.CONCAT(B44,C44,D44,E44,F44) -> BC Caiaponia1SG60KTL(COM1-012)46023,287546023,287546023,9013888889 | Q44: =_xlfn.CONCAT(H44,I44,J44) -> DAURDE
... B61: BC Caiaponia1 | C61: SG50CX(COM1-025) | D61: 46023.287 | E61: 46023.287 | F61: 46023.901 | G61: =F61-E61 -> 0.61388889 | H61: DAU | J61: RDE | K61: =_xlfn.XLOOKUP(J61,REF!$D$2:$D$12,REF!$E$2:$E$12) -> Rede | L61: Queda de rede da concessionária. | M61: Falha Rede | N61: Distribuidora | O61: Foi feito inspeção em todo complexo, checado nível de tensão e resetado relé e rearmado os disjuntores. | P61: =_xlfn.CONCAT(B61,C61,D61,E61,F61) -> BC Caiaponia1SG50CX(COM1-025)46023,287546023,287546023,9013888889 | Q61: =_xlfn.CONCAT(H61,I61,J61) -> DAURDE
B62: BC Ibiuna 1.1 | C62: Inverter(MBUS-12) | D62: 46023.321 | E62: 46023.321 | F62: 46028.521 | G62: =F62-E62 -> 5.2 | H62: DAU | J62: RDE | K62: Rede | L62: Função 59N atuada no relé. | M62: Falha Rede | N62: Distribuídora | O62: Foi feito inspeção em todo complexo, checado nível de tensão e realizado a manobra de normalização da geração. | P62: =_xlfn.CONCAT(B62,C62,D62,E62,F62) -> BC Ibiuna 1.1Inverter(MBUS-12)46023,320833333346023,320833333346028,5208333333 | Q62: =_xlfn.CONCAT(H62,I62,J62) -> DAURDE
B63: BC Ibiuna 1.1 | C63: Inverter(MBUS-13) | D63: 46023.321 | E63: 46023.321 | F63: 46028.521 | G63: =F63-E63 -> 5.2 | H63: DAU | J63: RDE | K63: Rede | L63: Função 59N atuada no relé. | M63: Falha Rede | N63: Distribuídora | O63: Foi feito inspeção em todo complexo, checado nível de tensão e realizado a manobra de normalização da geração. | P63: =_xlfn.CONCAT(B63,C63,D63,E63,F63) -> BC Ibiuna 1.1Inverter(MBUS-13)46023,320833333346023,320833333346028,5208333333 | Q63: =_xlfn.CONCAT(H63,I63,J63) -> DAURDE
B64: BC Ibiuna 1.1 | C64: Inverter(MBUS-14) | D64: 46023.321 | E64: 46023.321 | F64: 46028.521 | G64: =F64-E64 -> 5.2 | H64: DAU | J64: RDE | K64: Rede | L64: Função 59N atuada no relé. | M64: Falha Rede | N64: Distribuídora | O64: Foi feito inspeção em todo complexo, checado nível de tensão e realizado a manobra de normalização da geração. | P64: =_xlfn.CONCAT(B64,C64,D64,E64,F64) -> BC Ibiuna 1.1Inverter(MBUS-14)46023,320833333346023,320833333346028,5208333333 | Q64: =_xlfn.CONCAT(H64,I64,J64) -> DAURDE
B65: BC Ibiuna 1.1 | C65: Inverter(MBUS-15) | D65: 46023.321 | E65: 46023.321 | F65: 46028.521 | G65: =F65-E65 -> 5.2 | H65: DAU | J65: RDE | K65: Rede | L65: Função 59N atuada no relé. | M65: Falha Rede | N65: Distribuídora | O65: Foi feito inspeção em todo complexo, checado nível de tensão e realizado a manobra de normalização da geração. | P65: =_xlfn.CONCAT(B65,C65,D65,E65,F65) -> BC Ibiuna 1.1Inverter(MBUS-15)46023,320833333346023,320833333346028,5208333333 | Q65: =_xlfn.CONCAT(H65,I65,J65) -> DAURDE
B66: BC Ibiuna 1.2 | C66: Inverter(MBUS-12) | D66: 46023.321 | E66: 46023.321 | F66: 46028.521 | G66: =F66-E66 -> 5.2 | H66: DAU | J66: RDE | K66: Rede | L66: Função 59N, 27ABC atuada no relé. | M66: Falha Rede | N66: Distribuídora | O66: Foi feito inspeção em todo complexo, checado nível de tensão e realizado a manobra de normalização da geração. | P66: =_xlfn.CONCAT(B66,C66,D66,E66,F66) -> BC Ibiuna 1.2Inverter(MBUS-12)46023,320833333346023,320833333346028,5208333333 | Q66: =_xlfn.CONCAT(H66,I66,J66) -> DAURDE
B67: BC Ibiuna 1.2 | C67: Inverter(MBUS-13) | D67: 46023.321 | E67: 46023.321 | F67: 46028.521 | G67: =F67-E67 -> 5.2 | H67: DAU | J67: RDE | K67: Rede | L67: Função 59N, 27ABC atuada no relé. | M67: Falha Rede | N67: Distribuídora | O67: Foi feito inspeção em todo complexo, checado nível de tensão e realizado a manobra de normalização da geração. | P67: =_xlfn.CONCAT(B67,C67,D67,E67,F67) -> BC Ibiuna 1.2Inverter(MBUS-13)46023,320833333346023,320833333346028,5208333333 | Q67: =_xlfn.CONCAT(H67,I67,J67) -> DAURDE
B68: BC Ibiuna 1.2 | C68: Inverter(MBUS-14) | D68: 46023.321 | E68: 46023.321 | F68: 46028.521 | G68: =F68-E68 -> 5.2 | H68: DAU | J68: RDE | K68: Rede | L68: Função 59N, 27ABC atuada no relé. | M68: Falha Rede | N68: Distribuídora | O68: Foi feito inspeção em todo complexo, checado nível de tensão e realizado a manobra de normalização da geração. | P68: =_xlfn.CONCAT(B68,C68,D68,E68,F68) -> BC Ibiuna 1.2Inverter(MBUS-14)46023,320833333346023,320833333346028,5208333333 | Q68: =_xlfn.CONCAT(H68,I68,J68) -> DAURDE
B69: BC Ibiuna 1.2 | C69: Inverter(MBUS-15) | D69: 46023.321 | E69: 46023.321 | F69: 46028.521 | G69: =F69-E69 -> 5.2 | H69: DAU | J69: RDE | K69: Rede | L69: Função 59N, 27ABC atuada no relé. | M69: Falha Rede | N69: Distribuídora | O69: Foi feito inspeção em todo complexo, checado nível de tensão e realizado a manobra de normalização da geração. | P69: =_xlfn.CONCAT(B69,C69,D69,E69,F69) -> BC Ibiuna 1.2Inverter(MBUS-15)46023,320833333346023,320833333346028,5208333333 | Q69: =_xlfn.CONCAT(H69,I69,J69) -> DAURDE
B70: BC Vazante 1.1 | C70: Inverter13 | D70: 46023.359 | E70: 46023.359 | F70: 46036.479 | G70: =F70-E70 -> 13.120139 | H70: DAU | J70: INV | K70: Inversor | L70: Trip no disjuntor. | M70: Falha Inversor | N70: Prestador de Serviço O&M | O70: Foi feito inspeção em todo complexo, checado nível de tensão e realizado a manobra de normalização da geração. | P70: =_xlfn.CONCAT(B70,C70,D70,E70,F70) -> BC Vazante 1.1Inverter1346023,359027777846023,359027777846036,4791666667 | Q70: =_xlfn.CONCAT(H70,I70,J70) -> DAUINV
B71: BC Formoso1.2 | C71: Inverter(MBUS-13) | D71: 46023.426 | E71: 46023.426 | F71: 46024.396 | G71: =F71-E71 -> 0.97013889 | H71: DAU | J71: RDE | K71: Rede | L71: Função 86 atuada no relé. | M71: Falha Rede | N71: Distribuídora | O71: Foi feito inspeção em todo complexo, checado nível de tensão e realizado a manobra de normalização da geração. | P71: =_xlfn.CONCAT(B71,C71,D71,E71,F71) -> BC Formoso1.2Inverter(MBUS-13)46023,425694444446023,425694444446024,3958333333 | Q71: =_xlfn.CONCAT(H71,I71,J71) -> DAURDE
B72: BC Formoso1.2 | C72: Inverter(MBUS-12) | D72: 46023.426 | E72: 46023.426 | F72: 46024.396 | G72: =F72-E72 -> 0.97013889 | H72: DAU | J72: RDE | K72: Rede | L72: Função 86 atuada no relé. | M72: Falha Rede | N72: Distribuídora | O72: Foi feito inspeção em todo complexo, checado nível de tensão e realizado a manobra de normalização da geração. | P72: =_xlfn.CONCAT(B72,C72,D72,E72,F72) -> BC Formoso1.2Inverter(MBUS-12)46023,425694444446023,425694444446024,3958333333 | Q72: =_xlfn.CONCAT(H72,I72,J72) -> DAURDE
B73: BC Formoso1.2 | C73: Inverter(MBUS-15) | D73: 46023.426 | E73: 46023.426 | F73: 46024.396 | G73: =F73-E73 -> 0.97013889 | H73: DAU | J73: RDE | K73: Rede | L73: Função 86 atuada no relé. | M73: Falha Rede | N73: Distribuídora | O73: Foi feito inspeção em todo complexo, checado nível de tensão e realizado a manobra de normalização da geração. | P73: =_xlfn.CONCAT(B73,C73,D73,E73,F73) -> BC Formoso1.2Inverter(MBUS-15)46023,425694444446023,425694444446024,3958333333 | Q73: =_xlfn.CONCAT(H73,I73,J73) -> DAURDE
... B84: BC Formoso2.3 | C84: Inverter(MBUS-12) | D84: 46023.426 | E84: 46023.426 | F84: 46024.396 | G84: =F84-E84 -> 0.97013889 | H84: DAU | J84: RDE | K84: Rede | L84: Função 86 atuada no relé. | M84: Falha Rede | N84: Distribuídora | O84: Foi feito inspeção em todo complexo, checado nível de tensão e realizado a manobra de normalização da geração. | P84: =_xlfn.CONCAT(B84,C84,D84,E84,F84) -> BC Formoso2.3Inverter(MBUS-12)46023,425694444446023,425694444446024,3958333333 | Q84: =_xlfn.CONCAT(H84,I84,J84) -> DAURDE
B85: BC Vazante1.3 | C85: Inversor 1 | D85: 46023.517 | E85: 46023.517 | F85: 46023.573 | G85: =F85-E85 -> 0.055555556 | H85: DAU | J85: RDE | K85: Rede | L85: Queda de rede da concessionária | M85: Falha Rede | N85: Distribuídora | O85: Foi feito inspeção em todo complexo, checado nível de tensão e realizado a manobra de normalização da geração. | P85: =_xlfn.CONCAT(B85,C85,D86,E85,F85) -> BC Vazante1.3Inversor 146023,517361111146023,517361111146023,5729166667 | Q85: =_xlfn.CONCAT(H85,I85,J85) -> DAURDE
B86: BC Vazante1.3 | C86: Inversor 2 | D86: 46023.517 | E86: 46023.517 | F86: 46023.573 | G86: =F86-E86 -> 0.055555556 | H86: DAU | J86: RDE | K86: Rede | L86: Queda de rede da concessionária | M86: Falha Rede | N86: Distribuídora | O86: Foi feito inspeção em todo complexo, checado nível de tensão e realizado a manobra de normalização da geração. | P86: =_xlfn.CONCAT(B86,C86,D87,E86,F86) -> BC Vazante1.3Inversor 246023,517361111146023,517361111146023,5729166667 | Q86: =_xlfn.CONCAT(H86,I86,J86) -> DAURDE
B87: BC Vazante1.3 | C87: Inversor 3 | D87: 46023.517 | E87: 46023.517 | F87: 46023.573 | G87: =F87-E87 -> 0.055555556 | H87: DAU | J87: RDE | K87: Rede | L87: Queda de rede da concessionária | M87: Falha Rede | N87: Distribuídora | O87: Foi feito inspeção em todo complexo, checado nível de tensão e realizado a manobra de normalização da geração. | P87: =_xlfn.CONCAT(B87,C87,D88,E87,F87) -> BC Vazante1.3Inversor 346023,517361111146023,517361111146023,5729166667 | Q87: =_xlfn.CONCAT(H87,I87,J87) -> DAURDE
B88: BC Vazante1.3 | C88: Inversor 4 | D88: 46023.517 | E88: 46023.517 | F88: 46023.573 | G88: =F88-E88 -> 0.055555556 | H88: DAU | J88: RDE | K88: Rede | L88: Queda de rede da concessionária | M88: Falha Rede | N88: Distribuídora | O88: Foi feito inspeção em todo complexo, checado nível de tensão e realizado a manobra de normalização da geração. | P88: =_xlfn.CONCAT(B88,C88,D89,E88,F88) -> BC Vazante1.3Inversor 446023,517361111146023,517361111146023,5729166667 | Q88: =_xlfn.CONCAT(H88,I88,J88) -> DAURDE
B89: BC Vazante1.3 | C89: Inversor 5 | D89: 46023.517 | E89: 46023.517 | F89: 46023.573 | G89: =F89-E89 -> 0.055555556 | H89: DAU | J89: RDE | K89: Rede | L89: Queda de rede da concessionária | M89: Falha Rede | N89: Distribuídora | O89: Foi feito inspeção em todo complexo, checado nível de tensão e realizado a manobra de normalização da geração. | P89: =_xlfn.CONCAT(B89,C89,D90,E89,F89) -> BC Vazante1.3Inversor 546023,517361111146023,517361111146023,5729166667 | Q89: =_xlfn.CONCAT(H89,I89,J89) -> DAURDE
B90: BC Vazante1.3 | C90: Inversor 6 | D90: 46023.517 | E90: 46023.517 | F90: 46023.573 | G90: =F90-E90 -> 0.055555556 | H90: DAU | J90: RDE | K90: Rede | L90: Queda de rede da concessionária | M90: Falha Rede | N90: Distribuídora | O90: Foi feito inspeção em todo complexo, checado nível de tensão e realizado a manobra de normalização da geração. | P90: =_xlfn.CONCAT(B90,C90,D91,E90,F90) -> BC Vazante1.3Inversor 646023,517361111146023,517361111146023,5729166667 | Q90: =_xlfn.CONCAT(H90,I90,J90) -> DAURDE
B91: BC Vazante1.3 | C91: Inversor 7 | D91: 46023.517 | E91: 46023.517 | F91: 46023.573 | G91: =F91-E91 -> 0.055555556 | H91: DAU | J91: RDE | K91: Rede | L91: Queda de rede da concessionária | M91: Falha Rede | N91: Distribuídora | O91: Foi feito inspeção em todo complexo, checado nível de tensão e realizado a manobra de normalização da geração. | P91: =_xlfn.CONCAT(B91,C91,D92,E91,F91) -> BC Vazante1.3Inversor 746023,517361111146023,517361111146023,5729166667 | Q91: =_xlfn.CONCAT(H91,I91,J91) -> DAURDE
B92: BC Vazante1.3 | C92: Inversor 8 | D92: 46023.517 | E92: 46023.517 | F92: 46023.573 | G92: =F92-E92 -> 0.055555556 | H92: DAU | J92: RDE | K92: Rede | L92: Queda de rede da concessionária | M92: Falha Rede | N92: Distribuídora | O92: Foi feito inspeção em todo complexo, checado nível de tensão e realizado a manobra de normalização da geração. | P92: =_xlfn.CONCAT(B92,C92,D93,E92,F92) -> BC Vazante1.3Inversor 846023,517361111146023,517361111146023,5729166667 | Q92: =_xlfn.CONCAT(H92,I92,J92) -> DAURDE
B93: BC Vazante1.3 | C93: Inversor 9 | D93: 46023.517 | E93: 46023.517 | F93: 46023.573 | G93: =F93-E93 -> 0.055555556 | H93: DAU | J93: RDE | K93: Rede | L93: Queda de rede da concessionária | M93: Falha Rede | N93: Distribuídora | O93: Foi feito inspeção em todo complexo, checado nível de tensão e realizado a manobra de normalização da geração. | P93: =_xlfn.CONCAT(B93,C93,D94,E93,F93) -> BC Vazante1.3Inversor 946024,256944444446023,517361111146023,5729166667 | Q93: =_xlfn.CONCAT(H93,I93,J93) -> DAURDE
B94: BC Caiaponia2.1 | C94: 215KTL-H3(MBUS-12) | D94: 46024.257 | E94: 46024.257 | F94: 46024.317 | G94: =+F94-E94 -> 0.059722222 | H94: LIG | I94: RFO | J94: COM | K94: Comunicação | L94: Falha de comunicação | M94: Falha Comunicação | N94: Prestador de Serviço O&M | O94: Logger resetado. | P94: =_xlfn.CONCAT(B94,C94,D94,E94,F94) -> BC Caiaponia2.1215KTL-H3(MBUS-12)46024,256944444446024,256944444446024,3166666667 | Q94: =_xlfn.CONCAT(H94,I94,J94) -> LIGRFOCOM
B95: BC Caiaponia2.1 | C95: 215KTL-H3(MBUS-13) | D95: 46024.257 | E95: 46024.257 | F95: 46024.317 | G95: =F95-E95 -> 0.059722222 | H95: LIG | I95: RFO | J95: COM | K95: Comunicação | L95: Falha de comunicação | M95: Falha Comunicação | N95: Prestador de Serviço O&M | O95: Logger resetado. | P95: =_xlfn.CONCAT(B95,C95,D95,E95,F95) -> BC Caiaponia2.1215KTL-H3(MBUS-13)46024,256944444446024,256944444446024,3166666667 | Q95: =_xlfn.CONCAT(H95,I95,J95) -> LIGRFOCOM
B96: BC Caiaponia2.1 | C96: 215KTL-H3(MBUS-14) | D96: 46024.257 | E96: 46024.257 | F96: 46024.317 | G96: =F94-E94 -> 0.059722222 | H96: LIG | I96: RFO | J96: COM | K96: Comunicação | L96: Falha de comunicação | M96: Falha Comunicação | N96: Prestador de Serviço O&M | O96: Logger resetado. | P96: =_xlfn.CONCAT(B96,C96,D96,E96,F96) -> BC Caiaponia2.1215KTL-H3(MBUS-14)46024,256944444446024,256944444446024,3166666667 | Q96: =_xlfn.CONCAT(H96,I96,J96) -> LIGRFOCOM
B97: BC Caiaponia2.1 | C97: 215KTL-H3(MBUS-15) | D97: 46024.257 | E97: 46024.257 | F97: 46024.317 | G97: =F97-E97 -> 0.059722222 | H97: LIG | I97: RFO | J97: COM | K97: Comunicação | L97: Falha de comunicação | M97: Falha Comunicação | N97: Prestador de Serviço O&M | O97: Logger resetado. | P97: =_xlfn.CONCAT(B97,C97,D97,E97,F97) -> BC Caiaponia2.1215KTL-H3(MBUS-15)46024,256944444446024,256944444446024,3166666667 | Q97: =_xlfn.CONCAT(H97,I97,J97) -> LIGRFOCOM
B98: BC Caiaponia2.1 | C98: 215KTL-H3(MBUS-16) | D98: 46024.257 | E98: 46024.257 | F98: 46024.317 | G98: =F98-E98 -> 0.059722222 | H98: LIG | I98: RFO | J98: COM | K98: Comunicação | L98: Falha de comunicação | M98: Falha Comunicação | N98: Prestador de Serviço O&M | O98: Logger resetado. | P98: =_xlfn.CONCAT(B98,C98,D98,E98,F98) -> BC Caiaponia2.1215KTL-H3(MBUS-16)46024,256944444446024,256944444446024,3166666667 | Q98: =_xlfn.CONCAT(H98,I98,J98) -> LIGRFOCOM
B99: BC Caiaponia2.2 | C99: 215KTL-H3(MBUS-12) | D99: 46024.257 | E99: 46024.257 | F99: 46024.317 | G99: =F99-E99 -> 0.059722222 | H99: LIG | I99: RFO | J99: COM | K99: Comunicação | L99: Falha de comunicação | M99: Falha Comunicação | N99: Prestador de Serviço O&M | O99: Logger resetado. | P99: =_xlfn.CONCAT(B99,C99,D99,E99,F99) -> BC Caiaponia2.2215KTL-H3(MBUS-12)46024,256944444446024,256944444446024,3166666667 | Q99: =_xlfn.CONCAT(H99,I99,J99) -> LIGRFOCOM
B100: BC Caiaponia2.2 | C100: 215KTL-H3(MBUS-13) | D100: 46024.257 | E100: 46024.257 | F100: 46024.317 | G100: =F100-E100 -> 0.059722222 | H100: LIG | I100: RFO | J100: COM | K100: Comunicação | L100: Falha de comunicação | M100: Falha Comunicação | N100: Prestador de Serviço O&M | O100: Logger resetado. | P100: =_xlfn.CONCAT(B100,C100,D100,E100,F100) -> BC Caiaponia2.2215KTL-H3(MBUS-13)46024,256944444446024,256944444446024,3166666667 | Q100: =_xlfn.CONCAT(H100,I100,J100) -> LIGRFOCOM
B101: BC Caiaponia2.2 | C101: 215KTL-H3(MBUS-14) | D101: 46024.257 | E101: 46024.257 | F101: 46024.317 | G101: =F101-E101 -> 0.059722222 | H101: LIG | I101: RFO | J101: COM | K101: Comunicação | L101: Falha de comunicação | M101: Falha Comunicação | N101: Prestador de Serviço O&M | O101: Logger resetado. | P101: =_xlfn.CONCAT(B101,C101,D101,E101,F101) -> BC Caiaponia2.2215KTL-H3(MBUS-14)46024,256944444446024,256944444446024,3166666667 | Q101: =_xlfn.CONCAT(H101,I101,J101) -> LIGRFOCOM
B102: BC Caiaponia2.2 | C102: 215KTL-H3(MBUS-15) | D102: 46024.257 | E102: 46024.257 | F102: 46024.317 | G102: =F102-E102 -> 0.059722222 | H102: LIG | I102: RFO | J102: COM | K102: Comunicação | L102: Falha de comunicação | M102: Falha Comunicação | N102: Prestador de Serviço O&M | O102: Logger resetado. | P102: =_xlfn.CONCAT(B102,C102,D102,E102,F102) -> BC Caiaponia2.2215KTL-H3(MBUS-15)46024,256944444446024,256944444446024,3166666667 | Q102: =_xlfn.CONCAT(H102,I102,J102) -> LIGRFOCOM
B103: BC Caiaponia2.2 | C103: 215KTL-H3(MBUS-16) | D103: 46024.257 | E103: 46024.257 | F103: 46024.317 | G103: =F103-E103 -> 0.059722222 | H103: LIG | I103: RFO | J103: COM | K103: Comunicação | L103: Falha de comunicação | M103: Falha Comunicação | N103: Prestador de Serviço O&M | O103: Logger resetado. | P103: =_xlfn.CONCAT(B103,C103,D103,E103,F103) -> BC Caiaponia2.2215KTL-H3(MBUS-16)46024,256944444446024,256944444446024,3166666667 | Q103: =_xlfn.CONCAT(H103,I103,J103) -> LIGRFOCOM
B104: BC Caiaponia2.3 | C104: 215KTL-H3(MBUS-12) | D104: 46024.257 | E104: 46024.257 | F104: 46024.317 | G104: =F104-E104 -> 0.059722222 | H104: LIG | I104: RFO | J104: COM | K104: Comunicação | L104: Falha de comunicação | M104: Falha Comunicação | N104: Prestador de Serviço O&M | O104: Logger resetado. | P104: =_xlfn.CONCAT(B104,C104,D104,E104,F104) -> BC Caiaponia2.3215KTL-H3(MBUS-12)46024,256944444446024,256944444446024,3166666667 | Q104: =_xlfn.CONCAT(H104,I104,J104) -> LIGRFOCOM
B105: BC Caiaponia2.3 | C105: 215KTL-H3(MBUS-13) | D105: 46024.257 | E105: 46024.257 | F105: 46024.317 | G105: =F105-E105 -> 0.059722222 | H105: LIG | I105: RFO | J105: COM | K105: Comunicação | L105: Falha de comunicação | M105: Falha Comunicação | N105: Prestador de Serviço O&M | O105: Logger resetado. | P105: =_xlfn.CONCAT(B105,C105,D105,E105,F105) -> BC Caiaponia2.3215KTL-H3(MBUS-13)46024,256944444446024,256944444446024,3166666667 | Q105: =_xlfn.CONCAT(H105,I105,J105) -> LIGRFOCOM
B106: BC Caiaponia2.3 | C106: 215KTL-H3(MBUS-14) | D106: 46024.257 | E106: 46024.257 | F106: 46024.317 | G106: =F106-E106 -> 0.059722222 | H106: LIG | I106: RFO | J106: COM | K106: Comunicação | L106: Falha de comunicação | M106: Falha Comunicação | N106: Prestador de Serviço O&M | O106: Logger resetado. | P106: =_xlfn.CONCAT(B106,C106,D106,E106,F106) -> BC Caiaponia2.3215KTL-H3(MBUS-14)46024,256944444446024,256944444446024,3166666667 | Q106: =_xlfn.CONCAT(H106,I106,J106) -> LIGRFOCOM
B107: BC Caiaponia2.3 | C107: 215KTL-H3(MBUS-15) | D107: 46024.257 | E107: 46024.257 | F107: 46024.317 | G107: =F107-E107 -> 0.059722222 | H107: LIG | I107: RFO | J107: COM | K107: Comunicação | L107: Falha de comunicação | M107: Falha Comunicação | N107: Prestador de Serviço O&M | O107: Logger resetado. | P107: =_xlfn.CONCAT(B107,C107,D107,E107,F107) -> BC Caiaponia2.3215KTL-H3(MBUS-15)46024,256944444446024,256944444446024,3166666667 | Q107: =_xlfn.CONCAT(H107,I107,J107) -> LIGRFOCOM
B108: BC Caiaponia2.3 | C108: 215KTL-H3(MBUS-16) | D108: 46024.257 | E108: 46024.257 | F108: 46024.317 | G108: =F108-E108 -> 0.059722222 | H108: LIG | I108: RFO | J108: COM | K108: Comunicação | L108: Falha de comunicação | M108: Falha Comunicação | N108: Prestador de Serviço O&M | O108: Logger resetado. | P108: =_xlfn.CONCAT(B108,C108,D108,E108,F108) -> BC Caiaponia2.3215KTL-H3(MBUS-16)46024,256944444446024,256944444446024,3166666667 | Q108: =_xlfn.CONCAT(H108,I108,J108) -> LIGRFOCOM
B109: BC Barra1 | C109: Inverter__5 | D109: 46024.372 | E109: 46024.372 | F109: 46024.423 | G109: =F109-E109 -> 0.051388889 | H109: DAU | J109: INV | K109: Inversor | L109: Inversor off-line | M109: Falha Inversor | N109: Prestador de Serviço O&M | O109: Foi realizado um reset no inversor, e foi normalizado. | P109: =_xlfn.CONCAT(B109,C109,D109,E109,F109) -> BC Barra1Inverter__546024,371527777846024,371527777846024,4229166667 | Q109: =_xlfn.CONCAT(H109,I109,J109) -> DAUINV
B110: BC Formoso2.3 | C110: Inverter(MBUS-13) | D110: 46024.444 | E110: 46024.444 | F110: 46024.667 | G110: =F110-E110 -> 0.22222222 | H110: DAU | J110: RDE | K110: Rede | L110: Queda de rede da concessionária, sem alarme no relé | M110: Falha Rede | N110: Distribuídora | O110: Foi feito inspeção em todo complexo, checado nível de tensão e resetado relé e rearmado os disjuntores. | P110: =_xlfn.CONCAT(B110,C110,D110,E110,F110) -> BC Formoso2.3Inverter(MBUS-13)46024,444444444446024,444444444446024,6666666667 | Q110: =_xlfn.CONCAT(H110,I110,J110) -> DAURDE
B111: BC Formoso2.3 | C111: Inverter(MBUS-12) | D111: 46024.444 | E111: 46024.444 | F111: 46024.667 | G111: =F111-E111 -> 0.22222222 | H111: DAU | J111: RDE | K111: Rede | L111: Queda de rede da concessionária, sem alarme no relé | M111: Falha Rede | N111: Distribuídora | O111: Foi feito inspeção em todo complexo, checado nível de tensão e resetado relé e rearmado os disjuntores. | P111: =_xlfn.CONCAT(B111,C111,D111,E111,F111) -> BC Formoso2.3Inverter(MBUS-12)46024,444444444446024,444444444446024,6666666667 | Q111: =_xlfn.CONCAT(H111,I111,J111) -> DAURDE
B112: ARAGUATINS 1.1 | C112: Inverter(MBUS-12) | D112: 46024.674 | E112: 46024.674 | F112: 46024.707 | G112: =F112-E112 -> 0.033333333 | H112: DAU | J112: RDE | K112: Rede | L112: Falha atuada no relé: 67C e 86Q. | M112: Falha Rede | N112: Distribuídora | O112: Verificado painel dos transformadores e inversores, após verificação e não constatado nenhuma anomalia, foi realizado o reset do relé de proteção e normalizada a geração da UFV. | P112: =_xlfn.CONCAT(B112,C112,D112,E112,F112) -> ARAGUATINS 1.1Inverter(MBUS-12)46024,673611111146024,673611111146024,7069444444 | Q112: =_xlfn.CONCAT(H112,I112,J112) -> DAURDE
B113: ARAGUATINS 1.1 | C113: Inverter(MBUS-13) | D113: 46024.674 | E113: 46024.674 | F113: 46024.707 | G113: =F113-E113 -> 0.033333333 | H113: DAU | J113: RDE | K113: Rede | L113: Falha atuada no relé: 67C e 86Q. | M113: Falha Rede | N113: Distribuídora | O113: Verificado painel dos transformadores e inversores, após verificação e não constatado nenhuma anomalia, foi realizado o reset do relé de proteção e normalizada a geração da UFV. | P113: =_xlfn.CONCAT(B113,C113,D113,E113,F113) -> ARAGUATINS 1.1Inverter(MBUS-13)46024,673611111146024,673611111146024,7069444444 | Q113: =_xlfn.CONCAT(H113,I113,J113) -> DAURDE
B114: ARAGUATINS 1.1 | C114: Inverter(MBUS-14) | D114: 46024.674 | E114: 46024.674 | F114: 46024.707 | G114: =F114-E114 -> 0.033333333 | H114: DAU | J114: RDE | K114: Rede | L114: Falha atuada no relé: 67C e 86Q. | M114: Falha Rede | N114: Distribuídora | O114: Verificado painel dos transformadores e inversores, após verificação e não constatado nenhuma anomalia, foi realizado o reset do relé de proteção e normalizada a geração da UFV. | P114: =_xlfn.CONCAT(B114,C114,D114,E114,F114) -> ARAGUATINS 1.1Inverter(MBUS-14)46024,673611111146024,673611111146024,7069444444 | Q114: =_xlfn.CONCAT(H114,I114,J114) -> DAURDE
B115: ARAGUATINS 1.1 | C115: Inverter(MBUS-15) | D115: 46024.674 | E115: 46024.674 | F115: 46024.707 | G115: =F115-E115 -> 0.033333333 | H115: DAU | J115: RDE | K115: Rede | L115: Falha atuada no relé: 67C e 86Q. | M115: Falha Rede | N115: Distribuídora | O115: Verificado painel dos transformadores e inversores, após verificação e não constatado nenhuma anomalia, foi realizado o reset do relé de proteção e normalizada a geração da UFV. | P115: =_xlfn.CONCAT(B115,C115,D115,E115,F115) -> ARAGUATINS 1.1Inverter(MBUS-15)46024,673611111146024,673611111146024,7069444444 | Q115: =_xlfn.CONCAT(H115,I115,J115) -> DAURDE
B116: ARAGUATINS 1.2 | C116: Inverter(MBUS-12) | D116: 46024.674 | E116: 46024.674 | F116: 46024.707 | G116: =F116-E116 -> 0.033333333 | H116: DAU | J116: RDE | K116: Rede | L116: Falha atuada no relé: 67C e 86Q. | M116: Falha Rede | N116: Distribuídora | O116: Verificado painel dos transformadores e inversores, após verificação e não constatado nenhuma anomalia, foi realizado o reset do relé de proteção e normalizada a geração da UFV. | P116: =_xlfn.CONCAT(B116,C116,D116,E116,F116) -> ARAGUATINS 1.2Inverter(MBUS-12)46024,673611111146024,673611111146024,7069444444 | Q116: =_xlfn.CONCAT(H116,I116,J116) -> DAURDE
B117: ARAGUATINS 1.2 | C117: Inverter(MBUS-13) | D117: 46024.674 | E117: 46024.674 | F117: 46024.707 | G117: =F117-E117 -> 0.033333333 | H117: DAU | J117: RDE | K117: Rede | L117: Falha atuada no relé: 67C e 86Q. | M117: Falha Rede | N117: Distribuídora | O117: Verificado painel dos transformadores e inversores, após verificação e não constatado nenhuma anomalia, foi realizado o reset do relé de proteção e normalizada a geração da UFV. | P117: =_xlfn.CONCAT(B117,C117,D117,E117,F117) -> ARAGUATINS 1.2Inverter(MBUS-13)46024,673611111146024,673611111146024,7069444444 | Q117: =_xlfn.CONCAT(H117,I117,J117) -> DAURDE
B118: ARAGUATINS 1.2 | C118: Inverter(MBUS-14) | D118: 46024.674 | E118: 46024.674 | F118: 46024.707 | G118: =F118-E118 -> 0.033333333 | H118: DAU | J118: RDE | K118: Rede | L118: Falha atuada no relé: 67C e 86Q. | M118: Falha Rede | N118: Distribuídora | O118: Verificado painel dos transformadores e inversores, após verificação e não constatado nenhuma anomalia, foi realizado o reset do relé de proteção e normalizada a geração da UFV. | P118: =_xlfn.CONCAT(B118,C118,D118,E118,F118) -> ARAGUATINS 1.2Inverter(MBUS-14)46024,673611111146024,673611111146024,7069444444 | Q118: =_xlfn.CONCAT(H118,I118,J118) -> DAURDE
B119: ARAGUATINS 1.2 | C119: Inverter(MBUS-15) | D119: 46024.674 | E119: 46024.674 | F119: 46024.707 | G119: =F119-E119 -> 0.033333333 | H119: DAU | J119: RDE | K119: Rede | L119: Falha atuada no relé: 67C e 86Q. | M119: Falha Rede | N119: Distribuídora | O119: Verificado painel dos transformadores e inversores, após verificação e não constatado nenhuma anomalia, foi realizado o reset do relé de proteção e normalizada a geração da UFV. | P119: =_xlfn.CONCAT(B119,C119,D119,E119,F119) -> ARAGUATINS 1.2Inverter(MBUS-15)46024,673611111146024,673611111146024,7069444444 | Q119: =_xlfn.CONCAT(H119,I119,J119) -> DAURDE
B120: ARAGUATINS 1.3 | C120: Inverter(MBUS-20) | D120: 46024.674 | E120: 46024.674 | F120: 46024.707 | G120: =F120-E120 -> 0.033333333 | H120: DAU | J120: RDE | K120: Rede | L120: Falha atuada no relé: 67C e 86Q. | M120: Falha Rede | N120: Distribuídora | O120: Verificado painel dos transformadores e inversores, após verificação e não constatado nenhuma anomalia, foi realizado o reset do relé de proteção e normalizada a geração da UFV. | P120: =_xlfn.CONCAT(B120,C120,D120,E120,F120) -> ARAGUATINS 1.3Inverter(MBUS-20)46024,673611111146024,673611111146024,7069444444 | Q120: =_xlfn.CONCAT(H120,I120,J120) -> DAURDE
... B135: BC Aracu5.5 | C135: Inverter(MBUS-1) | D135: 46026.26 | E135: 46026.26 | F135: 46026.272 | G135: =F135-E135 -> 0.011111111 | H135: DAU | J135: RDE | K135: Rede | L135: Função 81 e 86 atuada no relé. | M135: Falha Rede | N135: Distribuídora | O135: Foi feito inspeção em todo complexo, checado nível de tensão e realizado a manobra de normalização da geração. | P135: =_xlfn.CONCAT(B135,C135,D135,E135,F135) -> BC Aracu5.5Inverter(MBUS-1)46026,260416666746026,260416666746026,2715277778 | Q135: =_xlfn.CONCAT(H135,I135,J135) -> DAURDE
B136: BC Formoso2.2 | C136: Inverter(MBUS-14) | D136: 46026.267 | E136: 46026.267 | F136: 46027.306 | G136: =F136-E136 -> 1.0381944 | H136: LIG | I136: RFO | J136: INT | K136: =_xlfn.XLOOKUP(J136,REF!D:D,REF!E:E) -> Internet | L136: Falha de sinal de internet. | M136: Conexão c/ Internet | N136: Prestador de Serviço O&M | O136: Realizado reset no modem de internet local. Após a reinicialização, a comunicação foi restabelecida. | P136: =_xlfn.CONCAT(B136,C136,D136,E136,F136) -> BC Formoso2.2Inverter(MBUS-14)46026,267361111146026,267361111146027,3055555556 | Q136: =_xlfn.CONCAT(H136,I136,J136) -> LIGRFOINT
B137: BC Formoso2.2 | C137: Inverter(MBUS-13) | D137: 46026.267 | E137: 46026.267 | F137: 46027.306 | G137: =F137-E137 -> 1.0381944 | H137: LIG | I137: RFO | J137: INT | K137: =_xlfn.XLOOKUP(J137,REF!D:D,REF!E:E) -> Internet | L137: Falha de sinal de internet. | M137: Conexão c/ Internet | N137: Prestador de Serviço O&M | O137: Realizado reset no modem de internet local. Após a reinicialização, a comunicação foi restabelecida. | P137: =_xlfn.CONCAT(B137,C137,D137,E137,F137) -> BC Formoso2.2Inverter(MBUS-13)46026,267361111146026,267361111146027,3055555556 | Q137: =_xlfn.CONCAT(H137,I137,J137) -> LIGRFOINT
B138: BC Formoso2.2 | C138: Inverter(MBUS-12) | D138: 46026.267 | E138: 46026.267 | F138: 46027.306 | G138: =F138-E138 -> 1.0381944 | H138: LIG | I138: RFO | J138: INT | K138: =_xlfn.XLOOKUP(J138,REF!D:D,REF!E:E) -> Internet | L138: Falha de sinal de internet. | M138: Conexão c/ Internet | N138: Prestador de Serviço O&M | O138: Realizado reset no modem de internet local. Após a reinicialização, a comunicação foi restabelecida. | P138: =_xlfn.CONCAT(B138,C138,D138,E138,F138) -> BC Formoso2.2Inverter(MBUS-12)46026,267361111146026,267361111146027,3055555556 | Q138: =_xlfn.CONCAT(H138,I138,J138) -> LIGRFOINT
B139: BC Formoso2.2 | C139: Inverter(MBUS-1) | D139: 46026.267 | E139: 46026.267 | F139: 46027.306 | G139: =F139-E139 -> 1.0381944 | H139: LIG | I139: RFO | J139: INT | K139: =_xlfn.XLOOKUP(J139,REF!D:D,REF!E:E) -> Internet | L139: Falha de sinal de internet. | M139: Conexão c/ Internet | N139: Prestador de Serviço O&M | O139: Realizado reset no modem de internet local. Após a reinicialização, a comunicação foi restabelecida. | P139: =_xlfn.CONCAT(B139,C139,D139,E139,F139) -> BC Formoso2.2Inverter(MBUS-1)46026,267361111146026,267361111146027,3055555556 | Q139: =_xlfn.CONCAT(H139,I139,J139) -> LIGRFOINT
B140: ARAGUATINS 2.1 | C140: Inverter(MBUS-12) | D140: 46026.438 | E140: 46026.438 | F140: 46026.473 | G140: =F140-E140 -> 0.035416667 | H140: DAU | J140: RDE | K140: Rede | L140: Disjuntor desarmado, sem alarme no Relé | M140: Falha Rede | N140: Distribuídora | O140: Foi feito inspeção em todo complexo, checado nível de tensão e realizado a manobra de normalização da geração. | P140: =_xlfn.CONCAT(B140,C140,D140,E140,F140) -> ARAGUATINS 2.1Inverter(MBUS-12)46026,437546026,437546026,4729166667 | Q140: =_xlfn.CONCAT(H140,I140,J140) -> DAURDE
B141: ARAGUATINS 2.1 | C141: Inverter(MBUS-15) | D141: 46026.438 | E141: 46026.438 | F141: 46026.473 | G141: =F141-E141 -> 0.035416667 | H141: DAU | J141: RDE | K141: Rede | L141: Disjuntor desarmado, sem alarme no Relé | M141: Falha Rede | N141: Distribuídora | O141: Foi feito inspeção em todo complexo, checado nível de tensão e realizado a manobra de normalização da geração. | P141: =_xlfn.CONCAT(B141,C141,D141,E141,F141) -> ARAGUATINS 2.1Inverter(MBUS-15)46026,437546026,437546026,4729166667 | Q141: =_xlfn.CONCAT(H141,I141,J141) -> DAURDE
B142: ARAGUATINS 2.1 | C142: Inverter(MBUS-14) | D142: 46026.438 | E142: 46026.438 | F142: 46026.473 | G142: =F142-E142 -> 0.035416667 | H142: DAU | J142: RDE | K142: Rede | L142: Disjuntor desarmado, sem alarme no Relé | M142: Falha Rede | N142: Distribuídora | O142: Foi feito inspeção em todo complexo, checado nível de tensão e realizado a manobra de normalização da geração. | P142: =_xlfn.CONCAT(B142,C142,D142,E142,F142) -> ARAGUATINS 2.1Inverter(MBUS-14)46026,437546026,437546026,4729166667 | Q142: =_xlfn.CONCAT(H142,I142,J142) -> DAURDE
...

Sheet REF
A1: Resolução | B1: ESTADO OPERATIVO | C1: CONDIÇÃO OPERATIVA | D1: ORIGEM | E1: Definição - Origem | F1: Causa Padrão
A2: Prestador de Serviço O&M | B2: LIG | C2: NOR | D2: INV | E2: Inversor | F2: Anomalia no arranjo FV
A3: Prestador de Serviço de TI/CFTV | B3: DEM | C3: RPR | D3: RDE | E3: Rede | F3: Anomalia OP. Sistema
A4: Provedora de Internet | B4: DUR | C4: RFO | D4: COM | E4: Comunicação | F4: B. Res. Isolamento
A5: Distribuidora | B5: DAU | C5: OEM | D5: DMT | E5: Disjuntor MT | F5: COD
A6: Colaborador Brasol | B6: DPR | D6: ESO | E6: Estação Solarimétrica | F6: Conexão c/ Internet
A7: Não Aplicável | D7: INT | E7: Internet | F7: Falha Comunicação
A8: Auto-Restart | D8: PRT | E8: Relé de proteção | F8: Falha Inversor
A9: EPC | D9: TRF | E9: Transformador | F9: Falha Rede
A10: Troca em Garantia | D10: UFV | E10: UFV | F10: Falha SPDA
A11: Manutenção Corretiva | D11: CBP | E11: Cabine Primária | F11: Falha String
A12: Prestador de Serviço SCADA | D12: STR | E12: String | F12: Furto
A13: Manutenção Preventiva | D13: TRK | E13: Tracker | F13: Identif. O&M
F14: Limitação
F15: Manutenção
F16: Urgência

Sheet Dezembro
A1: UC | B1: UFV | C1: Tag | D1: Início Real do Evento | E1: Início | F1: Fim | G1: Duração | H1: Estado Operativo | I1: Condição Operativa | J1: Origem | K1: Equipamento | L1: Causa | M1: Causas Padrão | N1: Resolução | O1: Observação | P1: Concat - duplicata | Q1: Combinação
B2: BC Varjao2.1 | C2: 215KTL-H0(MBUS-12) | D2: 45992.285 | E2: 45992.285 | F2: 46001.576 | G2: 9.2916667 | H2: DAU | J2: INV | K2: Inversor | L2: Inversor 12 com falha, alarme (equipamento anormal). | M2: Falha Inversor | N2: Manutenção Corretiva | O2: Foi aberto chamado com fabricante e o caso foi tratado como garantia. Após aceite de garantia por parte do fabricante, o inversor foi substituído por um sobressalente. A huawei irá enviar um inversor novo para reposição em garantia, que irá para o estoque. | P2: =_xlfn.CONCAT(B2,C2,D2,E2,F2) -> BC Varjao2.1215KTL-H0(MBUS-12)45992,284722222245992,284722222246001,5763888889 | Q2: =_xlfn.CONCAT(H2,I2,J2) -> DAUINV
B3: BC BomSucesso | C3: SG60KTL | D3: 45992.729 | E3: 45992.729 | F3: 45992.833 | G3: 0.10416667 | H3: LIG | I3: RFO | J3: COM | K3: Comunicação | L3: Foi identificada falha de comunicação que afetou simultaneamente os inversores e o sistema de CFTV da usina. | M3: Falha Comunicação | N3: Prestador de Serviço O&M | O3: Realizado reset no modem de internet local. Após a reinicialização, a comunicação foi restabelecida. | P3: =_xlfn.CONCAT(B3,C3,D3,E3,F3) -> BC BomSucessoSG60KTL45992,729166666745992,729166666745992,8333333333 | Q3: =_xlfn.CONCAT(H3,I3,J3) -> LIGRFOCOM
B4: BC BomSucesso | C4: ABB_01 | D4: 45992.729 | E4: 45992.729 | F4: 45992.833 | G4: 0.10416667 | H4: LIG | I4: RFO | J4: COM | K4: Comunicação | L4: Foi identificada falha de comunicação que afetou simultaneamente os inversores e o sistema de CFTV da usina. | M4: Falha Comunicação | N4: Prestador de Serviço O&M | O4: Realizado reset no modem de internet local. Após a reinicialização, a comunicação foi restabelecida. | P4: =_xlfn.CONCAT(B4,C4,D4,E4,F4) -> BC BomSucessoABB_0145992,729166666745992,729166666745992,8333333333 | Q4: =_xlfn.CONCAT(H4,I4,J4) -> LIGRFOCOM
B5: BC BomSucesso | C5: ABB_02 | D5: 45992.729 | E5: 45992.729 | F5: 45992.833 | G5: 0.10416667 | H5: LIG | I5: RFO | J5: COM | K5: Comunicação | L5: Foi identificada falha de comunicação que afetou simultaneamente os inversores e o sistema de CFTV da usina. | M5: Falha Comunicação | N5: Prestador de Serviço O&M | O5: Realizado reset no modem de internet local. Após a reinicialização, a comunicação foi restabelecida. | P5: =_xlfn.CONCAT(B5,C5,D5,E5,F5) -> BC BomSucessoABB_0245992,729166666745992,729166666745992,8333333333 | Q5: =_xlfn.CONCAT(H5,I5,J5) -> LIGRFOCOM
B6: BC BomSucesso | C6: ABB_03 | D6: 45992.729 | E6: 45992.729 | F6: 45992.833 | G6: 0.10416667 | H6: LIG | I6: RFO | J6: COM | K6: Comunicação | L6: Foi identificada falha de comunicação que afetou simultaneamente os inversores e o sistema de CFTV da usina. | M6: Falha Comunicação | N6: Prestador de Serviço O&M | O6: Realizado reset no modem de internet local. Após a reinicialização, a comunicação foi restabelecida. | P6: =_xlfn.CONCAT(B6,C6,D6,E6,F6) -> BC BomSucessoABB_0345992,729166666745992,729166666745992,8333333333 | Q6: =_xlfn.CONCAT(H6,I6,J6) -> LIGRFOCOM
